Workbook

Sheet Shared Dashboard - April
B2: Particulars | C2: 45749 | F2: YTM - April-25 | J2: Particulars | K2: 45750 | N2: YTM - April-25 | R2: AIPL SALES DB | S2: 45751 | W2: YTM - April-25 | AB2: AIPL SALES DB | AC2: 45752 | AG2: YTM - April-25 | AL2: AIPL SALES DB | AM2: 45754 | AQ2: YTM - April-25 | AV2: AIPL SALES DB | AW2: 45755 | BA2: YTM - April-25 | BF2: AIPL SALES DB | BG2: 45756 | BK2: YTM - April-25 | BP2: AIPL SALES DB | BQ2: 45757 | BU2: YTM - April-25 | BZ2: AIPL SALES DB | CA2: 45758 | CE2: YTM - April-25 | CJ2: AIPL SALES DB | CK2: 45760 | CO2: YTM - April-25 | CT2: AIPL SALES DB | CU2: 45761 | CY2: YTM - April-25 | DD2: AIPL SALES DB | DE2: 45762 | DI2: YTM - April-25 | DN2: AIPL SALES DB | DO2: 45763 | DS2: YTM - April-25 | DX2: AIPL SALES DB | DY2: 45764 | EC2: YTM - April-25 | EH2: AIPL SALES DB | EI2: 45765 | EM2: YTM - April-25 | ER2: AIPL SALES DB | ES2: 45767 | EW2: YTM - April-25 | FB2: AIPL SALES DB | FC2: 45768 | FG2: YTM - April-25 | FL2: AIPL SALES DB | FM2: 45769 | FQ2: YTM - April-25 | FV2: AIPL SALES DB | FW2: 45770 | GA2: YTM - April-25 | GF2: AIPL SALES DB | GG2: 45771 | GL2: YTM - April-25 | GR2: AIPL SALES DB | GS2: 45772 | GX2: YTM - April-25 | HD2: AIPL SALES DB | HE2: 45774 | HJ2: YTM - April-25 | HP2: AIPL SALES DB | HQ2: 45775 | HV2: YTM - April-25 | IB2: AIPL SALES DB | IC2: 45776 | IH2: YTM - April-25 | IN2: AIPL SALES DB | IO2: 45777 | IT2: YTM - April-25
B3: Product | C3: PCB-Ref | D3: PCB- CF | E3: Total | F3: PCB-Ref | G3: PCB- CF | H3: Total | J3: Product | K3: PCB - Ref | L3: PCB - CF | M3: Total | N3: PCB - Ref | O3: PCB - CF | P3: Total | R3: Product | S3: PCB - Ref | T3: PCB - CF | U3: Stator - CF | V3: Total | W3: PCB - Ref | X3: PCB - CF | Y3: Stator - CF | Z3: Total | AB3: Product | AC3: PCB - Ref | AD3: PCB - CF | AE3: Stator - CF | AF3: Total | AG3: PCB - Ref | AH3: PCB - CF | AI3: Stator - CF | AJ3: Total | AL3: Product | AM3: PCB - Ref | AN3: PCB - CF | AO3: Stator - CF | AP3: Total | AQ3: PCB - Ref | AR3: PCB - CF | AS3: Stator - CF | AT3: Total | AV3: Product | AW3: PCB - Ref | AX3: PCB - CF | AY3: Stator - CF | AZ3: Total | BA3: PCB - Ref | BB3: PCB - CF | BC3: Stator - CF | BD3: Total | BF3: Product | BG3: PCB - Ref | BH3: PCB - CF | BI3: Stator - CF | BJ3: Total | BK3: PCB - Ref | BL3: PCB - CF | BM3: Stator - CF | BN3: Total | BP3: Product | BQ3: PCB - Ref | BR3: PCB - CF | BS3: Stator - CF | BT3: Total | BU3: PCB - Ref | BV3: PCB - CF | BW3: Stator - CF | BX3: Total | BZ3: Product | CA3: PCB - Ref | CB3: PCB - CF | CC3: Stator - CF | CD3: Total | CE3: PCB - Ref | CF3: PCB - CF | CG3: Stator - CF | CH3: Total | CJ3: Product | CK3: PCB - Ref | CL3: PCB - CF | CM3: Stator - CF | CN3: Total | CO3: PCB - Ref | CP3: PCB - CF | CQ3: Stator - CF | CR3: Total | CT3: Product | CU3: PCB - Ref | CV3: PCB - CF | CW3: Stator - CF | CX3: Total | CY3: PCB - Ref | CZ3: PCB - CF | DA3: Stator - CF | DB3: Total | DD3: Product | DE3: PCB - Ref | DF3: PCB - CF | DG3: Stator - CF | DH3: Total | DI3: PCB - Ref | DJ3: PCB - CF | DK3: Stator - CF | DL3: Total | DN3: Product | DO3: PCB - Ref | DP3: PCB - CF | DQ3: Stator - CF | DR3: Total | DS3: PCB - Ref | DT3: PCB - CF | DU3: Stator - CF | DV3: Total | DX3: Product | DY3: PCB - Ref | DZ3: PCB - CF | EA3: Stator - CF | EB3: Total | EC3: PCB - Ref | ED3: PCB - CF | EE3: Stator - CF | EF3: Total | EH3: Product | EI3: PCB - Ref | EJ3: PCB - CF | EK3: Stator - CF | EL3: Total | EM3: PCB - Ref | EN3: PCB - CF | EO3: Stator - CF | EP3: Total | ER3: Product | ES3: PCB - Ref | ET3: PCB - CF | EU3: Stator - CF | EV3: Total | EW3: PCB - Ref | EX3: PCB - CF | EY3: Stator - CF | EZ3: Total | FB3: Product | FC3: PCB - Ref | FD3: PCB - CF | FE3: Stator - CF | FF3: Total | FG3: PCB - Ref | FH3: PCB - CF | FI3: Stator - CF | FJ3: Total | FL3: Product | FM3: PCB - Ref | FN3: PCB - CF | FO3: Stator - CF | FP3: Total | FQ3: PCB - Ref | FR3: PCB - CF | FS3: Stator - CF | FT3: Total | FV3: Product | FW3: PCB - Ref | FX3: PCB - CF | FY3: Stator - CF | FZ3: Total | GA3: PCB - Ref | GB3: PCB - CF | GC3: Stator - CF | GD3: Total | GF3: Product | GG3: PCB - Ref | GH3: PCB - CF | GI3: PCB - MG | GJ3: Stator - CF | GK3: Total | GL3: PCB - Ref | GM3: PCB - CF | GN3: PCB - MG | GO3: Stator - CF | GP3: Total | GR3: Product | GS3: PCB - Ref | GT3: PCB - CF | GU3: PCB - MG | GV3: Stator - CF | GW3: Total | GX3: PCB - Ref | GY3: PCB - CF | GZ3: PCB - MG | HA3: Stator - CF | HB3: Total | HD3: Product | HE3: PCB - Ref | HF3: PCB - CF | HG3: PCB - MG | HH3: Stator - CF | HI3: Total | HJ3: PCB - Ref | HK3: PCB - CF | HL3: PCB - MG | HM3: Stator - CF | HN3: Total | HP3: Product | HQ3: PCB - Ref | HR3: PCB - CF | HS3: PCB - MG | HT3: Stator - CF | HU3: Total | HV3: PCB - Ref | HW3: PCB - CF | HX3: PCB - MG | HY3: Stator - CF | HZ3: Total | IB3: Product | IC3: PCB - Ref | ID3: PCB - CF | IE3: PCB - MG | IF3: Stator - CF | IG3: Total | IH3: PCB - Ref | II3: PCB - CF | IJ3: PCB - MG | IK3: Stator - CF | IL3: Total | IN3: Product | IO3: PCB - Ref | IP3: PCB - CF | IQ3: PCB - MG | IR3: Stator - CF | IS3: Total | IT3: PCB - Ref | IU3: PCB - CF | IV3: PCB - MG | IW3: Stator - CF | IX3: Total
B4: Qty | C4: 500 | D4: 0 | E4: 500 | F4: 500 | G4: 0 | H4: 500 | J4: Qty | K4: 0 | L4: 50 | M4: 50 | N4: 500 | O4: 50 | P4: 550 | R4: Qty | S4: 463 | T4: 14930 | U4: 100 | V4: 15493 | W4: 963 | X4: 14980 | Y4: 100 | Z4: 16043 | AB4: Qty | AC4: 0 | AD4: 6720 | AE4: 0 | AF4: 6720 | AG4: 963 | AH4: 21700 | AI4: 100 | AJ4: 22763 | AL4: Qty | AM4: 0 | AN4: 7140 | AO4: 0 | AP4: 7140 | AQ4: 963 | AR4: 28840 | AS4: 100 | AT4: 29903 | AV4: Qty | AW4: 0 | AX4: 13930 | AY4: 0 | AZ4: 13930 | BA4: 963 | BB4: 42770 | BC4: 100 | BD4: 43833 | BF4: Qty | BG4: 3000 | BH4: 8450 | BI4: 0 | BJ4: 11450 | BK4: 3963 | BL4: 51220 | BM4: 100 | BN4: 55283 | BP4: Qty | BQ4: 0 | BR4: 0 | BS4: 453 | BT4: 453 | BU4: 3963 | BV4: 51220 | BW4: 553 | BX4: 55736 | BZ4: Qty | CA4: 5000 | CB4: 15960 | CC4: 0 | CD4: 20960 | CE4: 8963 | CF4: 67180 | CG4: 553 | CH4: 76696 | CJ4: Qty | CK4: 0 | CL4: 2660 | CM4: 0 | CN4: 2660 | CO4: 8963 | CP4: 69840 | CQ4: 553 | CR4: 79356 | CT4: Qty | CU4: 0 | CV4: 7140 | CW4: 0 | CX4: 7140 | CY4: 8963 | CZ4: 76980 | DA4: 553 | DB4: 86496 | DD4: Qty | DE4: 0 | DF4: 5040 | DG4: 0 | DH4: 5040 | DI4: 8963 | DJ4: 82020 | DK4: 553 | DL4: 91536 | DN4: Qty | DO4: 0 | DP4: 8400 | DQ4: 2240 | DR4: 10640 | DS4: 8963 | DT4: 90420 | DU4: 2793 | DV4: 102176 | DX4: Qty | DY4: 0 | DZ4: 8400 | EA4: 1760 | EB4: 10160 | EC4: 8963 | ED4: 98820 | EE4: 4553 | EF4: 112336 | EH4: Qty | EI4: 0 | EJ4: 7630 | EK4: 2716 | EL4: 10346 | EM4: 8963 | EN4: 106450 | EO4: 7269 | EP4: 122682 | ER4: Qty | ES4: 4000 | ET4: 6720 | EU4: 0 | EV4: 10720 | EW4: 13418 | EX4: 112715 | EY4: 7269 | EZ4: 133402 | FB4: Qty | FC4: 0 | FD4: 5040 | FE4: 2232 | FF4: 7272 | FG4: 13418 | FH4: 117755 | FI4: 9501 | FJ4: 140674 | FL4: Qty | FM4: 0 | FN4: 5880 | FO4: 3840 | FP4: 9720 | FQ4: 12963 | FR4: 124090 | FS4: 13341 | FT4: 150394 | FV4: Qty | FW4: 0 | FX4: 8470 | FY4: 3300 | FZ4: 11770 | GA4: 12963 | GB4: 132560 | GC4: 16641 | GD4: 162164 | GF4: Qty | GG4: 0 | GH4: 5040 | GI4: 900 | GJ4: 900 | GK4: 6840 | GL4: 12963 | GM4: 137600 | GN4: 900 | GO4: 17541 | GP4: 169004 | GR4: Qty | GS4: 3797 | GT4: 6720 | GU4: 1155 | GV4: 1200 | GW4: 12872 | GX4: 16760 | GY4: 144320 | GZ4: 2055 | HA4: 18741 | HB4: 181876 | HD4: Qty | HE4: 3000 | HF4: 7560 | HG4: 447 | HH4: 2870 | HI4: 13877 | HJ4: 19760 | HK4: 151880 | HL4: 2502 | HM4: 21611 | HN4: 195753 | HP4: Qty | HQ4: 0 | HR4: 12339 | HS4: 210 | HT4: 2907 | HU4: 15456 | HV4: 19760 | HW4: 164219 | HX4: 2712 | HY4: 24518 | HZ4: 211209 | IB4: Qty | IC4: 0 | ID4: 96 | IE4: 360 | IF4: 2540 | IG4: 2996 | IH4: 19760 | II4: 164315 | IJ4: 3072 | IK4: 27058 | IL4: 214205 | IN4: Qty | IO4: 0 | IP4: 8400 | IQ4: 175 | IR4: 2000 | IS4: 10575 | IT4: 19760 | IU4: 172715 | IV4: 3247 | IW4: 29058 | IX4: 224780
B5: Sales | C5: 369655 | D5: 0 | E5: 369655 | F5: 369655 | G5: 0 | H5: 369655 | J5: Sales | K5: 0 | L5: 23950 | M5: 23950 | N5: 369655 | O5: 23950 | P5: 393605 | R5: Sales | S5: 340911.53 | T5: 5628013.3 | U5: 18123.5 | V5: 5987048.4 | W5: 710566.53 | X5: 5651963.3 | Y5: 18123.5 | Z5: 6380653.4 | AB5: Sales | AC5: 0 | AD5: 2406297.6 | AE5: 0 | AF5: 2406297.6 | AG5: 710566.53 | AH5: 8058260.9 | AI5: 18123.5 | AJ5: 8786951 | AL5: Sales | AM5: 0 | AN5: 2542982.4 | AO5: 0 | AP5: 2542982.4 | AQ5: 710566.53 | AR5: 10601243 | AS5: 18123.5 | AT5: 11329933 | AV5: Sales | AW5: 0 | AX5: 4941988.8 | AY5: 0 | AZ5: 4941988.8 | BA5: 710566.53 | BB5: 15543232 | BC5: 18123.5 | BD5: 16271922 | BF5: Sales | BG5: 2208930 | BH5: 3009552 | BI5: 0 | BJ5: 5218482 | BK5: 2919496.5 | BL5: 18552784 | BM5: 18123.5 | BN5: 21490404 | BP5: Sales | BQ5: 0 | BR5: 0 | BS5: 94115.28 | BT5: 94115.28 | BU5: 2919496.5 | BV5: 18552784 | BW5: 112238.78 | BX5: 21584519 | BZ5: Sales | CA5: 3696550 | CB5: 5674233.6 | CC5: 0 | CD5: 9370783.6 | CE5: 6616046.5 | CF5: 24227018 | CG5: 112238.78 | CH5: 30955303 | CJ5: Sales | CK5: 0 | CL5: 947385.6 | CM5: 0 | CN5: 947385.6 | CO5: 6616046.5 | CP5: 25174403 | CQ5: 112238.78 | CR5: 31902689 | CT5: Sales | CU5: 0 | CV5: 2542982.4 | CW5: 0 | CX5: 2542982.4 | CY5: 6616046.5 | CZ5: 27717386 | DA5: 112238.78 | DB5: 34445671 | DD5: Sales | DE5: 0 | DF5: 1795046.4 | DG5: 0 | DH5: 1795046.4 | DI5: 6616046.5 | DJ5: 29512432 | DK5: 112238.78 | DL5: 36240717 | DN5: Sales | DO5: 0 | DP5: 3004646.4 | DQ5: 346550.4 | DR5: 3351196.8 | DS5: 6616046.5 | DT5: 32517079 | DU5: 458789.18 | DV5: 39591914 | DX5: Sales | DY5: 0 | DZ5: 2998195.2 | EA5: 272289.6 | EB5: 3270484.8 | EC5: 6616046.5 | ED5: 35515274 | EE5: 731078.78 | EF5: 42862399 | EH5: Sales | EI5: 0 | EJ5: 2715680.8 | EK5: 420192.36 | EL5: 3135873.2 | EM5: 6616046.5 | EN5: 38230955 | EO5: 1151271.1 | EP5: 45998272 | ER5: Sales | ES5: 2957240 | ET5: 2393395.2 | EU5: 0 | EV5: 5350635.2 | EW5: 9733519.3 | EX5: 40464117 | EY5: 1151271.1 | EZ5: 51348907 | FB5: Sales | FC5: 0 | FD5: 1795046.4 | FE5: 345312.72 | FF5: 2140359.1 | FG5: 9733519.3 | FH5: 42259163 | FI5: 1496583.9 | FJ5: 53489267 | FL5: Sales | FM5: 0 | FN5: 2110214.4 | FO5: 594086.4 | FP5: 2704300.8 | FQ5: 9573286.5 | FR5: 44529611 | FS5: 2090670.3 | FT5: 56193567 | FV5: Sales | FW5: 0 | FX5: 3024772.8 | FY5: 510543 | FZ5: 3535315.8 | GA5: 9573286.5 | GB5: 47554383 | GC5: 2601213.3 | GD5: 59728883 | GF5: Sales | GG5: 0 | GH5: 1795046.4 | GI5: 416650.5 | GJ5: 139239 | GK5: 2350935.9 | GL5: 9573286.5 | GM5: 49349430 | GN5: 416650.5 | GO5: 2740452.3 | GP5: 62079819 | GR5: Sales | GS5: 2795760.1 | GT5: 2393395.2 | GU5: 821733.15 | GV5: 185652 | GW5: 6196540.4 | GX5: 12369047 | GY5: 51742825 | GZ5: 1238383.6 | HA5: 2926104.3 | HB5: 68276359 | HD5: Sales | HE5: 2217930 | HF5: 2935044 | HG5: 293091.99 | HH5: 444017.7 | HI5: 5890083.7 | HJ5: 14586977 | HK5: 54677869 | HL5: 1531475.6 | HM5: 3370122 | HN5: 74166443 | HP5: Sales | HQ5: 0 | HR5: 4261132.8 | HS5: 64967.7 | HT5: 425710.32 | HU5: 4751810.8 | HV5: 14586977 | HW5: 58939002 | HX5: 1596443.3 | HY5: 3795832.3 | HZ5: 78918254 | IB5: Sales | IC5: 0 | ID5: 45984 | IE5: 111373.2 | IF5: 392963.4 | IG5: 550320.6 | IH5: 14586977 | II5: 58984986 | IJ5: 1707816.5 | IK5: 4188795.7 | IL5: 79468575 | IN5: Sales | IO5: 0 | IP5: 2971584 | IQ5: 54139.75 | IR5: 309420 | IS5: 3335143.8 | IT5: 14586977 | IU5: 61956570 | IV5: 1761956.3 | IW5: 4498215.7 | IX5: 82803718
B6: COGS | C6: 284150 | D6: 0 | E6: 284150 | F6: 284150 | G6: 0 | H6: 284150 | J6: COGS | K6: 0 | L6: 23124.5 | M6: 23124.5 | N6: 284150 | O6: 23124.5 | P6: 307274.5 | R6: COGS | S6: 263122.9 | T6: 5319618.5 | U6: 18522 | V6: 5601263.4 | W6: 547272.9 | X6: 5342743 | Y6: 18522 | Z6: 5908537.9 | AB6: COGS | AC6: 0 | AD6: 2265513.6 | AE6: 0 | AF6: 2265513.6 | AG6: 547272.9 | AH6: 7608256.6 | AI6: 18522 | AJ6: 8174051.5 | AL6: COGS | AM6: 0 | AN6: 2390551.8 | AO6: 0 | AP6: 2390551.8 | AQ6: 547272.9 | AR6: 9998808.4 | AS6: 18522 | AT6: 10564603 | AV6: COGS | AW6: 0 | AX6: 4651753.4 | AY6: 0 | AZ6: 4651753.4 | BA6: 547272.9 | BB6: 14650562 | BC6: 18522 | BD6: 15216357 | BF6: COGS | BG6: 1449630 | BH6: 2829271 | BI6: 0 | BJ6: 4278901 | BK6: 1996902.9 | BL6: 17479833 | BM6: 18522 | BN6: 19495258 | BP6: COGS | BQ6: 0 | BR6: 0 | BS6: 96339.51 | BT6: 96339.51 | BU6: 1996902.9 | BV6: 17479833 | BW6: 114861.51 | BX6: 19591597 | BZ6: COGS | CA6: 2416050 | CB6: 5338082.4 | CC6: 0 | CD6: 7754132.4 | CE6: 4412952.9 | CF6: 22817915 | CG6: 114861.51 | CH6: 27345730 | CJ6: COGS | CK6: 0 | CL6: 890541.4 | CM6: 0 | CN6: 890541.4 | CO6: 4412952.9 | CP6: 23708457 | CQ6: 114861.51 | CR6: 28236271 | CT6: COGS | CU6: 0 | CV6: 2390561.2 | CW6: 0 | CX6: 2390561.2 | CY6: 4412952.9 | CZ6: 26099018 | DA6: 114861.51 | DB6: 30626832 | DD6: COGS | DE6: 0 | DF6: 1687492.8 | DG6: 0 | DH6: 1687492.8 | DI6: 4412952.9 | DJ6: 27786511 | DK6: 114861.51 | DL6: 32314325 | DN6: COGS | DO6: 0 | DP6: 2828011.2 | DQ6: 353404.8 | DR6: 3181416 | DS6: 4412952.9 | DT6: 30614522 | DU6: 468266.31 | DV6: 35495741 | DX6: COGS | DY6: 0 | DZ6: 2820199.2 | EA6: 277675.2 | EB6: 3097874.4 | EC6: 4412952.9 | ED6: 33434721 | EE6: 745941.51 | EF6: 38593615 | EH6: COGS | EI6: 0 | EJ6: 2555618.1 | EK6: 428503.32 | EL6: 2984121.4 | EM6: 4412952.9 | EN6: 35990339 | EO6: 1174444.8 | EP6: 41577737 | ER6: COGS | ES6: 1932840 | ET6: 2249940 | EU6: 0 | EV6: 4182780 | EW6: 6499141.6 | EX6: 38086931 | EY6: 1174444.8 | EZ6: 45760517 | FB6: COGS | FC6: 0 | FD6: 1687492.8 | FE6: 352142.64 | FF6: 2039635.4 | FG6: 6499141.6 | FH6: 39774423 | FI6: 1526587.5 | FJ6: 47800152 | FL6: COGS | FM6: 0 | FN6: 2045013.6 | FO6: 605836.8 | FP6: 2650850.4 | FQ6: 6345792.9 | FR6: 41972786 | FS6: 2132424.3 | FT6: 50451003 | FV6: COGS | FW6: 0 | FX6: 2907121.7 | FY6: 520641 | FZ6: 3427762.7 | GA6: 6345792.9 | GB6: 44879907 | GC6: 2653065.3 | GD6: 53878765 | GF6: COGS | GG6: 0 | GH6: 1687492.8 | GI6: 441709.5 | GJ6: 141993 | GK6: 2271195.3 | GL6: 6345792.9 | GM6: 46567400 | GN6: 441709.5 | GO6: 2795058.3 | GP6: 56149961 | GR6: COGS | GS6: 1837647.6 | GT6: 2250032.4 | GU6: 770503.65 | GV6: 189324 | GW6: 5047507.7 | GX6: 8183440.5 | GY6: 48817432 | GZ6: 1212213.1 | HA6: 2984382.3 | HB6: 61197468 | HD6: COGS | HE6: 1449630 | HF6: 2824021.2 | HG6: 280508.01 | HH6: 452799.9 | HI6: 5006959.1 | HJ6: 9633070.5 | HK6: 51641454 | HL6: 1492721.2 | HM6: 3437182.2 | HN6: 66204428 | HP6: COGS | HQ6: 0 | HR6: 4000582.1 | HS6: 80184.3 | HT6: 433767.69 | HU6: 4514534.1 | HV6: 9630171.3 | HW6: 55642036 | HX6: 1572905.5 | HY6: 3870949.9 | HZ6: 70716062 | IB6: COGS | IC6: 0 | ID6: 44399.04 | IE6: 137458.8 | IF6: 400735.8 | IG6: 582593.64 | IH6: 9630171.3 | II6: 55686435 | IJ6: 1710364.3 | IK6: 4271685.7 | IL6: 71298656 | IN6: COGS | IO6: 0 | IP6: 2799417.6 | IQ6: 66820.25 | IR6: 315540 | IS6: 3181777.9 | IT6: 9630171.3 | IU6: 58485852 | IV6: 1777184.5 | IW6: 4587225.7 | IX6: 74480434
B7: BOM cost | C7: 255890 | D7: 0 | E7: 255890 | F7: 255890 | G7: 0 | H7: 255890 | J7: BOM cost | K7: 0 | L7: 20452.5 | M7: 20452.5 | N7: 255890 | O7: 20452.5 | P7: 276342.5 | R7: BOM cost | S7: 236954.14 | T7: 4521759.3 | U7: 16472 | V7: 4775185.4 | W7: 492844.14 | X7: 4542211.8 | Y7: 16472 | Z7: 5051527.9 | AB7: BOM cost | AC7: 0 | AD7: 1906396.8 | AE7: 0 | AF7: 1906396.8 | AG7: 492844.14 | AH7: 6448608.6 | AI7: 16472 | AJ7: 6957924.7 | AL7: BOM cost | AM7: 0 | AN7: 2008990.2 | AO7: 0 | AP7: 2008990.2 | AQ7: 492844.14 | AR7: 8457598.8 | AS7: 16472 | AT7: 8966914.9 | AV7: BOM cost | AW7: 0 | AX7: 3907334.2 | AY7: 0 | AZ7: 3907334.2 | BA7: 492844.14 | BB7: 12364933 | BC7: 16472 | BD7: 12874249 | BF7: BOM cost | BG7: 1280070 | BH7: 2377703 | BI7: 0 | BJ7: 3657773 | BK7: 1772914.1 | BL7: 14742636 | BM7: 16472 | BN7: 16532022 | BP7: BOM cost | BQ7: 0 | BR7: 0 | BS7: 87053.01 | BT7: 87053.01 | BU7: 1772914.1 | BV7: 14742636 | BW7: 103525.01 | BX7: 16619075 | BZ7: BOM cost | CA7: 2133450 | CB7: 4485180 | CC7: 0 | CD7: 6618630 | CE7: 3906364.1 | CF7: 19227816 | CG7: 103525.01 | CH7: 23237705 | CJ7: BOM cost | CK7: 0 | CL7: 748391 | CM7: 0 | CN7: 748391 | CO7: 3906364.1 | CP7: 19976207 | CQ7: 103525.01 | CR7: 23986096 | CT7: BOM cost | CU7: 0 | CV7: 2008999.6 | CW7: 0 | CX7: 2008999.6 | CY7: 3906364.1 | CZ7: 21985207 | DA7: 103525.01 | DB7: 25995096 | DD7: BOM cost | DE7: 0 | DF7: 1418155.2 | DG7: 0 | DH7: 1418155.2 | DI7: 3906364.1 | DJ7: 23403362 | DK7: 103525.01 | DL7: 27413251 | DN7: BOM cost | DO7: 0 | DP7: 2379115.2 | DQ7: 307484.8 | DR7: 2686600 | DS7: 3906364.1 | DT7: 25782477 | DU7: 411009.81 | DV7: 30099851 | DX7: BOM cost | DY7: 0 | DZ7: 2371303.2 | EA7: 241595.2 | EB7: 2612898.4 | EC7: 3906364.1 | ED7: 28153780 | EE7: 652605.01 | EF7: 32712749 | EH7: BOM cost | EI7: 0 | EJ7: 2147588.8 | EK7: 372825.32 | EL7: 2520414.1 | EM7: 3906364.1 | EN7: 30301369 | EO7: 1025430.3 | EP7: 35233164 | ER7: BOM cost | ES7: 1706760 | ET7: 1890823.2 | EU7: 0 | EV7: 3597583.2 | EW7: 5741875.5 | EX7: 32063441 | EY7: 1025430.3 | EZ7: 38830747 | FB7: BOM cost | FC7: 0 | FD7: 1418155.2 | FE7: 306386.64 | FF7: 1724541.8 | FG7: 5741875.5 | FH7: 33481596 | FI7: 1331817 | FJ7: 40555289 | FL7: BOM cost | FM7: 0 | FN7: 1685157.6 | FO7: 527116.8 | FP7: 2212274.4 | FQ7: 5613124.1 | FR7: 35295505 | FS7: 1858933.8 | FT7: 42767563 | FV7: BOM cost | FW7: 0 | FX7: 2408465.5 | FY7: 452991 | FZ7: 2861456.5 | GA7: 5613124.1 | GB7: 37703971 | GC7: 2311924.8 | GD7: 45629019 | GF7: BOM cost | GG7: 0 | GH7: 1418155.2 | GI7: 392071 | GJ7: 123543 | GK7: 1933769.2 | GL7: 5613124.1 | GM7: 39122126 | GN7: 392071 | GO7: 2435467.8 | GP7: 47562789 | GR7: BOM cost | GS7: 1620141.9 | GT7: 1890915.6 | GU7: 703597.65 | GV7: 164724 | GW7: 4379379.2 | GX7: 7233266.1 | GY7: 41013041 | GZ7: 1095668.6 | HA7: 2600191.8 | HB7: 51942168 | HD7: BOM cost | HE7: 1280070 | HF7: 2374906.8 | HG7: 254892.73 | HH7: 393964.9 | HI7: 4303834.4 | HJ7: 8513336.1 | HK7: 43387948 | HL7: 1350561.4 | HM7: 2994156.7 | HN7: 56246002 | HP7: BOM cost | HQ7: 0 | HR7: 3341186 | HS7: 68961.9 | HT7: 374174.19 | HU7: 3784322 | HV7: 8513336.1 | HW7: 46729134 | HX7: 1419523.3 | HY7: 3368330.9 | HZ7: 60030324 | IB7: BOM cost | IC7: 0 | ID7: 39268.8 | IE7: 118220.4 | IF7: 348665.8 | IG7: 506155 | IH7: 8513336.1 | II7: 46768403 | IJ7: 1537743.7 | IK7: 3716996.7 | IL7: 60536479 | IN7: BOM cost | IO7: 0 | IP7: 2350521.6 | IQ7: 57468.25 | IR7: 274540 | IS7: 2682529.9 | IT7: 8513336.1 | IU7: 49118924 | IV7: 1595211.9 | IW7: 3991536.7 | IX7: 63219009
B8: Labour Cost | C8: 20505 | D8: 0 | E8: 20505 | F8: 20505 | G8: 0 | H8: 20505 | J8: Labour Cost | K8: 0 | L8: 1936.5 | M8: 1936.5 | N8: 20505 | O8: 1936.5 | P8: 22441.5 | R8: Labour Cost | S8: 18987.63 | T8: 578238.9 | U8: 1243 | V8: 598469.53 | W8: 39492.63 | X8: 580175.4 | Y8: 1243 | Z8: 620911.03 | AB8: Labour Cost | AC8: 0 | AD8: 260265.6 | AE8: 0 | AF8: 260265.6 | AG8: 39492.63 | AH8: 840441 | AI8: 1243 | AJ8: 881176.63 | AL8: Labour Cost | AM8: 0 | AN8: 276532.2 | AO8: 0 | AP8: 276532.2 | AQ8: 39492.63 | AR8: 1116973.2 | AS8: 1243 | AT8: 1157708.8 | AV8: Labour Cost | AW8: 0 | AX8: 539508.9 | AY8: 0 | AZ8: 539508.9 | BA8: 39492.63 | BB8: 1656482.1 | BC8: 1243 | BD8: 1697217.7 | BF8: Labour Cost | BG8: 123030 | BH8: 327268.5 | BI8: 0 | BJ8: 450298.5 | BK8: 162522.63 | BL8: 1983750.6 | BM8: 1243 | BN8: 2147516.2 | BP8: Labour Cost | BQ8: 0 | BR8: 0 | BS8: 5630.79 | BT8: 5630.79 | BU8: 162522.63 | BV8: 1983750.6 | BW8: 6873.79 | BX8: 2153147 | BZ8: Labour Cost | CA8: 205050 | CB8: 618130.8 | CC8: 0 | CD8: 823180.8 | CE8: 367572.63 | CF8: 2601881.4 | CG8: 6873.79 | CH8: 2976327.8 | CJ8: Labour Cost | CK8: 0 | CL8: 103021.8 | CM8: 0 | CN8: 103021.8 | CO8: 367572.63 | CP8: 2704903.2 | CQ8: 6873.79 | CR8: 3079349.6 | CT8: Labour Cost | CU8: 0 | CV8: 276532.2 | CW8: 0 | CX8: 276532.2 | CY8: 367572.63 | CZ8: 2981435.4 | DA8: 6873.79 | DB8: 3355881.8 | DD8: Labour Cost | DE8: 0 | DF8: 195199.2 | DG8: 0 | DH8: 195199.2 | DI8: 367572.63 | DJ8: 3176634.6 | DK8: 6873.79 | DL8: 3551081 | DN8: Labour Cost | DO8: 0 | DP8: 325332 | DQ8: 27843.2 | DR8: 353175.2 | DS8: 367572.63 | DT8: 3501966.6 | DU8: 34716.99 | DV8: 3904256.2 | DX8: Labour Cost | DY8: 0 | DZ8: 325332 | EA8: 21876.8 | EB8: 347208.8 | EC8: 367572.63 | ED8: 3827298.6 | EE8: 56593.79 | EF8: 4251465 | EH8: Labour Cost | EI8: 0 | EJ8: 295719.2 | EK8: 33759.88 | EL8: 329479.08 | EM8: 367572.63 | EN8: 4123017.8 | EO8: 90353.67 | EP8: 4580944.1 | ER8: Labour Cost | ES8: 164040 | ET8: 260265.6 | EU8: 0 | EV8: 424305.6 | EW8: 549444.08 | EX8: 4365452 | EY8: 90353.67 | EZ8: 5005249.7 | FB8: Labour Cost | FC8: 0 | FD8: 195199.2 | FE8: 27743.76 | FF8: 222942.96 | FG8: 549444.08 | FH8: 4560651.2 | FI8: 118097.43 | FJ8: 5228192.7 | FL8: Labour Cost | FM8: 0 | FN8: 259039.2 | FO8: 47731.2 | FP8: 306770.4 | FQ8: 531612.63 | FR8: 4837521.8 | FS8: 165828.63 | FT8: 5534963.1 | FV8: Labour Cost | FW8: 0 | FX8: 359639.7 | FY8: 41019 | FZ8: 400658.7 | GA8: 531612.63 | GB8: 5197161.5 | GC8: 206847.63 | GD8: 5935621.8 | GF8: Labour Cost | GG8: 0 | GH8: 195199.2 | GI8: 35994.5 | GJ8: 11187 | GK8: 242380.7 | GL8: 531612.63 | GM8: 5392360.7 | GN8: 35994.5 | GO8: 218034.63 | GP8: 6178002.5 | GR8: Labour Cost | GS8: 155714.97 | GT8: 260265.6 | GU8: 48555.15 | GV8: 14916 | GW8: 479451.72 | GX8: 687327.6 | GY8: 5652626.3 | GZ8: 84549.65 | HA8: 232950.63 | HB8: 6657454.2 | HD8: Labour Cost | HE8: 123030 | HF8: 323719.2 | HG8: 18586.31 | HH8: 35674.1 | HI8: 501009.61 | HJ8: 810357.6 | HK8: 5976345.5 | HL8: 103135.96 | HM8: 268624.73 | HN8: 7158463.8 | HP8: Labour Cost | HQ8: 0 | HR8: 477889.47 | HS8: 8133.3 | HT8: 36134.01 | HU8: 522156.78 | HV8: 810357.6 | HW8: 6454235 | HX8: 111269.26 | HY8: 304758.74 | HZ8: 7680620.6 | IB8: Labour Cost | IC8: 0 | ID8: 3718.08 | IE8: 13942.8 | IF8: 31572.2 | IG8: 49233.08 | IH8: 810357.6 | II8: 6457953.1 | IJ8: 125212.06 | IK8: 336330.94 | IL8: 7729853.7 | IN8: Labour Cost | IO8: 0 | IP8: 325332 | IQ8: 6777.75 | IR8: 24860 | IS8: 356969.75 | IT8: 810357.6 | IU8: 6783285 | IV8: 131989.81 | IW8: 361190.94 | IX8: 8086823.4
B9: Other Conv Cost | C9: 7760 | D9: 0 | E9: 7760 | F9: 7760 | G9: 0 | H9: 7760 | J9: Other Conv Cost | K9: 0 | L9: 735.5 | M9: 735.5 | N9: 7760 | O9: 735.5 | P9: 8495.5 | R9: Other Conv Cost | S9: 7185.76 | T9: 219620.3 | U9: 807 | V9: 227613.06 | W9: 14945.76 | X9: 220355.8 | Y9: 807 | Z9: 236108.56 | AB9: Other Conv Cost | AC9: 0 | AD9: 98851.2 | AE9: 0 | AF9: 98851.2 | AG9: 14945.76 | AH9: 319207 | AI9: 807 | AJ9: 334959.76 | AL9: Other Conv Cost | AM9: 0 | AN9: 105029.4 | AO9: 0 | AP9: 105029.4 | AQ9: 14945.76 | AR9: 424236.4 | AS9: 807 | AT9: 439989.16 | AV9: Other Conv Cost | AW9: 0 | AX9: 204910.3 | AY9: 0 | AZ9: 204910.3 | BA9: 14945.76 | BB9: 629146.7 | BC9: 807 | BD9: 644899.46 | BF9: Other Conv Cost | BG9: 46560 | BH9: 124299.5 | BI9: 0 | BJ9: 170859.5 | BK9: 61505.76 | BL9: 753446.2 | BM9: 807 | BN9: 815758.96 | BP9: Other Conv Cost | BQ9: 0 | BR9: 0 | BS9: 3655.71 | BT9: 3655.71 | BU9: 61505.76 | BV9: 753446.2 | BW9: 4462.71 | BX9: 819414.67 | BZ9: Other Conv Cost | CA9: 77600 | CB9: 234771.6 | CC9: 0 | CD9: 312371.6 | CE9: 139105.76 | CF9: 988217.8 | CG9: 4462.71 | CH9: 1131786.3 | CJ9: Other Conv Cost | CK9: 0 | CL9: 39128.6 | CM9: 0 | CN9: 39128.6 | CO9: 139105.76 | CP9: 1027346.4 | CQ9: 4462.71 | CR9: 1170914.9 | CT9: Other Conv Cost | CU9: 0 | CV9: 105029.4 | CW9: 0 | CX9: 105029.4 | CY9: 139105.76 | CZ9: 1132375.8 | DA9: 4462.71 | DB9: 1275944.3 | DD9: Other Conv Cost | DE9: 0 | DF9: 74138.4 | DG9: 0 | DH9: 74138.4 | DI9: 139105.76 | DJ9: 1206514.2 | DK9: 4462.71 | DL9: 1350082.7 | DN9: Other Conv Cost | DO9: 0 | DP9: 123564 | DQ9: 18076.8 | DR9: 141640.8 | DS9: 139105.76 | DT9: 1330078.2 | DU9: 22539.51 | DV9: 1491723.5 | DX9: Other Conv Cost | DY9: 0 | DZ9: 123564 | EA9: 14203.2 | EB9: 137767.2 | EC9: 139105.76 | ED9: 1453642.2 | EE9: 36742.71 | EF9: 1629490.7 | EH9: Other Conv Cost | EI9: 0 | EJ9: 112310.1 | EK9: 21918.12 | EL9: 134228.22 | EM9: 139105.76 | EN9: 1565952.3 | EO9: 58660.83 | EP9: 1763718.9 | ER9: Other Conv Cost | ES9: 62080 | ET9: 98851.2 | EU9: 0 | EV9: 160931.2 | EW9: 207951.61 | EX9: 1658037.7 | EY9: 58660.83 | EZ9: 1924650.1 | FB9: Other Conv Cost | FC9: 0 | FD9: 74138.4 | FE9: 18012.24 | FF9: 92150.64 | FG9: 207951.61 | FH9: 1732176.1 | FI9: 76673.07 | FJ9: 2016800.7 | FL9: Other Conv Cost | FM9: 0 | FN9: 100816.8 | FO9: 30988.8 | FP9: 131805.6 | FQ9: 201185.76 | FR9: 1839758.7 | FS9: 107661.87 | FT9: 2148606.3 | FV9: Other Conv Cost | FW9: 0 | FX9: 139016.5 | FY9: 26631 | FZ9: 165647.5 | GA9: 201185.76 | GB9: 1978775.2 | GC9: 134292.87 | GD9: 2314253.8 | GF9: Other Conv Cost | GG9: 0 | GH9: 74138.4 | GI9: 13644 | GJ9: 7263 | GK9: 95045.4 | GL9: 201185.76 | GM9: 2052913.6 | GN9: 13644 | GO9: 141555.87 | GP9: 2409299.2 | GR9: Other Conv Cost | GS9: 58929.44 | GT9: 98851.2 | GU9: 18350.85 | GV9: 9684 | GW9: 185815.49 | GX9: 260115.2 | GY9: 2151764.8 | GZ9: 31994.85 | HA9: 151239.87 | HB9: 2595114.7 | HD9: Other Conv Cost | HE9: 46560 | HF9: 125395.2 | HG9: 7028.97 | HH9: 23160.9 | HI9: 202145.07 | HJ9: 306675.2 | HK9: 2277160 | HL9: 39023.82 | HM9: 174400.77 | HN9: 2797259.8 | HP9: Other Conv Cost | HQ9: 0 | HR9: 181506.69 | HS9: 3089.1 | HT9: 23459.49 | HU9: 208055.28 | HV9: 306675.2 | HW9: 2458666.7 | HX9: 42112.92 | HY9: 197860.26 | HZ9: 3005315.1 | IB9: Other Conv Cost | IC9: 0 | ID9: 1412.16 | IE9: 5295.6 | IF9: 20497.8 | IG9: 27205.56 | IH9: 306675.2 | II9: 2460078.9 | IJ9: 47408.52 | IK9: 218358.06 | IL9: 3032520.6 | IN9: Other Conv Cost | IO9: 0 | IP9: 123564 | IQ9: 2574.25 | IR9: 16140 | IS9: 142278.25 | IT9: 306675.2 | IU9: 2583642.9 | IV9: 49982.77 | IW9: 234498.06 | IX9: 3174798.9
B10: Margin | C10: 85505 | E10: 85505 | F10: 85505 | H10: 85505 | J10: Margin | K10: 0 | L10: 825.5 | M10: 825.5 | N10: 85505 | O10: 825.5 | P10: 86330.5 | R10: Margin | S10: 77788.63 | T10: 308394.85 | U10: -398.5 | V10: 385784.98 | W10: 163293.63 | X10: 309220.35 | Y10: -398.5 | Z10: 472115.48 | AB10: Margin | AC10: 0 | AD10: 140784 | AE10: 0 | AF10: 140784 | AG10: 163293.63 | AH10: 450004.35 | AI10: -398.5 | AJ10: 612899.48 | AL10: Margin | AM10: 0 | AN10: 152430.6 | AO10: 0 | AP10: 152430.6 | AQ10: 163293.63 | AR10: 602434.95 | AS10: -398.5 | AT10: 765330.08 | AV10: Margin | AW10: 0 | AX10: 290235.4 | AY10: 0 | AZ10: 290235.4 | BA10: 163293.63 | BB10: 892670.35 | BC10: -398.5 | BD10: 1055565.5 | BF10: Margin | BG10: 759300 | BH10: 180281 | BI10: 0 | BJ10: 939581 | BK10: 922593.63 | BL10: 1072951.3 | BM10: -398.5 | BN10: 1995146.5 | BP10: Margin | BQ10: 0 | BR10: 0 | BS10: -2224.23 | BT10: -2224.23 | BU10: 922593.63 | BV10: 1072951.3 | BW10: -2622.73 | BX10: 1992922.2 | BZ10: Margin | CA10: 1280500 | CB10: 336151.2 | CC10: 0 | CD10: 1616651.2 | CE10: 2203093.6 | CF10: 1409102.6 | CG10: -2622.73 | CH10: 3609573.5 | CJ10: Margin | CK10: 0 | CL10: 56844.2 | CM10: 0 | CN10: 56844.2 | CO10: 2203093.6 | CP10: 1465946.8 | CQ10: -2622.73 | CR10: 3666417.6 | CT10: Margin | CU10: 0 | CV10: 152421.15 | CW10: 0 | CX10: 152421.15 | CY10: 2203093.6 | CZ10: 1618367.9 | DA10: -2622.73 | DB10: 3818838.8 | DD10: Margin | DE10: 0 | DF10: 107553.6 | DG10: 0 | DH10: 107553.6 | DI10: 2203093.6 | DJ10: 1725921.5 | DK10: -2622.73 | DL10: 3926392.4 | DN10: Margin | DO10: 0 | DP10: 176635.2 | DQ10: -6854.4 | DR10: 169780.8 | DS10: 2203093.6 | DT10: 1902556.7 | DU10: -9477.13 | DV10: 4096173.2 | DX10: Margin | DY10: 0 | DZ10: 177996 | EA10: -5385.6 | EB10: 172610.4 | EC10: 2203093.6 | ED10: 2080552.7 | EE10: -14862.73 | EF10: 4268783.6 | EH10: Margin | EI10: 0 | EJ10: 160062.7 | EK10: -8310.96 | EL10: 151751.74 | EM10: 2203093.6 | EN10: 2240615.4 | EO10: -23173.69 | EP10: 4420535.3 | ER10: Margin | ES10: 1024400 | ET10: 143455.2 | EU10: 0 | EV10: 1167855.2 | EW10: 3234377.8 | EX10: 2377186.4 | EY10: -23173.69 | EZ10: 5588390.5 | FB10: Margin | FC10: 0 | FD10: 107553.6 | FE10: -6829.92 | FF10: 100723.68 | FG10: 3234377.8 | FH10: 2484740 | FI10: -30003.61 | FJ10: 5689114.2 | FL10: Margin | FM10: 0 | FN10: 65200.8 | FO10: -11750.4 | FP10: 53450.4 | FQ10: 3227493.6 | FR10: 2556825 | FS10: -41754.01 | FT10: 5742564.6 | FV10: Margin | FW10: 0 | FX10: 117651.1 | FY10: -10098 | FZ10: 107553.1 | GA10: 3227493.6 | GB10: 2674476.1 | GC10: -51852.01 | GD10: 5850117.7 | GF10: Margin | GG10: 0 | GH10: 107553.6 | GI10: -25059 | GJ10: -2754 | GK10: 79740.6 | GL10: 3227493.6 | GM10: 2782029.7 | GN10: -25059 | GO10: -54606.01 | GP10: 5929858.3 | GR10: Margin | GS10: 958112.44 | GT10: 143362.8 | GU10: 51229.5 | GV10: -3672 | GW10: 1149032.7 | GX10: 4185606.1 | GY10: 2925392.5 | GZ10: 26170.5 | HA10: -58278.01 | HB10: 7078891.1 | HD10: Margin | HE10: 768300 | HF10: 111022.8 | HG10: 12583.98 | HH10: -8782.2 | HI10: 883124.58 | HJ10: 4953906.1 | HK10: 3036415.3 | HL10: 38754.48 | HM10: -67060.21 | HN10: 7962015.6 | HP10: Margin | HQ10: 0 | HR10: 260550.69 | HS10: -15216.6 | HT10: -8057.37 | HU10: 237276.72 | HV10: 4956805.3 | HW10: 3296966 | HX10: 23537.88 | HY10: -75117.58 | HZ10: 8202191.6 | IB10: Margin | IC10: 0 | ID10: 1584.96 | IE10: -26085.6 | IF10: -7772.4 | IG10: -32273.04 | IH10: 4956805.3 | II10: 3298550.9 | IJ10: -2547.72 | IK10: -82889.98 | IL10: 8169918.6 | IN10: Margin | IO10: 0 | IP10: 172166.4 | IQ10: -12680.5 | IR10: -6120 | IS10: 153365.9 | IT10: 4956805.3 | IU10: 3470717.3 | IV10: -15228.22 | IW10: -89009.98 | IX10: 8323284.5
B11: Margin % | C11: 0.23131028 | E11: 0.23131028 | F11: 0.23131028 | H11: 0.23131028 | J11: Margin % | L11: 0.034467641 | M11: 0.034467641 | N11: 0.23131028 | O11: 0.034467641 | P11: 0.21933283 | R11: Margin % | S11: 0.22817835 | T11: 0.054796396 | U11: -0.021988027 | V11: 0.06443659 | W11: 0.22980766 | X11: 0.054710254 | Y11: -0.021988027 | Z11: 0.073991714 | AB11: Margin % | AD11: 0.058506479 | AF11: 0.058506479 | AG11: 0.22980766 | AH11: 0.055843854 | AI11: -0.021988027 | AJ11: 0.069751098 | AL11: Margin % | AN11: 0.059941665 | AP11: 0.059941665 | AQ11: 0.22980766 | AR11: 0.05682682 | AS11: -0.021988027 | AT11: 0.067549389 | AV11: Margin % | AX11: 0.058728462 | AZ11: 0.058728462 | BA11: 0.22980766 | BB11: 0.057431449 | BC11: -0.021988027 | BD11: 0.064870362 | BF11: Margin % | BG11: 0.34374109 | BH11: 0.059902936 | BJ11: 0.18004872 | BK11: 0.31601121 | BL11: 0.057832363 | BM11: -0.021988027 | BN11: 0.092838946 | BP11: Margin % | BS11: -0.023633038 | BT11: -0.023633038 | BU11: 0.31601121 | BV11: 0.057832363 | BW11: -0.023367414 | BX11: 0.092331092 | BZ11: Margin % | CA11: 0.34640408 | CB11: 0.059241692 | CD11: 0.17252039 | CE11: 0.33299246 | CF11: 0.058162443 | CG11: -0.023367414 | CH11: 0.11660598 | CJ11: Margin % | CL11: 0.060001123 | CN11: 0.060001123 | CO11: 0.33299246 | CP11: 0.058231638 | CQ11: -0.023367414 | CR11: 0.11076908 | CT11: Margin % | CV11: 0.059937949 | CX11: 0.059937949 | CY11: 0.33299246 | CZ11: 0.058388187 | DA11: -0.023367414 | DB11: 0.10701817 | DD11: Margin % | DF11: 0.059916891 | DH11: 0.059916891 | DI11: 0.33299246 | DJ11: 0.058481168 | DK11: -0.023367414 | DL11: 0.10468621 | DN11: Margin % | DP11: 0.05878735 | DQ11: -0.019778941 | DR11: 0.050662736 | DS11: 0.33299246 | DT11: 0.05850946 | DU11: -0.02065683 | DV11: 0.10011532 | DX11: Margin % | DZ11: 0.059367716 | EA11: -0.019778941 | EB11: 0.05277823 | EC11: 0.33299246 | ED11: 0.058581914 | EE11: -0.020329861 | EF11: 0.096504751 | EH11: Margin % | EJ11: 0.058940174 | EK11: -0.019778941 | EL11: 0.048392181 | EM11: 0.33299246 | EN11: 0.058607362 | EO11: -0.020128786 | EP11: 0.093225876 | ER11: Margin % | ES11: 0.34640408 | ET11: 0.059937949 | EV11: 0.21826478 | EW11: 0.33229274 | EX11: 0.058748013 | EY11: -0.020128786 | EZ11: 0.10625107 | FB11: Margin % | FD11: 0.059916891 | FE11: -0.019778941 | FF11: 0.047059243 | FG11: 0.33229274 | FH11: 0.058797663 | FI11: -0.020048065 | FJ11: 0.10388323 | FL11: Margin % | FN11: 0.030897714 | FO11: -0.019778941 | FP11: 0.025854109 | FQ11: 0.33713538 | FR11: 0.057418535 | FS11: -0.01997159 | FT11: 0.099845417 | FV11: Margin % | FX11: 0.038895847 | FY11: -0.019778941 | FZ11: 0.02812675 | GA11: 0.33713538 | GB11: 0.05624037 | GC11: -0.019933779 | GD11: 0.09558202 | GF11: Margin % | GH11: 0.059916891 | GI11: -0.060143934 | GJ11: -0.019778941 | GK11: 0.030861718 | GL11: 0.33713538 | GM11: 0.0563741 | GN11: -0.060143934 | GO11: -0.019925912 | GP11: 0.095519903 | GR11: Margin % | GS11: 0.34270195 | GT11: 0.059899343 | GU11: 0.062343231 | GV11: -0.019778941 | GW11: 0.18543133 | GX11: 0.33839359 | GY11: 0.056537162 | GZ11: 0.021132789 | HA11: -0.019916587 | HB11: 0.10367997 | HD11: Margin % | HE11: 0.34640408 | HF11: 0.037826622 | HG11: 0.042935257 | HH11: -0.019778941 | HI11: 0.14993413 | HJ11: 0.33961157 | HK11: 0.055532803 | HL11: 0.025305319 | HM11: -0.019898452 | HN11: 0.10735334 | HP11: Margin % | HR11: 0.061145874 | HS11: -0.23421793 | HT11: -0.018926884 | HU11: 0.049933958 | HV11: 0.33981033 | HW11: 0.055938613 | HX11: 0.01474395 | HY11: -0.019789489 | HZ11: 0.10393276 | IB11: Margin % | ID11: 0.034467641 | IE11: -0.23421793 | IF11: -0.019778941 | IG11: -0.05864407 | IH11: 0.33981033 | II11: 0.055921874 | IJ11: -0.0014917996 | IK11: -0.019788499 | IL11: 0.10280691 | IN11: Margin % | IP11: 0.057937585 | IQ11: -0.23421793 | IR11: -0.019778941 | IS11: 0.045984795 | IT11: 0.33981033 | IU11: 0.056018552 | IV11: -0.008642791 | IW11: -0.019787842 | IX11: 0.10051825
AB12: Rent & White Collar employees Salary doesn't form part of Other Conversion Cost | AL12: Rent & White Collar employees Salary doesn't form part of Other Conversion Cost | AV12: Rent & White Collar employees Salary doesn't form part of Other Conversion Cost | BF12: Rent & White Collar employees Salary doesn't form part of Other Conversion Cost | BP12: Rent & White Collar employees Salary doesn't form part of Other Conversion Cost | BZ12: Rent & White Collar employees Salary doesn't form part of Other Conversion Cost Sales of NPI not included | CJ12: Rent & White Collar employees Salary doesn't form part of Other Conversion Cost Sales of NPI not included | CT12: Rent & White Collar employees Salary doesn't form part of Other Conversion Cost Sales of NPI not included | DD12: Rent & White Collar employees Salary doesn't form part of Other Conversion Cost Sales of NPI not included | DN12: Rent & White Collar employees Salary doesn't form part of Other Conversion Cost Sales of NPI not included | DX12: Rent & White Collar employees Salary doesn't form part of Other Conversion Cost Sales of NPI not included | EH12: Rent & White Collar employees Salary doesn't form part of Other Conversion Cost Sales of NPI not included | ER12: Rent & White Collar employees Salary doesn't form part of Other Conversion Cost Sales of NPI not included | FB12: Rent & White Collar employees Salary doesn't form part of Other Conversion Cost Sales of NPI not included | FL12: Rent & White Collar employees Salary doesn't form part of Other Conversion Cost Sales of NPI not included | FV12: Rent & White Collar employees Salary doesn't form part of Other Conversion Cost Sales of NPI not included | GF12: Rent & White Collar employees Salary doesn't form part of Other Conversion Cost Sales of NPI not included | GR12: Rent & White Collar employees Salary doesn't form part of Other Conversion Cost Sales of NPI not included | HD12: Rent & White Collar employees Salary doesn't form part of Other Conversion Cost Sales of NPI not included | HP12: Rent & White Collar employees Salary doesn't form part of Other Conversion Cost Sales of NPI not included | IB12: Rent & White Collar employees Salary doesn't form part of Other Conversion Cost Sales of NPI not included | IN12: Rent & White Collar employees Salary doesn't form part of Other Conversion Cost Sales of NPI not included
IN14: ASP | IO14: =IO5/IO$4 -> #DIV/0! | IP14: =IP5/IP$4 -> 353.76 | IQ14: =IQ5/IQ$4 -> 309.37 | IR14: =IR5/IR$4 -> 154.71 | IS14: =IS5/IS$4 -> 315.38002 | IT14: =IT5/IT$4 -> 738.20732 | IU14: =IU5/IU$4 -> 358.72142 | IV14: =IV5/IV$4 -> 542.6413 | ... IX14: =IX5/IX$4 -> 368.37672
IN15: PGI pu | IO15: =IO6/IO$4 -> #DIV/0! | IP15: =IP6/IP$4 -> 333.264 | IQ15: =IQ6/IQ$4 -> 381.83 | IR15: =IR6/IR$4 -> 157.77 | IS15: =IS6/IS$4 -> 300.87734 | IT15: =IT6/IT$4 -> 487.35685 | IU15: =IU6/IU$4 -> 338.62636 | IV15: =IV6/IV$4 -> 547.33123 | ... IX15: =IX6/IX$4 -> 331.34814
IN16: GM pu | IO16: =IO14-IO15 -> #DIV/0! | IP16: =IP14-IP15 -> 20.496 | IQ16: =IQ14-IQ15 -> -72.46 | IR16: =IR14-IR15 -> -3.06 | IS16: =IS14-IS15 -> 14.502686 | IT16: =IT14-IT15 -> 250.85047 | IU16: =IU14-IU15 -> 20.095055 | IV16: =IV14-IV15 -> -4.6899353 | IW16: =IW14-IW15 -> -3.0631833 | IX16: =IX7/IX$4 -> 281.24837
IN17: BOM pu | IO17: =IO7/IO4 -> #DIV/0! | IP17: =IP7/IP4 -> 279.824 | IQ17: =IQ7/IQ4 -> 328.39 | IR17: =IR7/IR4 -> 137.27 | IS17: =IS7/IS4 -> 253.66713 | IT17: =IT7/IT4 -> 430.83685 | IU17: =IU7/IU4 -> 284.39293 | IV17: =IV7/IV4 -> 491.28794 | ... IX17: =IX7/IX4 -> 281.24837

Sheet Shared Dashboard - May
B2: AIPL SALES DB | C2: 45781 | H2: YTM - May-25 | N2: AIPL SALES DB | O2: 45782 | T2: YTM - May-25 | Z2: AIPL SALES DB | AA2: 45783 | AF2: YTM - May-25 | AL2: AIPL SALES DB | AM2: 45784 | AR2: YTM - May-25 | AX2: AIPL SALES DB | AY2: 45785 | BD2: YTM - May-25 | BJ2: AIPL SALES DB | BK2: 45786 | BP2: YTM - May-25 | BV2: AIPL SALES DB | BW2: 45788 | CB2: YTM - May-25 | CH2: AIPL SALES DB | CI2: 45789 | CN2: YTM - May-25 | CT2: AIPL SALES DB | CU2: 45790 | CZ2: YTM - May-25 | DF2: AIPL SALES DB | DG2: 45791 | DL2: YTM - May-25 | DR2: AIPL SALES DB | DS2: 45792 | DX2: YTM - May-25 | ED2: AIPL SALES DB | EE2: 45793 | EJ2: YTM - May-25 | EP2: AIPL SALES DB | EQ2: 45795 | EV2: YTM - May-25 | FB2: AIPL SALES DB | FC2: 45796 | FH2: YTM - May-25 | FN2: AIPL SALES DB | FO2: 45797 | FT2: YTM - May-25 | FZ2: AIPL SALES DB | GA2: 45798 | GG2: YTM - May-25 | GN2: AIPL SALES DB | GO2: 45799 | GU2: YTM - May-25 | HB2: AIPL SALES DB | HC2: 45800 | HI2: YTM - May-25 | HP2: AIPL SALES DB | HQ2: 45802 | HW2: YTM - May-25 | ID2: AIPL SALES DB | IE2: 45803 | IK2: YTM - May-25 | IR2: AIPL SALES DB | IS2: 45804 | IY2: YTM - May-25 | JF2: AIPL SALES DB | JG2: 45805 | JM2: YTM - May-25 | JT2: AIPL SALES DB | JU2: 45806 | KA2: YTM - May-25 | KH2: AIPL SALES DB | KI2: 45807 | KO2: YTM - May-25
B3: Product | C3: PCB - Ref | D3: PCB - CF | E3: PCB - MG | F3: Stator - CF | G3: Total | H3: PCB - Ref | I3: PCB - CF | J3: PCB - MG | K3: Stator - CF | L3: Total | N3: Product | O3: PCB - Ref | P3: PCB - CF | Q3: PCB - MG | R3: Stator - CF | S3: Total | T3: PCB - Ref | U3: PCB - CF | V3: PCB - MG | W3: Stator - CF | X3: Total | Z3: Product | AA3: PCB - Ref | AB3: PCB - CF | AC3: PCB - MG | AD3: Stator - CF | AE3: Total | AF3: PCB - Ref | AG3: PCB - CF | AH3: PCB - MG | AI3: Stator - CF | AJ3: Total | AL3: Product | AM3: PCB - Ref | AN3: PCB - CF | AO3: PCB - MG | AP3: Stator - CF | AQ3: Total | AR3: PCB - Ref | AS3: PCB - CF | AT3: PCB - MG | AU3: Stator - CF | AV3: Total | AX3: Product | AY3: PCB - Ref | AZ3: PCB - CF | BA3: PCB - MG | BB3: Stator - CF | BC3: Total | BD3: PCB - Ref | BE3: PCB - CF | BF3: PCB - MG | BG3: Stator - CF | BH3: Total | BJ3: Product | BK3: PCB - Ref | BL3: PCB - CF | BM3: PCB - MG | BN3: Stator - CF | BO3: Total | BP3: PCB - Ref | BQ3: PCB - CF | BR3: PCB - MG | BS3: Stator - CF | BT3: Total | BV3: Product | BW3: PCB - Ref | BX3: PCB - CF | BY3: PCB - MG | BZ3: Stator - CF | CA3: Total | CB3: PCB - Ref | CC3: PCB - CF | CD3: PCB - MG | CE3: Stator - CF | CF3: Total | CH3: Product | CI3: PCB - Ref | CJ3: PCB - CF | CK3: PCB - MG | CL3: Stator - CF | CM3: Total | CN3: PCB - Ref | CO3: PCB - CF | CP3: PCB - MG | CQ3: Stator - CF | CR3: Total | CT3: Product | CU3: PCB - Ref | CV3: PCB - CF | CW3: PCB - MG | CX3: Stator - CF | CY3: Total | CZ3: PCB - Ref | DA3: PCB - CF | DB3: PCB - MG | DC3: Stator - CF | DD3: Total | DF3: Product | DG3: PCB - Ref | DH3: PCB - CF | DI3: PCB - MG | DJ3: Stator - CF | DK3: Total | DL3: PCB - Ref | DM3: PCB - CF | DN3: PCB - MG | DO3: Stator - CF | DP3: Total | DR3: Product | DS3: PCB - Ref | DT3: PCB - CF | DU3: PCB - MG | DV3: Stator - CF | DW3: Total | DX3: PCB - Ref | DY3: PCB - CF | DZ3: PCB - MG | EA3: Stator - CF | EB3: Total | ED3: Product | EE3: PCB - Ref | EF3: PCB - CF | EG3: PCB - MG | EH3: Stator - CF | EI3: Total | EJ3: PCB - Ref | EK3: PCB - CF | EL3: PCB - MG | EM3: Stator - CF | EN3: Total | EP3: Product | EQ3: PCB - Ref | ER3: PCB - CF | ES3: PCB - MG | ET3: Stator - CF | EU3: Total | EV3: PCB - Ref | EW3: PCB - CF | EX3: PCB - MG | EY3: Stator - CF | EZ3: Total | FB3: Product | FC3: PCB - Ref | FD3: PCB - CF | FE3: PCB - MG | FF3: Stator - CF | FG3: Total | FH3: PCB - Ref | FI3: PCB - CF | FJ3: PCB - MG | FK3: Stator - CF | FL3: Total | FN3: Product | FO3: PCB - Ref | FP3: PCB - CF | FQ3: PCB - MG | FR3: Stator - CF | FS3: Total | FT3: PCB - Ref | FU3: PCB - CF | FV3: PCB - MG | FW3: Stator - CF | FX3: Total | FZ3: Product (INR in '000) | GA3: PCB Ref | GB3: PCB CF | GC3: PCB MG | GD3: Stator CF | GE3: Rotor Ref | GF3: Total | GG3: PCB Ref | GH3: PCB CF | GI3: PCB MG | GJ3: Stator CF | GK3: Rotor Ref | GL3: Total | GN3: Product (INR in '000) | GO3: PCB Ref | GP3: PCB CF | GQ3: PCB MG | GR3: Stator CF | GS3: Rotor Ref | GT3: Total | GU3: PCB Ref | GV3: PCB CF | GW3: PCB MG | GX3: Stator CF | GY3: Rotor Ref | GZ3: Total | HB3: Product (INR in '000) | HC3: PCB Ref | HD3: PCB CF | HE3: PCB MG | HF3: Stator CF | HG3: Rotor Ref | HH3: Total | HI3: PCB Ref | HJ3: PCB CF | HK3: PCB MG | HL3: Stator CF | HM3: Rotor Ref | HN3: Total | HP3: Product (INR in '000) | HQ3: PCB Ref | HR3: PCB CF | HS3: PCB MG | HT3: Stator CF | HU3: Rotor Ref | HV3: Total | HW3: PCB Ref | HX3: PCB CF | HY3: PCB MG | HZ3: Stator CF | IA3: Rotor Ref | IB3: Total | ID3: Product (INR in '000) | IE3: PCB Ref | IF3: PCB CF | IG3: PCB MG | IH3: Stator CF | II3: Rotor Ref | IJ3: Total | IK3: PCB Ref | IL3: PCB CF | IM3: PCB MG | IN3: Stator CF | IO3: Rotor Ref | IP3: Total | IR3: Product (INR in '000) | IS3: PCB Ref | IT3: PCB CF | IU3: PCB MG | IV3: Stator CF | IW3: Rotor Ref | IX3: Total | IY3: PCB Ref | IZ3: PCB CF | JA3: PCB MG | JB3: Stator CF | JC3: Rotor Ref | JD3: Total | JF3: Product (INR in '000) | JG3: PCB Ref | JH3: PCB CF | JI3: PCB MG | JJ3: Stator CF | JK3: Rotor Ref | JL3: Total | JM3: PCB Ref | JN3: PCB CF | JO3: PCB MG | JP3: Stator CF | JQ3: Rotor Ref | JR3: Total | JT3: Product (INR in '000) | JU3: PCB Ref | JV3: PCB CF | JW3: PCB MG | JX3: Stator CF | JY3: Rotor Ref | JZ3: Total | KA3: PCB Ref | KB3: PCB CF | KC3: PCB MG | KD3: Stator CF | KE3: Rotor Ref | KF3: Total | KH3: Product (INR in '000) | KI3: PCB Ref | KJ3: PCB CF | KK3: PCB MG | KL3: Stator CF | KM3: Rotor Ref | KN3: Total | KO3: PCB Ref | KP3: PCB CF | KQ3: PCB MG | KR3: Stator CF | KS3: Rotor Ref | KT3: Total
B4: Qty | C4: 2000 | D4: 5880 | E4: 630 | F4: 2374 | G4: 10884 | H4: 2000 | I4: 5880 | J4: 630 | K4: 2374 | L4: 10884 | N4: Qty | O4: 0 | P4: 11760 | Q4: 1435 | R4: 5420 | S4: 18615 | T4: 2000 | U4: 17640 | V4: 2065 | W4: 7794 | X4: 29499 | Z4: Qty | AA4: 0 | AB4: 6720 | AC4: 455 | AD4: 2000 | AE4: 9175 | AF4: 2000 | AG4: 24360 | AH4: 2520 | AI4: 9794 | AJ4: 38674 | AL4: Qty | AM4: 0 | AN4: 10080 | AO4: 980 | AP4: 0 | AQ4: 11060 | AR4: 2000 | AS4: 34440 | AT4: 3500 | AU4: 9794 | AV4: 49734 | AX4: Qty | AY4: 0 | AZ4: 13125 | BA4: 0 | BB4: 3360 | BC4: 16485 | BD4: 2000 | BE4: 47565 | BF4: 3500 | BG4: 13154 | BH4: 66219 | BJ4: Qty | BK4: 0 | BL4: 5880 | BM4: 613 | BN4: 1200 | BO4: 7693 | BP4: 2000 | BQ4: 53445 | BR4: 4113 | BS4: 14354 | BT4: 73912 | BV4: Qty | BW4: 0 | BX4: 7910 | BY4: 648 | BZ4: 3600 | CA4: 12158 | CB4: 2000 | CC4: 61355 | CD4: 4761 | CE4: 17954 | CF4: 86070 | CH4: Qty | CI4: 0 | CJ4: 9310 | CK4: 910 | CL4: 2880 | CM4: 13100 | CN4: 2000 | CO4: 70665 | CP4: 5671 | CQ4: 20834 | CR4: 99170 | CT4: Qty | CU4: 0 | CV4: 6790 | CW4: 617 | CX4: 2520 | CY4: 9927 | CZ4: 2000 | DA4: 77455 | DB4: 6288 | DC4: 23354 | DD4: 109097 | DF4: Qty | DG4: 0 | DH4: 4268 | DI4: 280 | DJ4: 2268 | DK4: 6816 | DL4: 2000 | DM4: 81723 | DN4: 6568 | DO4: 25622 | DP4: 115913 | DR4: Qty | DS4: 0 | DT4: 10850 | DU4: 175 | DV4: 2480 | DW4: 13505 | DX4: 2000 | DY4: 92573 | DZ4: 6743 | EA4: 28102 | EB4: 129418 | ED4: Qty | EE4: 0 | EF4: 10535 | EG4: 824 | EH4: 2448 | EI4: 13807 | EJ4: 2000 | EK4: 103108 | EL4: 7567 | EM4: 30550 | EN4: 143225 | EP4: Qty | EQ4: 0 | ER4: 5600 | ES4: 420 | ET4: 1720 | EU4: 7740 | EV4: 2000 | EW4: 108708 | EX4: 7987 | EY4: 32270 | EZ4: 150965 | FB4: Qty | FC4: 0 | FD4: 8225 | FE4: 910 | FF4: 3236 | FG4: 12371 | FH4: 2000 | FI4: 116933 | FJ4: 8897 | FK4: 35506 | FL4: 163336 | FN4: Qty | FO4: 0 | FP4: 6160 | FQ4: 770 | FR4: 1008 | FS4: 7938 | FT4: 2000 | FU4: 123093 | FV4: 9667 | FW4: 36514 | FX4: 171274 | FZ4: Qty (In Units) | GA4: 0 | GB4: 4515 | GC4: 1848 | GD4: 2016 | GE4: 40 | GF4: 8419 | GG4: 2000 | GH4: 127608 | GI4: 11515 | GJ4: 38530 | GK4: 40 | GL4: 179693 | GN4: Qty (In Units) | GO4: 3600 | GP4: 5740 | GQ4: 1365 | GR4: 3160 | GS4: 0 | GT4: 13865 | GU4: 5600 | GV4: 133348 | GW4: 12880 | GX4: 41690 | GY4: 40 | GZ4: 193558 | HB4: Qty (In Units) | HC4: 0 | HD4: 6615 | HE4: 70 | HF4: 3132 | HG4: 0 | HH4: 9817 | HI4: 5600 | HJ4: 139963 | HK4: 12950 | HL4: 44822 | HM4: 40 | HN4: 203375 | HP4: Qty (In Units) | HQ4: 0 | HR4: 7210 | HS4: 910 | HT4: 2208 | HU4: 0 | HV4: 10328 | HW4: 5600 | HX4: 147173 | HY4: 13860 | HZ4: 47030 | IA4: 40 | IB4: 213703 | ID4: Qty (In Units) | IE4: 0 | IF4: 8715 | IG4: 1680 | IH4: 3640 | II4: 0 | IJ4: 14035 | IK4: 5600 | IL4: 155888 | IM4: 15540 | IN4: 50670 | IO4: 40 | IP4: 227738 | IR4: Qty (In Units) | IS4: 0 | IT4: 5600 | IU4: 285 | IV4: 3056 | IW4: 0 | IX4: 8941 | IY4: 5600 | IZ4: 161488 | JA4: 15825 | JB4: 53726 | JC4: 40 | JD4: 236679 | JF4: Qty (In Units) | JG4: 3000 | JH4: 5110 | JI4: 215 | JJ4: 2976 | JK4: 0 | JL4: 11301 | JM4: 8600 | JN4: 166598 | JO4: 16040 | JP4: 56702 | JQ4: 40 | JR4: 247980 | JT4: Qty (In Units) | JU4: 0 | JV4: 2520 | JW4: 875 | JX4: 3048 | JY4: 0 | JZ4: 6443 | KA4: 8600 | KB4: 169118 | KC4: 16915 | KD4: 59750 | KE4: 40 | KF4: 254423 | KH4: Qty (In Units) | KI4: 0 | KJ4: 6370 | KK4: 0 | KL4: 3024 | KM4: 0 | KN4: 9394 | KO4: 8600 | KP4: 175488 | KQ4: 16915 | KR4: 62774 | KS4: 40 | KT4: 263817
B5: Sales ('000) | C5: 1472.62 | D5: 2314.116 | E5: 465.8094 | F5: 367.28154 | G5: 4619.8269 | H5: 1472.62 | I5: 2314.116 | J5: 465.8094 | K5: 367.28154 | L5: 4619.8269 | N5: Sales ('000) | O5: 0 | P5: 4178.3616 | Q5: 850.3054 | R5: 838.5282 | S5: 5867.1952 | T5: 1472.62 | U5: 6492.4776 | V5: 1316.1148 | W5: 1205.8097 | X5: 10487.022 | Z5: Sales ('000) | AA5: 0 | AB5: 2399.8464 | AC5: 392.3192 | AD5: 309.42 | AE5: 3101.5856 | AF5: 1472.62 | AG5: 8892.324 | AH5: 1708.434 | AI5: 1515.2297 | AJ5: 13588.608 | AL5: Sales ('000) | AM5: 0 | AN5: 3590.0928 | AO5: 632.14025 | AP5: 0 | AQ5: 4222.233 | AR5: 1472.62 | AS5: 12482.417 | AT5: 2340.5743 | AU5: 1515.2297 | AV5: 17810.841 | AX5: Sales ('000) | AY5: 0 | AZ5: 4784.0432 | BA5: 0 | BB5: 519.8256 | BC5: 5303.8688 | BD5: 1472.62 | BE5: 17266.46 | BF5: 2340.5743 | BG5: 2035.0553 | BH5: 23114.71 | BJ5: Sales ('000) | BK5: 0 | BL5: 2204.1684 | BM5: 340.57732 | BN5: 185.652 | BO5: 2730.3977 | BP5: 1472.62 | BQ5: 19470.628 | BR5: 2681.1516 | BS5: 2220.7073 | BT5: 25845.107 | BV5: Sales ('000) | BW5: 0 | BX5: 2927.1732 | BY5: 298.63057 | BZ5: 556.956 | CA5: 3782.7598 | CB5: 1472.62 | CC5: 22397.802 | CD5: 2979.7821 | CE5: 2777.6633 | CF5: 29627.867 | CH5: Sales ('000) | CI5: 0 | CJ5: 3318.9352 | CK5: 649.18525 | CL5: 445.5648 | CM5: 4413.6853 | CN5: 1472.62 | CO5: 25716.737 | CP5: 3628.9674 | CQ5: 3223.2281 | CR5: 34041.552 | CT5: Sales ('000) | CU5: 0 | CV5: 2519.1117 | CW5: 473.95073 | CX5: 389.8692 | CY5: 3382.9316 | CZ5: 1472.62 | DA5: 28235.849 | DB5: 4102.9181 | DC5: 3613.0973 | DD5: 37424.484 | DF5: Sales ('000) | DG5: 0 | DH5: 1528.7269 | DI5: 164.0254 | DJ5: 350.88228 | DK5: 2043.6346 | DL5: 1472.62 | DM5: 29764.575 | DN5: 4266.9435 | DO5: 3963.9796 | DP5: 39468.119 | DR5: Sales ('000) | DS5: 0 | DT5: 3934.3857 | DU5: 54.96575 | DV5: 383.6808 | DW5: 4373.0323 | DX5: 1472.62 | DY5: 33698.961 | DZ5: 4321.9093 | EA5: 4347.6604 | EB5: 43841.151 | ED5: Sales ('000) | EE5: 0 | EF5: 4015.5847 | EG5: 253.52714 | EH5: 378.73008 | EI5: 4647.8419 | EJ5: 1472.62 | EK5: 37714.546 | EL5: 4575.4364 | EM5: 4726.3905 | EN5: 48488.993 | EP5: Sales ('000) | EQ5: 0 | ER5: 2101.6492 | ES5: 285.3998 | ET5: 276.621 | EU5: 2663.67 | EV5: 1472.62 | EW5: 39816.195 | EX5: 4860.8362 | EY5: 5003.0115 | EZ5: 51152.663 | FB5: Sales ('000) | FC5: 0 | FD5: 3090.521 | FE5: 281.6919 | FF5: 500.64156 | FG5: 3872.8545 | FH5: 1472.62 | FI5: 42906.716 | FJ5: 5142.5281 | FK5: 5503.6531 | FL5: 55025.517 | FN5: Sales ('000) | FO5: 0 | FP5: 2303.2506 | FQ5: 297.58785 | FR5: 155.94768 | FS5: 2756.7861 | FT5: 1472.62 | FU5: 45209.967 | FV5: 5440.116 | FW5: 5659.6007 | FX5: 57782.303 | FZ5: Sales | GA5: 0 | GB5: 1608.0624 | GC5: 927.54452 | GD5: 311.89536 | GE5: 5.8696 | GF5: 2853.3719 | GG5: 1472.62 | GH5: 46818.029 | GI5: 6367.6605 | GJ5: 5971.4961 | GK5: 5.8696 | GL5: 60635.675 | GN5: Sales | GO5: 2650.716 | GP5: 2119.9234 | GQ5: 634.56435 | GR5: 488.8836 | GS5: 0 | GT5: 5894.0873 | GU5: 4123.336 | GV5: 48937.952 | GW5: 7002.2248 | GX5: 6460.3797 | GY5: 5.8696 | GZ5: 66529.763 | HB5: Sales | HC5: 0 | HD5: 2493.7934 | HE5: 41.17155 | HF5: 484.55172 | HG5: 0 | HH5: 3019.5167 | HI5: 4123.336 | HJ5: 51431.746 | HK5: 7043.3964 | HL5: 6944.9314 | HM5: 5.8696 | HN5: 69549.279 | HP5: Sales | HQ5: 0 | HR5: 2688.7336 | HS5: 330.72165 | HT5: 341.59968 | HU5: 0 | HV5: 3361.0549 | HW5: 4123.336 | HX5: 54120.479 | HY5: 7374.118 | HZ5: 7286.5311 | IA5: 5.8696 | IB5: 72910.334 | ID5: Sales | IE5: 0 | IF5: 3335.0744 | IG5: 632.3702 | IH5: 563.1444 | II5: 0 | IJ5: 4530.589 | IK5: 4123.336 | IL5: 57455.554 | IM5: 8006.4882 | IN5: 7849.6755 | IO5: 5.8696 | IP5: 77440.923 | IR5: Sales | IS5: 0 | IT5: 2136.736 | IU5: 99.32225 | IV5: 472.79376 | IW5: 0 | IX5: 2708.852 | IY5: 4123.336 | IZ5: 59592.29 | JA5: 8105.8105 | JB5: 8322.4693 | JC5: 5.8696 | JD5: 80149.775 | JF5: Sales | JG5: 2217.93 | JH5: 1939.9926 | JI5: 132.1116 | JJ5: 460.41696 | JK5: 0 | JL5: 4750.4512 | JM5: 6341.266 | JN5: 61532.282 | JO5: 8237.9221 | JP5: 8782.8862 | JQ5: 5.8696 | JR5: 84900.226 | JT5: Sales | JU5: 0 | JV5: 964.1982 | JW5: 381.57 | JX5: 471.55608 | JY5: 0 | JZ5: 1817.3243 | KA5: 6341.266 | KB5: 62496.481 | KC5: 8619.4921 | KD5: 9254.4423 | KE5: 5.8696 | KF5: 86717.551 | KH5: Sales | KI5: 0 | KJ5: 2268.7392 | KK5: 0 | KL5: 467.84304 | KM5: 0 | KN5: 2736.5822 | KO5: 6341.266 | KP5: 64765.22 | KQ5: 8619.4921 | KR5: 9722.2853 | KS5: 5.8696 | KT5: 89454.133
B6: COGS ('000) | C6: 951.44 | D6: 2114.8176 | E6: 404.4719 | F6: 329.13136 | G6: 3799.8609 | H6: 951.44 | I6: 2114.8176 | J6: 404.4719 | K6: 329.13136 | L6: 3799.8609 | N6: COGS ('000) | O6: 0 | P6: 3851.1984 | Q6: 750.01815 | R6: 751.4288 | S6: 5352.6453 | T6: 951.44 | U6: 5966.016 | V6: 1154.4901 | W6: 1080.5602 | X6: 9152.5062 | Z6: COGS ('000) | AA6: 0 | AB6: 2212.1904 | AC6: 337.55995 | AD6: 277.28 | AE6: 2827.0303 | AF6: 951.44 | AG6: 8178.2064 | AH6: 1492.05 | AI6: 1357.8402 | AJ6: 11979.537 | AL6: COGS ('000) | AM6: 0 | AN6: 3306.6432 | AO6: 554.0255 | AP6: 0 | AQ6: 3860.6687 | AR6: 951.44 | AS6: 11484.85 | AT6: 2046.0755 | AU6: 1357.8402 | AV6: 15840.205 | AX6: COGS ('000) | AY6: 0 | AZ6: 4402.6489 | BA6: 0 | BB6: 465.8304 | BC6: 4868.4793 | BD6: 951.44 | BE6: 15887.499 | BF6: 2046.0755 | BG6: 1823.6706 | BH6: 20708.685 | BJ6: COGS ('000) | BK6: 0 | BL6: 2021.8716 | BM6: 301.97577 | BN6: 166.368 | BO6: 2490.2154 | BP6: 951.44 | BQ6: 17909.37 | BR6: 2348.0513 | BS6: 1990.0386 | BT6: 23198.9 | BV6: COGS ('000) | BW6: 0 | BX6: 2687.8131 | BY6: 268.51176 | BZ6: 499.104 | CA6: 3455.4289 | CB6: 951.44 | CC6: 20597.183 | CD6: 2616.563 | CE6: 2489.1426 | CF6: 26654.329 | CH6: COGS ('000) | CI6: 0 | CJ6: 3058.0098 | CK6: 565.012 | CL6: 399.2832 | CM6: 4022.305 | CN6: 951.44 | CO6: 23655.193 | CP6: 3181.575 | CQ6: 2888.4258 | CR6: 30676.634 | CT6: COGS ('000) | CU6: 0 | CV6: 2312.6089 | CW6: 410.55703 | CX6: 349.3728 | CY6: 3072.5387 | CZ6: 951.44 | DA6: 25967.802 | DB6: 3592.1321 | DC6: 3237.7986 | DD6: 33749.173 | DF6: COGS ('000) | DG6: 0 | DH6: 1407.603 | DI6: 144.8104 | DJ6: 314.43552 | DK6: 1866.8489 | DL6: 951.44 | DM6: 27375.405 | DN6: 3736.9425 | DO6: 3552.2341 | DP6: 35616.022 | DR6: COGS ('000) | DS6: 0 | DT6: 3624.3172 | DU6: 51.3835 | DV6: 343.8272 | DW6: 4019.5279 | DX6: 951.44 | DY6: 30999.722 | DZ6: 3788.326 | EA6: 3896.0613 | EB6: 39635.549 | ED6: COGS ('000) | EE6: 0 | EF6: 3683.6338 | EG6: 234.75981 | EH6: 339.39072 | EI6: 4257.7843 | EJ6: 951.44 | EK6: 34683.356 | EL6: 4023.0858 | EM6: 4235.452 | EN6: 43893.334 | EP6: COGS ('000) | EQ6: 0 | ER6: 1929.9882 | ES6: 248.836 | ET6: 248.2368 | EU6: 2427.061 | EV6: 951.44 | EW6: 36613.344 | EX6: 4271.9218 | EY6: 4483.6888 | EZ6: 46320.395 | FB6: COGS ('000) | FC6: 0 | FD6: 2839.2388 | FE6: 266.18795 | FF6: 448.63904 | FG6: 3554.0658 | FH6: 951.44 | FI6: 39452.583 | FJ6: 4538.1097 | FK6: 4932.3278 | FL6: 49874.461 | FN6: COGS ('000) | FO6: 0 | FP6: 2116.4587 | FQ6: 272.713 | FR6: 139.74912 | FS6: 2528.9209 | FT6: 951.44 | FU6: 41569.042 | FV6: 4810.8227 | FW6: 5072.077 | FX6: 52403.381 | FZ6: COGS | GA6: 0 | GB6: 1481.1037 | GC6: 808.34397 | GD6: 279.49824 | GE6: 3.629 | GF6: 2572.575 | GG6: 951.44 | GH6: 43050.146 | GI6: 5619.1667 | GJ6: 5351.5752 | GK6: 3.629 | GL6: 54975.956 | GN6: COGS | GO6: 1712.592 | GP6: 1948.822 | GQ6: 561.14275 | GR6: 438.1024 | GS6: 0 | GT6: 4660.6592 | GU6: 2664.032 | GV6: 44998.968 | GW6: 6180.3094 | GX6: 5789.6776 | GY6: 3.629 | GZ6: 59636.616 | HB6: COGS | HC6: 0 | HD6: 2290.105 | HE6: 36.24285 | HF6: 434.22048 | HG6: 0 | HH6: 2760.5683 | HI6: 2664.032 | HJ6: 47289.073 | HK6: 6216.5523 | HL6: 6223.8981 | HM6: 3.629 | HN6: 62397.184 | HP6: COGS | HQ6: 0 | HR6: 2476.5216 | HS6: 295.21275 | HT6: 306.11712 | HU6: 0 | HV6: 3077.8515 | HW6: 2664.032 | HX6: 49765.594 | HY6: 6511.765 | HZ6: 6530.0152 | IA6: 3.629 | IB6: 65475.035 | ID6: COGS | IE6: 0 | IF6: 3060.379 | IG6: 562.9533 | IH6: 504.6496 | II6: 0 | IJ6: 4127.9819 | IK6: 2664.032 | IL6: 52825.973 | IM6: 7074.7183 | IN6: 7034.6648 | IO6: 3.629 | IP6: 69603.017 | IR6: COGS | IS6: 0 | IT6: 1961.064 | IU6: 92.36535 | IV6: 423.68384 | IW6: 0 | IX6: 2477.1132 | IY6: 2664.032 | IZ6: 54787.037 | JA6: 7167.0837 | JB6: 7458.3486 | JC6: 3.629 | JD6: 72080.13 | JF6: COGS | JG6: 1427.16 | JH6: 1780.9246 | JI6: 114.49285 | JJ6: 412.59264 | JK6: 0 | JL6: 3735.1701 | JM6: 4091.192 | JN6: 56567.962 | JO6: 7281.5765 | JP6: 7870.9413 | JQ6: 3.629 | JR6: 75815.301 | JT6: COGS | JU6: 0 | JV6: 884.8035 | JW6: 334.05925 | JX6: 422.57472 | JY6: 0 | JZ6: 1641.4375 | KA6: 4091.192 | KB6: 57452.765 | KC6: 7615.6358 | KD6: 8293.516 | KE6: 3.629 | KF6: 77456.738 | KH6: COGS | KI6: 0 | KJ6: 2089.6148 | KK6: 0 | KL6: 419.24736 | KM6: 0 | KN6: 2508.8622 | KO6: 4091.192 | KP6: 59542.38 | KQ6: 7615.6358 | KR6: 8712.7634 | KS6: 3.629 | KT6: 79965.6
B7: BOM cost ('000) | C7: 847.34 | D7: 1824.1104 | E7: 370.7571 | F7: 313.46296 | G7: 3355.6705 | H7: 847.34 | I7: 1824.1104 | J7: 370.7571 | K7: 313.46296 | L7: 3355.6705 | N7: BOM cost ('000) | O7: 0 | P7: 3269.784 | Q7: 675.22035 | R7: 715.6568 | S7: 4660.6611 | T7: 847.34 | U7: 5093.8944 | V7: 1045.9774 | W7: 1029.1198 | X7: 8016.3316 | Z7: BOM cost ('000) | AA7: 0 | AB7: 1879.9536 | AC7: 312.68055 | AD7: 264.08 | AE7: 2456.7141 | AF7: 847.34 | AG7: 6973.848 | AH7: 1358.658 | AI7: 1293.1998 | AJ7: 10473.046 | AL7: BOM cost ('000) | AM7: 0 | AN7: 2808.288 | AO7: 502.4565 | AP7: 0 | AQ7: 3310.7445 | AR7: 847.34 | AS7: 9782.136 | AT7: 1861.1145 | AU7: 1293.1998 | AV7: 13783.79 | AX7: BOM cost ('000) | AY7: 0 | AZ7: 3753.749 | BA7: 0 | BB7: 443.6544 | BC7: 4197.4034 | BD7: 847.34 | BE7: 13535.885 | BF7: 1861.1145 | BG7: 1736.8542 | BH7: 17981.194 | BJ7: BOM cost ('000) | BK7: 0 | BL7: 1731.1644 | BM7: 270.23853 | BN7: 158.448 | BO7: 2159.8509 | BP7: 847.34 | BQ7: 15267.049 | BR7: 2131.353 | BS7: 1895.3022 | BT7: 20141.045 | BV7: BOM cost ('000) | BW7: 0 | BX7: 2296.7427 | BY7: 235.87352 | BZ7: 475.344 | CA7: 3007.9602 | CB7: 847.34 | CC7: 17563.792 | CD7: 2367.2265 | CE7: 2370.6462 | CF7: 23149.005 | CH7: BOM cost ('000) | CI7: 0 | CJ7: 2597.7049 | CK7: 516.537 | CL7: 380.2752 | CM7: 3494.5171 | CN7: 847.34 | CO7: 20161.497 | CP7: 2883.7635 | CQ7: 2750.9214 | CR7: 26643.522 | CT7: BOM cost ('000) | CU7: 0 | CV7: 1976.9113 | CW7: 377.36967 | CX7: 332.7408 | CY7: 2687.0218 | CZ7: 847.34 | DA7: 22138.408 | DB7: 3261.1332 | DC7: 3083.6622 | DD7: 29330.544 | DF7: BOM cost ('000) | DG7: 0 | DH7: 1196.5931 | DI7: 130.2336 | DJ7: 299.46672 | DK7: 1626.2934 | DL7: 847.34 | DM7: 23335.001 | DN7: 3391.3668 | DO7: 3383.1289 | DP7: 30956.837 | DR7: BOM cost ('000) | DS7: 0 | DT7: 3087.8932 | DU7: 42.917 | DV7: 327.4592 | DW7: 3458.2694 | DX7: 847.34 | DY7: 26422.895 | DZ7: 3434.2838 | EA7: 3710.5881 | EB7: 34415.106 | ED7: BOM cost ('000) | EE7: 0 | EF7: 3162.7834 | EG7: 195.61107 | EH7: 323.23392 | EI7: 3681.6284 | EJ7: 847.34 | EK7: 29585.678 | EL7: 3629.8949 | EM7: 4033.822 | EN7: 38096.735 | EP7: BOM cost ('000) | EQ7: 0 | ER7: 1653.1242 | ES7: 226.7524 | ET7: 236.8848 | EU7: 2116.7614 | EV7: 847.34 | EW7: 31238.802 | EX7: 3856.6473 | EY7: 4270.7068 | EZ7: 40213.496 | FB7: BOM cost ('000) | FC7: 0 | FD7: 2432.5948 | FE7: 221.23465 | FF7: 427.28144 | FG7: 3081.1109 | FH7: 847.34 | FI7: 33671.397 | FJ7: 4077.8819 | FK7: 4697.9882 | FL7: 43294.607 | FN7: BOM cost ('000) | FO7: 0 | FP7: 1811.9084 | FQ7: 234.3908 | FR7: 133.09632 | FS7: 2179.3955 | FT7: 847.34 | FU7: 35483.305 | FV7: 4312.2727 | FW7: 4831.0846 | FX7: 45474.003 | FZ7: BOM cost | GA7: 0 | GB7: 1257.8821 | GC7: 735.34783 | GD7: 266.19264 | GE7: 3.365 | GF7: 2262.7876 | GG7: 847.34 | GH7: 36741.187 | GI7: 5047.6206 | GJ7: 5097.2772 | GK7: 3.365 | GL7: 47736.79 | GN7: BOM cost | GO7: 1525.212 | GP7: 1665.0364 | GQ7: 501.71415 | GR7: 417.2464 | GS7: 0 | GT7: 4109.209 | GU7: 2372.552 | GV7: 38406.224 | GW7: 5549.3347 | GX7: 5514.5236 | GY7: 3.365 | GZ7: 51845.999 | HB7: BOM cost | HC7: 0 | HD7: 1963.0593 | HE7: 32.63575 | HF7: 413.54928 | HG7: 0 | HH7: 2409.2444 | HI7: 2372.552 | HJ7: 40369.283 | HK7: 5581.9705 | HL7: 5928.0729 | HM7: 3.365 | HN7: 54255.244 | HP7: BOM cost | HQ7: 0 | HR7: 2119.5769 | HS7: 260.46265 | HT7: 291.54432 | HU7: 0 | HV7: 2671.5839 | HW7: 2372.552 | HX7: 42488.86 | HY7: 5842.4331 | HZ7: 6219.6172 | IA7: 3.365 | IB7: 56926.828 | ID7: BOM cost | IE7: 0 | IF7: 2629.5094 | IG7: 498.4231 | IH7: 480.6256 | II7: 0 | IJ7: 3608.5581 | IK7: 2372.552 | IL7: 45118.37 | IM7: 6340.8562 | IN7: 6700.2428 | IO7: 3.365 | IP7: 60535.386 | IR7: BOM cost | IS7: 0 | IT7: 1684.2 | IU7: 78.19135 | IV7: 403.51424 | IW7: 0 | IX7: 2165.9056 | IY7: 2372.552 | IZ7: 46802.57 | JA7: 6419.0476 | JB7: 7103.757 | JC7: 3.365 | JD7: 62701.291 | JF7: BOM cost | JG7: 1271.01 | JH7: 1528.2862 | JI7: 104.98085 | JJ7: 392.95104 | JK7: 0 | JL7: 3297.2281 | JM7: 3643.562 | JN7: 48330.856 | JO7: 6524.0284 | JP7: 7496.7081 | JQ7: 3.365 | JR7: 65998.519 | JT7: BOM cost | JU7: 0 | JV7: 760.2147 | JW7: 301.92365 | JX7: 402.45792 | JY7: 0 | JZ7: 1464.5963 | KA7: 3643.562 | KB7: 49091.07 | KC7: 6825.9521 | KD7: 7899.166 | KE7: 3.365 | KF7: 67463.116 | KH7: BOM cost | KI7: 0 | KJ7: 1774.682 | KK7: 0 | KL7: 399.28896 | KM7: 0 | KN7: 2173.971 | KO7: 3643.562 | KP7: 50865.752 | KQ7: 6825.9521 | KR7: 8298.455 | KS7: 3.365 | KT7: 69637.087
B8: Labour Cost ('000) | C8: 65.14 | D8: 180.8688 | E8: 21.1526 | F8: 10.9204 | G8: 278.0818 | H8: 65.14 | I8: 180.8688 | J8: 21.1526 | K8: 10.9204 | L8: 278.0818 | N8: Labour Cost ('000) | O8: 0 | P8: 361.7376 | Q8: 46.8013 | R8: 24.932 | S8: 433.4709 | T8: 65.14 | U8: 542.6064 | V8: 67.9539 | W8: 35.8524 | X8: 711.5527 | Z8: Labour Cost ('000) | AA8: 0 | AB8: 206.7072 | AC8: 15.6429 | AD8: 9.2 | AE8: 231.5501 | AF8: 65.14 | AG8: 749.3136 | AH8: 83.5968 | AI8: 45.0524 | AJ8: 943.1028 | AL8: Labour Cost ('000) | AM8: 0 | AN8: 310.0608 | AO8: 32.2987 | AP8: 0 | AQ8: 342.3595 | AR8: 65.14 | AS8: 1059.3744 | AT8: 115.8955 | AU8: 45.0524 | AV8: 1285.4623 | AX8: Labour Cost ('000) | AY8: 0 | AZ8: 403.725 | BA8: 0 | BB8: 15.456 | BC8: 419.181 | BD8: 65.14 | BE8: 1463.0994 | BF8: 115.8955 | BG8: 60.5084 | BH8: 1704.6433 | BJ8: Labour Cost ('000) | BK8: 0 | BL8: 180.8688 | BM8: 19.84414 | BN8: 5.52 | BO8: 206.23294 | BP8: 65.14 | BQ8: 1643.9682 | BR8: 135.73964 | BS8: 66.0284 | BT8: 1910.8762 | BV8: Labour Cost ('000) | BW8: 0 | BX8: 243.3116 | BY8: 20.34844 | BZ8: 16.56 | CA8: 280.22004 | CB8: 65.14 | CC8: 1887.2798 | CD8: 156.08808 | CE8: 82.5884 | CF8: 2191.0963 | CH8: Labour Cost ('000) | CI8: 0 | CJ8: 286.3882 | CK8: 30.3989 | CL8: 13.248 | CM8: 330.0351 | CN8: 65.14 | CO8: 2173.668 | CP8: 186.48698 | CQ8: 95.8364 | CR8: 2521.1314 | CT8: Labour Cost ('000) | CU8: 0 | CV8: 208.8604 | CW8: 20.83236 | CX8: 11.592 | CY8: 241.28476 | CZ8: 65.14 | DA8: 2382.5284 | DB8: 207.31934 | DC8: 107.4284 | DD8: 2762.4161 | DF8: Labour Cost ('000) | DG8: 0 | DH8: 131.28368 | DI8: 9.1196 | DJ8: 10.4328 | DK8: 150.83608 | DL8: 65.14 | DM8: 2513.8121 | DN8: 216.43894 | DO8: 117.8612 | DP8: 2913.2522 | DR8: Labour Cost ('000) | DS8: 0 | DT8: 333.746 | DU8: 5.25525 | DV8: 11.408 | DW8: 350.40925 | DX8: 65.14 | DY8: 2847.5581 | DZ8: 221.69419 | EA8: 129.2692 | EB8: 3263.6615 | ED8: Labour Cost ('000) | EE8: 0 | EF8: 324.0566 | EG8: 24.25241 | EH8: 11.2608 | EI8: 359.56981 | EJ8: 65.14 | EK8: 3171.6147 | EL8: 245.9466 | EM8: 140.53 | EN8: 3623.2313 | EP8: Labour Cost ('000) | EQ8: 0 | ER8: 172.256 | ES8: 13.8306 | ET8: 7.912 | EU8: 193.9986 | EV8: 65.14 | EW8: 3343.8707 | EX8: 259.7772 | EY8: 148.442 | EZ8: 3817.2299 | FB8: Labour Cost ('000) | FC8: 0 | FD8: 253.001 | FE8: 27.96605 | FF8: 14.8856 | FG8: 295.85265 | FH8: 65.14 | FI8: 3596.8717 | FJ8: 287.74325 | FK8: 163.3276 | FL8: 4113.0825 | FN8: Labour Cost ('000) | FO8: 0 | FP8: 189.4816 | FQ8: 23.8609 | FR8: 4.6368 | FS8: 217.9793 | FT8: 65.14 | FU8: 3786.3533 | FV8: 311.60415 | FW8: 167.9644 | FX8: 4331.0618 | FZ8: Labour Cost | GA8: 0 | GB8: 138.8814 | GC8: 44.22299 | GD8: 9.2736 | GE8: 0.184 | GF8: 192.56199 | GG8: 65.14 | GH8: 3925.2347 | GI8: 355.82714 | GJ8: 177.238 | GK8: 0.184 | GL8: 4523.6238 | GN8: Labour Cost | GO8: 117.252 | GP8: 176.5624 | GQ8: 36.4525 | GR8: 14.536 | GS8: 0 | GT8: 344.8029 | GU8: 182.392 | GV8: 4101.7971 | GW8: 392.27964 | GX8: 191.774 | GY8: 0.184 | GZ8: 4868.4267 | HB8: Labour Cost | HC8: 0 | HD8: 203.4774 | HE8: 2.25435 | HF8: 14.4072 | HG8: 0 | HH8: 220.13895 | HI8: 182.392 | HJ8: 4305.2745 | HK8: 394.53399 | HL8: 206.1812 | HM8: 0.184 | HN8: 5088.5657 | HP8: Labour Cost | HQ8: 0 | HR8: 222.1072 | HS8: 20.95065 | HT8: 10.1568 | HU8: 0 | HV8: 253.21465 | HW8: 182.392 | HX8: 4527.3817 | HY8: 415.48464 | HZ8: 216.338 | IA8: 0.184 | IB8: 5341.7803 | ID8: Labour Cost | IE8: 0 | IF8: 268.0734 | IG8: 38.9375 | IH8: 16.744 | II8: 0 | IJ8: 323.7549 | IK8: 182.392 | IL8: 4795.4551 | IM8: 454.42214 | IN8: 233.082 | IO8: 0.184 | IP8: 5665.5352 | IR8: Labour Cost | IS8: 0 | IT8: 172.256 | IU8: 8.8244 | IV8: 14.0576 | IW8: 0 | IX8: 195.138 | IY8: 182.392 | IZ8: 4967.7111 | JA8: 463.24654 | JB8: 247.1396 | JC8: 0.184 | JD8: 5860.6732 | JF8: Labour Cost | JG8: 97.71 | JH8: 157.1836 | JI8: 5.8468 | JJ8: 13.6896 | JK8: 0 | JL8: 274.43 | JM8: 280.102 | JN8: 5124.8947 | JO8: 469.09334 | JP8: 260.8292 | JQ8: 0.184 | JR8: 6135.1032 | JT8: Labour Cost | JU8: 0 | JV8: 77.5152 | JW8: 19.2682 | JX8: 14.0208 | JY8: 0 | JZ8: 110.8042 | KA8: 280.102 | KB8: 5202.4099 | KC8: 488.36154 | KD8: 274.85 | KE8: 0.184 | KF8: 6245.9074 | KH8: Labour Cost | KI8: 0 | KJ8: 195.9412 | KK8: 0 | KL8: 13.9104 | KM8: 0 | KN8: 209.8516 | KO8: 280.102 | KP8: 5398.3511 | KQ8: 488.36154 | KR8: 288.7604 | KS8: 0.184 | KT8: 6455.759
B9: Other Conv Cost ('000) | C9: 39.02 | D9: 109.8972 | E9: 12.5783 | F9: 4.748 | G9: 166.2435 | H9: 39.02 | I9: 109.8972 | J9: 12.5783 | K9: 4.748 | L9: 166.2435 | N9: Other Conv Cost ('000) | O9: 0 | P9: 219.7944 | Q9: 28.02555 | R9: 10.84 | S9: 258.65995 | T9: 39.02 | U9: 329.6916 | V9: 40.60385 | W9: 15.588 | X9: 424.90345 | Z9: Other Conv Cost ('000) | AA9: 0 | AB9: 125.5968 | AC9: 9.25015 | AD9: 4 | AE9: 138.84695 | AF9: 39.02 | AG9: 455.2884 | AH9: 49.854 | AI9: 19.588 | AJ9: 563.7504 | AL9: Other Conv Cost ('000) | AM9: 0 | AN9: 188.3952 | AO9: 19.292 | AP9: 0 | AQ9: 207.6872 | AR9: 39.02 | AS9: 643.6836 | AT9: 69.146 | AU9: 19.588 | AV9: 771.4376 | AX9: Other Conv Cost ('000) | AY9: 0 | AZ9: 245.30625 | BA9: 0 | BB9: 6.72 | BC9: 252.02625 | BD9: 39.02 | BE9: 888.98985 | BF9: 69.146 | BG9: 26.308 | BH9: 1023.4638 | BJ9: Other Conv Cost ('000) | BK9: 0 | BL9: 109.8972 | BM9: 11.90469 | BN9: 2.4 | BO9: 124.20189 | BP9: 39.02 | BQ9: 998.88705 | BR9: 81.05069 | BS9: 28.708 | BT9: 1147.6657 | BV9: Other Conv Cost ('000) | BW9: 0 | BX9: 147.8379 | BY9: 12.29978 | BZ9: 7.2 | CA9: 167.33768 | CB9: 39.02 | CC9: 1146.7249 | CD9: 93.35047 | CE9: 35.908 | CF9: 1315.0034 | CH9: Other Conv Cost ('000) | CI9: 0 | CJ9: 174.0095 | CK9: 18.0985 | CL9: 5.76 | CM9: 197.868 | CN9: 39.02 | CO9: 1320.7344 | CP9: 111.44897 | CQ9: 41.668 | CR9: 1512.8714 | CT9: Other Conv Cost ('000) | CU9: 0 | CV9: 126.9051 | CW9: 12.37141 | CX9: 5.04 | CY9: 144.31651 | CZ9: 39.02 | DA9: 1447.6396 | DB9: 123.82038 | DC9: 46.708 | DD9: 1657.1879 | DF9: Other Conv Cost ('000) | DG9: 0 | DH9: 79.76892 | DI9: 5.4628 | DJ9: 4.536 | DK9: 89.76772 | DL9: 39.02 | DM9: 1527.4085 | DN9: 129.28318 | DO9: 51.244 | DP9: 1746.9557 | DR9: Other Conv Cost ('000) | DS9: 0 | DT9: 202.7865 | DU9: 3.213 | DV9: 4.96 | DW9: 210.9595 | DX9: 39.02 | DY9: 1730.195 | DZ9: 132.49618 | EA9: 56.204 | EB9: 1957.9152 | ED9: Other Conv Cost ('000) | EE9: 0 | EF9: 196.89915 | EG9: 14.90517 | EH9: 4.896 | EI9: 216.70032 | EJ9: 39.02 | EK9: 1927.0941 | EL9: 147.40135 | EM9: 61.1 | EN9: 2174.6155 | EP9: Other Conv Cost ('000) | EQ9: 0 | ER9: 104.664 | ES9: 8.2628 | ET9: 3.44 | EU9: 116.3668 | EV9: 39.02 | EW9: 2031.7581 | EX9: 155.66415 | EY9: 64.54 | EZ9: 2290.9823 | FB9: Other Conv Cost ('000) | FC9: 0 | FD9: 153.72525 | FE9: 16.99635 | FF9: 6.472 | FG9: 177.1936 | FH9: 39.02 | FI9: 2185.4834 | FJ9: 172.6605 | FK9: 71.012 | FL9: 2468.1759 | FN9: Other Conv Cost ('000) | FO9: 0 | FP9: 115.1304 | FQ9: 14.4711 | FR9: 2.016 | FS9: 131.6175 | FT9: 39.02 | FU9: 2300.6138 | FV9: 187.1316 | FW9: 73.028 | FX9: 2599.7934 | FZ9: Other Conv Cost | GA9: 0 | GB9: 84.38535 | GC9: 28.81984 | GD9: 4.032 | GE9: 0.08 | GF9: 117.31719 | GG9: 39.02 | GH9: 2384.9991 | GI9: 215.95144 | GJ9: 77.06 | GK9: 0.08 | GL9: 2717.1106 | GN9: Other Conv Cost | GO9: 70.236 | GP9: 107.2806 | GQ9: 23.0041 | GR9: 6.32 | GS9: 0 | GT9: 206.8407 | GU9: 109.256 | GV9: 2492.2797 | GW9: 238.95554 | GX9: 83.38 | GY9: 0.08 | GZ9: 2923.9513 | HB9: Other Conv Cost | HC9: 0 | HD9: 123.63435 | HE9: 1.35415 | HF9: 6.264 | HG9: 0 | HH9: 131.2525 | HI9: 109.256 | HJ9: 2615.9141 | HK9: 240.30969 | HL9: 89.644 | HM9: 0.08 | HN9: 3055.2038 | HP9: Other Conv Cost | HQ9: 0 | HR9: 134.9005 | HS9: 13.81765 | HT9: 4.416 | HU9: 0 | HV9: 153.13415 | HW9: 109.256 | HX9: 2750.8146 | HY9: 254.12734 | HZ9: 94.06 | IA9: 0.08 | IB9: 3208.3379 | ID9: Other Conv Cost | IE9: 0 | IF9: 162.88335 | IG9: 25.627 | IH9: 7.28 | II9: 0 | IJ9: 195.79035 | IK9: 109.256 | IL9: 2913.6979 | IM9: 279.75434 | IN9: 101.34 | IO9: 0.08 | IP9: 3404.1283 | IR9: Other Conv Cost | IS9: 0 | IT9: 104.664 | IU9: 5.35285 | IV9: 6.112 | IW9: 0 | IX9: 116.12885 | IY9: 109.256 | IZ9: 3018.3619 | JA9: 285.10719 | JB9: 107.452 | JC9: 0.08 | JD9: 3520.2571 | JF9: Other Conv Cost | JG9: 58.53 | JH9: 95.5059 | JI9: 3.67095 | JJ9: 5.952 | JK9: 0 | JL9: 163.65885 | JM9: 167.786 | JN9: 3113.8678 | JO9: 288.77814 | JP9: 113.404 | JQ9: 0.08 | JR9: 3683.916 | JT9: Other Conv Cost | JU9: 0 | JV9: 47.0988 | JW9: 12.88875 | JX9: 6.096 | JY9: 0 | JZ9: 66.08355 | KA9: 167.786 | KB9: 3160.9666 | KC9: 301.66689 | KD9: 119.5 | KE9: 0.08 | KF9: 3749.9995 | KH9: Other Conv Cost | KI9: 0 | KJ9: 119.0553 | KK9: 0 | KL9: 6.048 | KM9: 0 | KN9: 125.1033 | KO9: 167.786 | KP9: 3280.0219 | KQ9: 301.66689 | KR9: 125.548 | KS9: 0.08 | KT9: 3875.1028
B10: Margin ('000) | C10: 521.18 | D10: 199.2984 | E10: 61.3375 | F10: 38.15018 | G10: 819.96608 | H10: 521.18 | I10: 199.2984 | J10: 61.3375 | K10: 38.15018 | L10: 819.96608 | N10: Margin ('000) | O10: 0 | P10: 327.1632 | Q10: 100.28725 | R10: 87.0994 | S10: 514.54985 | T10: 521.18 | U10: 526.4616 | V10: 161.62475 | W10: 125.24958 | X10: 1334.5159 | Z10: Margin ('000) | AA10: 0 | AB10: 187.656 | AC10: 54.75925 | AD10: 32.14 | AE10: 274.55525 | AF10: 521.18 | AG10: 714.1176 | AH10: 216.384 | AI10: 157.38958 | AJ10: 1609.0712 | AL10: Margin ('000) | AM10: 0 | AN10: 283.4496 | AO10: 78.11475 | AP10: 0 | AQ10: 361.56435 | AR10: 521.18 | AS10: 997.5672 | AT10: 294.49875 | AU10: 157.38958 | AV10: 1970.6355 | AX10: Margin ('000) | AY10: 0 | AZ10: 381.3943 | BA10: 0 | BB10: 53.9952 | BC10: 435.3895 | BD10: 521.18 | BE10: 1378.9615 | BF10: 294.49875 | BG10: 211.38478 | BH10: 2406.025 | BJ10: Margin ('000) | BK10: 0 | BL10: 182.2968 | BM10: 38.60155 | BN10: 19.284 | BO10: 240.18235 | BP10: 521.18 | BQ10: 1561.2583 | BR10: 333.1003 | BS10: 230.66878 | BT10: 2646.2074 | BV10: Margin ('000) | BW10: 0 | BX10: 239.3601 | BY10: 30.11881 | BZ10: 57.852 | CA10: 327.33091 | CB10: 521.18 | CC10: 1800.6184 | CD10: 363.21911 | CE10: 288.52078 | CF10: 2973.5383 | CH10: Margin ('000) | CI10: 0 | CJ10: 260.92535 | CK10: 84.17325 | CL10: 46.2816 | CM10: 391.3802 | CN10: 521.18 | CO10: 2061.5437 | CP10: 447.39236 | CQ10: 334.80238 | CR10: 3364.9185 | CT10: Margin ('000) | CU10: 0 | CV10: 206.5028 | CW10: 63.3937 | CX10: 40.4964 | CY10: 310.3929 | CZ10: 521.18 | DA10: 2268.0465 | DB10: 510.78606 | DC10: 375.29878 | DD10: 3675.3114 | DF10: Margin ('000) | DG10: 0 | DH10: 121.12388 | DI10: 19.215 | DJ10: 36.44676 | DK10: 176.78564 | DL10: 521.18 | DM10: 2389.1704 | DN10: 530.00106 | DO10: 411.74554 | DP10: 3852.097 | DR10: Margin ('000) | DS10: 0 | DT10: 310.0685 | DU10: 3.58225 | DV10: 39.8536 | DW10: 353.50435 | DX10: 521.18 | DY10: 2699.2389 | DZ10: 533.58331 | EA10: 451.59914 | EB10: 4205.6014 | ED10: Margin ('000) | EE10: 0 | EF10: 331.95085 | EG10: 18.76733 | EH10: 39.33936 | EI10: 390.05754 | EJ10: 521.18 | EK10: 3031.1898 | EL10: 552.35064 | EM10: 490.9385 | EN10: 4595.6589 | EP10: Margin ('000) | EQ10: 0 | ER10: 171.661 | ES10: 36.5638 | ET10: 28.3842 | EU10: 236.609 | EV10: 521.18 | EW10: 3202.8508 | EX10: 588.91444 | EY10: 519.3227 | EZ10: 4832.2679 | FB10: Margin ('000) | FC10: 0 | FD10: 251.28215 | FE10: 15.50395 | FF10: 52.00252 | FG10: 318.78862 | FH10: 521.18 | FI10: 3454.1329 | FJ10: 604.41839 | FK10: 571.32522 | FL10: 5151.0565 | FN10: Margin ('000) | FO10: 0 | FP10: 186.79185 | FQ10: 24.87485 | FR10: 16.19856 | FS10: 227.86526 | FT10: 521.18 | FU10: 3640.9248 | FV10: 629.29324 | FW10: 587.52378 | FX10: 5378.9218 | FZ10: Margin | GA10: 0 | GB10: 126.95865 | GC10: 119.20055 | GD10: 32.39712 | GE10: 2.2406 | GF10: 280.79692 | GG10: 521.18 | GH10: 3767.8834 | GI10: 748.49379 | GJ10: 619.9209 | GK10: 2.2406 | GL10: 5659.7187 | GN10: Margin | GO10: 938.124 | GP10: 171.10135 | GQ10: 73.4216 | GR10: 50.7812 | GS10: 0 | GT10: 1233.4281 | GU10: 1459.304 | GV10: 3938.9848 | GW10: 821.91539 | GX10: 670.7021 | GY10: 2.2406 | GZ10: 6893.1469 | HB10: Margin | HC10: 0 | HD10: 203.68845 | HE10: 4.9287 | HF10: 50.33124 | HG10: 0 | HH10: 258.94839 | HI10: 1459.304 | HJ10: 4142.6732 | HK10: 826.84409 | HL10: 721.03334 | HM10: 2.2406 | HN10: 7152.0953 | HP10: Margin | HQ10: 0 | HR10: 212.212 | HS10: 35.5089 | HT10: 35.48256 | HU10: 0 | HV10: 283.20346 | HW10: 1459.304 | HX10: 4354.8852 | HY10: 862.35299 | HZ10: 756.5159 | IA10: 2.2406 | IB10: 7435.2987 | ID10: Margin | IE10: 0 | IF10: 274.6954 | IG10: 69.4169 | IH10: 58.4948 | II10: 0 | IJ10: 402.6071 | IK10: 1459.304 | IL10: 4629.5806 | IM10: 931.76989 | IN10: 815.0107 | IO10: 2.2406 | IP10: 7837.9058 | IR10: Margin | IS10: 0 | IT10: 175.672 | IU10: 6.9569 | IV10: 49.10992 | IW10: 0 | IX10: 231.73882 | IY10: 1459.304 | IZ10: 4805.2526 | JA10: 938.72679 | JB10: 864.12062 | JC10: 2.2406 | JD10: 8069.6446 | JF10: Margin | JG10: 790.77 | JH10: 159.068 | JI10: 17.61875 | JJ10: 47.82432 | JK10: 0 | JL10: 1015.2811 | JM10: 2250.074 | JN10: 4964.3206 | JO10: 956.34554 | JP10: 911.94494 | JQ10: 2.2406 | JR10: 9084.9257 | JT10: Margin | JU10: 0 | JV10: 79.3947 | JW10: 47.51075 | JX10: 48.98136 | JY10: 0 | JZ10: 175.88681 | KA10: 2250.074 | KB10: 5043.7153 | KC10: 1003.8563 | KD10: 960.9263 | KE10: 2.2406 | KF10: 9260.8125 | KH10: Margin | KI10: 0 | KJ10: 179.1244 | KK10: 0 | KL10: 48.59568 | KM10: 0 | KN10: 227.72008 | KO10: 2250.074 | KP10: 5222.8397 | KQ10: 1003.8563 | KR10: 1009.522 | KS10: 2.2406 | KT10: 9488.5326
B11: Margin % | C11: 0.35391343 | D11: 0.086122908 | E11: 0.1316794 | F11: 0.10387176 | G11: 0.17748848 | H11: 0.35391343 | I11: 0.086122908 | J11: 0.1316794 | K11: 0.10387176 | L11: 0.17748848 | N11: Margin % | P11: 0.078299399 | Q11: 0.11794262 | R11: 0.10387176 | S11: 0.08769946 | T11: 0.35391343 | U11: 0.081087935 | V11: 0.12280445 | W11: 0.10387176 | X11: 0.12725404 | Z11: Margin % | AB11: 0.078195004 | AC11: 0.13957831 | AD11: 0.10387176 | AE11: 0.088520933 | AF11: 0.35391343 | AG11: 0.080307195 | AH11: 0.12665634 | AI11: 0.10387176 | AJ11: 0.11841325 | AL11: Margin % | AN11: 0.078953279 | AO11: 0.12357187 | AQ11: 0.085633442 | AR11: 0.35391343 | AS11: 0.079917793 | AT11: 0.12582329 | AU11: 0.10387176 | AV11: 0.11064248 | AX11: Margin % | AZ11: 0.079722168 | BB11: 0.10387176 | BC11: 0.08208904 | BD11: 0.35391343 | BE11: 0.079863591 | BF11: 0.12582329 | BG11: 0.10387176 | BH11: 0.10409064 | BJ11: Margin % | BL11: 0.082705477 | BM11: 0.11334152 | BN11: 0.10387176 | BO11: 0.087966067 | BP11: 0.35391343 | BQ11: 0.080185306 | BR11: 0.12423777 | BS11: 0.10387176 | BT11: 0.10238717 | BV11: Margin % | BX11: 0.081771759 | BY11: 0.10085642 | BZ11: 0.10387176 | CA11: 0.086532302 | CB11: 0.35391343 | CC11: 0.08039264 | CD11: 0.12189452 | CE11: 0.10387176 | CF11: 0.10036289 | CH11: Margin % | CJ11: 0.078617187 | CK11: 0.12965983 | CL11: 0.10387176 | CM11: 0.088674243 | CN11: 0.35391343 | CO11: 0.080163504 | CP11: 0.12328365 | CQ11: 0.10387176 | CR11: 0.098847387 | CT11: Margin % | CV11: 0.081974452 | CW11: 0.13375589 | CX11: 0.10387176 | CY11: 0.091752638 | CZ11: 0.35391343 | DA11: 0.080325071 | DB11: 0.12449336 | DC11: 0.10387176 | DD11: 0.098206067 | DF11: Margin % | DH11: 0.079231864 | DI11: 0.11714649 | DJ11: 0.10387176 | DK11: 0.086505505 | DL11: 0.35391343 | DM11: 0.080268924 | DN11: 0.12421094 | DO11: 0.10387176 | DP11: 0.097600219 | DR11: Margin % | DT11: 0.078809889 | DU11: 0.065172403 | DV11: 0.10387176 | DW11: 0.080837353 | DX11: 0.35391343 | DY11: 0.08009858 | DZ11: 0.12346009 | EA11: 0.10387176 | EB11: 0.09592817 | ED11: Margin % | EF11: 0.082665634 | EG11: 0.074024935 | EH11: 0.10387176 | EI11: 0.083922291 | EJ11: 0.35391343 | EK11: 0.080371902 | EL11: 0.12072086 | EM11: 0.10387176 | EN11: 0.094777364 | EP11: Margin % | ER11: 0.081679188 | ES11: 0.12811432 | ET11: 0.10261043 | EU11: 0.088828196 | EV11: 0.35391343 | EW11: 0.080440906 | EX11: 0.12115496 | EY11: 0.10380202 | EZ11: 0.094467573 | FB11: Margin % | FD11: 0.081307375 | FE11: 0.055038679 | FF11: 0.10387176 | FG11: 0.082313607 | FH11: 0.35391343 | FI11: 0.080503316 | FJ11: 0.11753332 | FK11: 0.10380836 | FL11: 0.093612142 | FN11: Margin % | FP11: 0.08109923 | FQ11: 0.083588258 | FR11: 0.10387176 | FS11: 0.082656125 | FT11: 0.35391343 | FU11: 0.080533676 | FV11: 0.11567644 | FW11: 0.10381011 | FX11: 0.093089432 | FZ11: Margin % | GB11: 0.078951321 | GC11: 0.12851194 | GD11: 0.10387176 | GE11: 0.38172959 | GF11: 0.098408806 | GG11: 0.35391343 | GH11: 0.080479326 | GI11: 0.11754612 | GJ11: 0.10381333 | GK11: 0.38172959 | GL11: 0.093339749 | GN11: Margin % | GO11: 0.35391343 | GP11: 0.0807111 | GQ11: 0.11570395 | GR11: 0.10387176 | GT11: 0.20926533 | GU11: 0.35391343 | GV11: 0.080489366 | GW11: 0.11737918 | GX11: 0.10381775 | GY11: 0.38172959 | GZ11: 0.10360997 | HB11: Margin % | HD11: 0.081678157 | HE11: 0.11971131 | HF11: 0.10387176 | HH11: 0.085758225 | HI11: 0.35391343 | HJ11: 0.080547008 | HK11: 0.11739281 | HL11: 0.10382152 | HM11: 0.38172959 | HN11: 0.10283493 | HP11: Margin % | HR11: 0.078926376 | HS11: 0.10736793 | HT11: 0.10387176 | HV11: 0.084260289 | HW11: 0.35391343 | HX11: 0.080466494 | HY11: 0.1169432 | HZ11: 0.10382388 | IA11: 0.38172959 | IB11: 0.10197867 | ID11: Margin % | IF11: 0.082365599 | IG11: 0.10977257 | IH11: 0.10387176 | IJ11: 0.088864185 | IK11: 0.35391343 | IL11: 0.08057673 | IM11: 0.11637685 | IN11: 0.10382731 | IO11: 0.38172959 | IP11: 0.10121142 | IR11: Margin % | IT11: 0.082215117 | IU11: 0.070043721 | IV11: 0.10387176 | IX11: 0.085548719 | IY11: 0.35391343 | IZ11: 0.080635476 | JA11: 0.11580912 | JB11: 0.10382984 | JC11: 0.38172959 | JD11: 0.10068206 | JF11: Margin % | JG11: 0.35653515 | JH11: 0.081994127 | JI11: 0.13336263 | JJ11: 0.10387176 | JL11: 0.21372308 | JM11: 0.35483041 | JN11: 0.080678311 | JO11: 0.11609063 | JP11: 0.10383203 | JQ11: 0.38172959 | JR11: 0.10700708 | JT11: Margin % | JV11: 0.082342718 | JW11: 0.12451385 | JX11: 0.10387176 | JZ11: 0.096783393 | KA11: 0.35483041 | KB11: 0.08070399 | KC11: 0.11646351 | KD11: 0.10383406 | KE11: 0.38172959 | KF11: 0.10679283 | KH11: Margin % | KJ11: 0.078953279 | KL11: 0.10387176 | KN11: 0.083213315 | KO11: 0.35483041 | KP11: 0.080642662 | KQ11: 0.11646351 | KR11: 0.10383587 | KS11: 0.38172959 | KT11: 0.10607148
B12: Rent & White Collar employees Salary doesn't form part of Other Conversion Cost | N12: Rent & White Collar employees Salary doesn't form part of Other Conversion Cost | Z12: Rent & White Collar employees Salary doesn't form part of Other Conversion Cost | AL12: Rent & White Collar employees Salary doesn't form part of Other Conversion Cost | AX12: Rent & White Collar employees Salary doesn't form part of Other Conversion Cost | BJ12: Rent & White Collar employees Salary doesn't form part of Other Conversion Cost | BV12: Rent & White Collar employees Salary doesn't form part of Other Conversion Cost | CH12: Rent & White Collar employees Salary doesn't form part of Other Conversion Cost | CT12: Rent & White Collar employees Salary doesn't form part of Other Conversion Cost | DF12: Rent & White Collar employees Salary doesn't form part of Other Conversion Cost | DR12: Rent & White Collar employees Salary doesn't form part of Other Conversion Cost | ED12: Rent & White Collar employees Salary doesn't form part of Other Conversion Cost | EP12: Rent & White Collar employees Salary doesn't form part of Other Conversion Cost | FB12: Rent & White Collar employees Salary doesn't form part of Other Conversion Cost | FN12: Rent & White Collar employees Salary doesn't form part of Other Conversion Cost | FZ12: Rent & White Collar employees Salary doesn't form part of Other Conversion Cost | GN12: Rent & White Collar employees Salary doesn't form part of Other Conversion Cost | HB12: Rent & White Collar employees Salary doesn't form part of Other Conversion Cost | HP12: Rent & White Collar employees Salary doesn't form part of Other Conversion Cost | ID12: Rent & White Collar employees Salary doesn't form part of Other Conversion Cost | IR12: Rent & White Collar employees Salary doesn't form part of Other Conversion Cost | JF12: Rent & White Collar employees Salary doesn't form part of Other Conversion Cost | JT12: Rent & White Collar employees Salary doesn't form part of Other Conversion Cost | KH12: Rent & White Collar employees Salary doesn't form part of Other Conversion Cost
B14: ASP | C14: =C5/C$4 -> 0.73631 | D14: =D5/D$4 -> 0.39355714 | E14: =E5/E$4 -> 0.73938 | F14: =F5/F$4 -> 0.15471 | G14: =G5/G$4 -> 0.4244604 | H14: =H5/H$4 -> 0.73631 | I14: =I5/I$4 -> 0.39355714 | J14: =J5/J$4 -> 0.73938 | ... L14: =L5/L$4 -> 0.4244604 | N14: ASP | O14: =O5/O$4 -> #DIV/0! | P14: =P5/P$4 -> 0.35530286 | Q14: =Q5/Q$4 -> 0.59254732 | R14: =R5/R$4 -> 0.15471 | S14: =S5/S$4 -> 0.31518642 | T14: =T5/T$4 -> 0.73631 | U14: =U5/U$4 -> 0.36805429 | V14: =V5/V$4 -> 0.63734373 | ... X14: =X5/X$4 -> 0.35550433 | Z14: ASP | AA14: =AA5/AA$4 -> #DIV/0! | AB14: =AB5/AB$4 -> 0.35712 | AC14: =AC5/AC$4 -> 0.86224 | AD14: =AD5/AD$4 -> 0.15471 | AE14: =AE5/AE$4 -> 0.33804748 | AF14: =AF5/AF$4 -> 0.73631 | AG14: =AG5/AG$4 -> 0.36503793 | AH14: =AH5/AH$4 -> 0.67795 | ... AJ14: =AJ5/AJ$4 -> 0.35136287 | AL14: ASP | AM14: =AM5/AM$4 -> #DIV/0! | AN14: =AN5/AN$4 -> 0.35616 | AO14: =AO5/AO$4 -> 0.64504107 | AP14: =AP5/AP$4 -> #DIV/0! | AQ14: =AQ5/AQ$4 -> 0.38175706 | AR14: =AR5/AR$4 -> 0.73631 | AS14: =AS5/AS$4 -> 0.36243951 | AT14: =AT5/AT$4 -> 0.6687355 | ... AV14: =AV5/AV$4 -> 0.35812202 | AX14: ASP | AY14: =AY5/AY$4 -> #DIV/0! | AZ14: =AZ5/AZ$4 -> 0.36449853 | BA14: =BA5/BA$4 -> #DIV/0! | BB14: =BB5/BB$4 -> 0.15471 | BC14: =BC5/BC$4 -> 0.32173909 | BD14: =BD5/BD$4 -> 0.73631 | BE14: =BE5/BE$4 -> 0.36300767 | BF14: =BF5/BF$4 -> 0.6687355 | ... BH14: =BH5/BH$4 -> 0.34906461 | BJ14: ASP | BK14: =BK5/BK$4 -> #DIV/0! | BL14: =BL5/BL$4 -> 0.37485857 | BM14: =BM5/BM$4 -> 0.55559106 | BN14: =BN5/BN$4 -> 0.15471 | BO14: =BO5/BO$4 -> 0.35491976 | BP14: =BP5/BP$4 -> 0.73631 | BQ14: =BQ5/BQ$4 -> 0.36431151 | BR14: =BR5/BR$4 -> 0.65187249 | ... BT14: =BT5/BT$4 -> 0.34967404 | BV14: ASP | BW14: =BW5/BW$4 -> #DIV/0! | BX14: =BX5/BX$4 -> 0.37005982 | BY14: =BY5/BY$4 -> 0.46084965 | BZ14: =BZ5/BZ$4 -> 0.15471 | CA14: =CA5/CA$4 -> 0.31113339 | CB14: =CB5/CB$4 -> 0.73631 | CC14: =CC5/CC$4 -> 0.36505259 | CD14: =CD5/CD$4 -> 0.62587317 | ... CF14: =CF5/CF$4 -> 0.3442299 | CH14: ASP | CI14: =CI5/CI$4 -> #DIV/0! | CJ14: =CJ5/CJ$4 -> 0.35649143 | CK14: =CK5/CK$4 -> 0.71339038 | CL14: =CL5/CL$4 -> 0.15471 | CM14: =CM5/CM$4 -> 0.33692254 | CN14: =CN5/CN$4 -> 0.73631 | CO14: =CO5/CO$4 -> 0.36392467 | CP14: =CP5/CP$4 -> 0.63991666 | ... CR14: =CR5/CR$4 -> 0.34326462 | CT14: ASP | CU14: =CU5/CU$4 -> #DIV/0! | CV14: =CV5/CV$4 -> 0.3710032 | CW14: =CW5/CW$4 -> 0.76815353 | CX14: =CX5/CX$4 -> 0.15471 | CY14: =CY5/CY$4 -> 0.34078086 | CZ14: =CZ5/CZ$4 -> 0.73631 | DA14: =DA5/DA$4 -> 0.3645452 | DB14: =DB5/DB$4 -> 0.6524997 | ... DD14: =DD5/DD$4 -> 0.34303862 | DF14: ASP | DG14: =DG5/DG$4 -> #DIV/0! | DH14: =DH5/DH$4 -> 0.35818343 | DI14: =DI5/DI$4 -> 0.585805 | DJ14: =DJ5/DJ$4 -> 0.15471 | DK14: =DK5/DK$4 -> 0.29982901 | DL14: =DL5/DL$4 -> 0.73631 | DM14: =DM5/DM$4 -> 0.36421296 | DN14: =DN5/DN$4 -> 0.64965644 | ... DP14: =DP5/DP$4 -> 0.34049777 | DR14: ASP | DS14: =DS5/DS$4 -> #DIV/0! | DT14: =DT5/DT$4 -> 0.36261619 | DU14: =DU5/DU$4 -> 0.31409 | DV14: =DV5/DV$4 -> 0.15471 | DW14: =DW5/DW$4 -> 0.32380839 | DX14: =DX5/DX$4 -> 0.73631 | DY14: =DY5/DY$4 -> 0.36402581 | DZ14: =DZ5/DZ$4 -> 0.64094754 | ... EB14: =EB5/EB$4 -> 0.33875621 | ED14: ASP | EE14: =EE5/EE$4 -> #DIV/0! | EF14: =EF5/EF$4 -> 0.38116608 | EG14: =EG5/EG$4 -> 0.30767857 | EH14: =EH5/EH$4 -> 0.15471 | EI14: =EI5/EI$4 -> 0.33662938 | EJ14: =EJ5/EJ$4 -> 0.73631 | EK14: =EK5/EK$4 -> 0.36577711 | EL14: =EL5/EL$4 -> 0.60465659 | ... EN14: =EN5/EN$4 -> 0.33855118 | EP14: ASP | EQ14: =EQ5/EQ$4 -> #DIV/0! | ER14: =ER5/ER$4 -> 0.3752945 | ES14: =ES5/ES$4 -> 0.67952333 | ET14: =ET5/ET$4 -> 0.16082616 | EU14: =EU5/EU$4 -> 0.34414341 | EV14: =EV5/EV$4 -> 0.73631 | EW14: =EW5/EW$4 -> 0.36626739 | EX14: =EX5/EX$4 -> 0.60859349 | ... EZ14: =EZ5/EZ$4 -> 0.33883789 | FB14: ASP | FC14: =FC5/FC$4 -> #DIV/0! | FD14: =FD5/FD$4 -> 0.37574723 | FE14: =FE5/FE$4 -> 0.30955154 | FF14: =FF5/FF$4 -> 0.15471 | FG14: =FG5/FG$4 -> 0.31305913 | FH14: =FH5/FH$4 -> 0.73631 | FI14: =FI5/FI$4 -> 0.36693419 | FJ14: =FJ5/FJ$4 -> 0.57800698 | ... FL14: =FL5/FL$4 -> 0.33688542 | FN14: ASP | FO14: =FO5/FO$4 -> #DIV/0! | FP14: =FP5/FP$4 -> 0.37390432 | FQ14: =FQ5/FQ$4 -> 0.38647773 | FR14: =FR5/FR$4 -> 0.15471 | FS14: =FS5/FS$4 -> 0.34728976 | FT14: =FT5/FT$4 -> 0.73631 | FU14: =FU5/FU$4 -> 0.367283 | FV14: =FV5/FV$4 -> 0.56275121 | ... FX14: =FX5/FX$4 -> 0.33736763 | FZ14: ASP | GA14: =GA5/GA$4 -> #DIV/0! | GB14: =GB5/GB$4 -> 0.35616 | GC14: =GC5/GC$4 -> 0.50191803 | GD14: =GD5/GD$4 -> 0.15471 | GE14: =GE5/GE$4 -> 0.14674 | GF14: =GF5/GF$4 -> 0.33892052 | GG14: =GG5/GG$4 -> 0.73631 | GH14: =GH5/GH$4 -> 0.36688945 | ... GL14: =GL5/GL$4 -> 0.33744039 | GN14: ASP | GO14: =GO5/GO$4 -> 0.73631 | GP14: =GP5/GP$4 -> 0.36932463 | GQ14: =GQ5/GQ$4 -> 0.46488231 | GR14: =GR5/GR$4 -> 0.15471 | GS14: =GS5/GS$4 -> #DIV/0! | GT14: =GT5/GT$4 -> 0.42510547 | GU14: =GU5/GU$4 -> 0.73631 | GV14: =GV5/GV$4 -> 0.36699427 | ... GZ14: =GZ5/GZ$4 -> 0.34372003 | HB14: ASP | HC14: =HC5/HC$4 -> #DIV/0! | HD14: =HD5/HD$4 -> 0.37699069 | HE14: =HE5/HE$4 -> 0.588165 | HF14: =HF5/HF$4 -> 0.15471 | HG14: =HG5/HG$4 -> #DIV/0! | HH14: =HH5/HH$4 -> 0.30758039 | HI14: =HI5/HI$4 -> 0.73631 | HJ14: =HJ5/HJ$4 -> 0.36746673 | ... HN14: =HN5/HN$4 -> 0.34197556 | HP14: ASP | HQ14: =HQ5/HQ$4 -> #DIV/0! | HR14: =HR5/HR$4 -> 0.37291728 | HS14: =HS5/HS$4 -> 0.36343038 | HT14: =HT5/HT$4 -> 0.15471 | HU14: =HU5/HU$4 -> #DIV/0! | HV14: =HV5/HV$4 -> 0.32543134 | HW14: =HW5/HW$4 -> 0.73631 | HX14: =HX5/HX$4 -> 0.36773375 | ... IB14: =IB5/IB$4 -> 0.341176 | ID14: ASP | IE14: =IE5/IE$4 -> #DIV/0! | IF14: =IF5/IF$4 -> 0.38268209 | IG14: =IG5/IG$4 -> 0.37641083 | IH14: =IH5/IH$4 -> 0.15471 | II14: =II5/II$4 -> #DIV/0! | IJ14: =IJ5/IJ$4 -> 0.32280648 | IK14: =IK5/IK$4 -> 0.73631 | IL14: =IL5/IL$4 -> 0.36856945 | ... IP14: =IP5/IP$4 -> 0.34004392 | IR14: ASP | IS14: =IS5/IS$4 -> #DIV/0! | IT14: =IT5/IT$4 -> 0.38156 | IU14: =IU5/IU$4 -> 0.34849912 | IV14: =IV5/IV$4 -> 0.15471 | IW14: =IW5/IW$4 -> #DIV/0! | IX14: =IX5/IX$4 -> 0.30296969 | IY14: =IY5/IY$4 -> 0.73631 | IZ14: =IZ5/IZ$4 -> 0.36901993 | ... JD14: =JD5/JD$4 -> 0.33864337 | JF14: ASP | JG14: =JG5/JG$4 -> 0.73931 | JH14: =JH5/JH$4 -> 0.3796463 | JI14: =JI5/JI$4 -> 0.61447256 | JJ14: =JJ5/JJ$4 -> 0.15471 | JK14: =JK5/JK$4 -> #DIV/0! | JL14: =JL5/JL$4 -> 0.42035671 | JM14: =JM5/JM$4 -> 0.73735651 | JN14: =JN5/JN$4 -> 0.36934586 | ... JR14: =JR5/JR$4 -> 0.34236723 | JT14: ASP | JU14: =JU5/JU$4 -> #DIV/0! | JV14: =JV5/JV$4 -> 0.38261833 | JW14: =JW5/JW$4 -> 0.43608 | JX14: =JX5/JX$4 -> 0.15471 | JY14: =JY5/JY$4 -> #DIV/0! | JZ14: =JZ5/JZ$4 -> 0.28206182 | KA14: =KA5/KA$4 -> 0.73735651 | KB14: =KB5/KB$4 -> 0.36954364 | ... KF14: =KF5/KF$4 -> 0.34084006 | KH14: ASP | KI14: =KI5/KI$4 -> #DIV/0! | KJ14: =KJ5/KJ$4 -> 0.35616 | KK14: =KK5/KK$4 -> #DIV/0! | KL14: =KL5/KL$4 -> 0.15471 | KM14: =KM5/KM$4 -> #DIV/0! | KN14: =KN5/KN$4 -> 0.29131171 | KO14: =KO5/KO$4 -> 0.73735651 | KP14: =KP5/KP$4 -> 0.36905783 | ... KT14: =KT5/KT$4 -> 0.33907645
B15: PGI pu | C15: =C6/C$4 -> 0.47572 | D15: =D6/D$4 -> 0.35966286 | E15: =E6/E$4 -> 0.64201889 | F15: =F6/F$4 -> 0.13864 | G15: =G6/G$4 -> 0.34912356 | H15: =H6/H$4 -> 0.47572 | I15: =I6/I$4 -> 0.35966286 | J15: =J6/J$4 -> 0.64201889 | ... L15: =L6/L$4 -> 0.34912356 | N15: PGI pu | O15: =O6/O$4 -> #DIV/0! | P15: =P6/P$4 -> 0.32748286 | Q15: =Q6/Q$4 -> 0.52266073 | R15: =R6/R$4 -> 0.13864 | S15: =S6/S$4 -> 0.28754474 | T15: =T6/T$4 -> 0.47572 | U15: =U6/U$4 -> 0.33820952 | V15: =V6/V$4 -> 0.55907508 | ... X15: =X6/X$4 -> 0.31026497 | Z15: PGI pu | AA15: =AA6/AA$4 -> #DIV/0! | AB15: =AB6/AB$4 -> 0.329195 | AC15: =AC6/AC$4 -> 0.74189 | AD15: =AD6/AD$4 -> 0.13864 | AE15: =AE6/AE$4 -> 0.3081232 | AF15: =AF6/AF$4 -> 0.47572 | AG15: =AG6/AG$4 -> 0.33572276 | AH15: =AH6/AH$4 -> 0.59208333 | ... AJ15: =AJ6/AJ$4 -> 0.30975685 | AL15: PGI pu | AM15: =AM6/AM$4 -> #DIV/0! | AN15: =AN6/AN$4 -> 0.32804 | AO15: =AO6/AO$4 -> 0.56533214 | AP15: =AP6/AP$4 -> #DIV/0! | AQ15: =AQ6/AQ$4 -> 0.34906589 | AR15: =AR6/AR$4 -> 0.47572 | AS15: =AS6/AS$4 -> 0.33347415 | AT15: =AT6/AT$4 -> 0.584593 | ... AV15: =AV6/AV$4 -> 0.31849852 | AX15: PGI pu | AY15: =AY6/AY$4 -> #DIV/0! | AZ15: =AZ6/AZ$4 -> 0.33543992 | BA15: =BA6/BA$4 -> #DIV/0! | BB15: =BB6/BB$4 -> 0.13864 | BC15: =BC6/BC$4 -> 0.29532783 | BD15: =BD6/BD$4 -> 0.47572 | BE15: =BE6/BE$4 -> 0.33401658 | BF15: =BF6/BF$4 -> 0.584593 | ... BH15: =BH6/BH$4 -> 0.31273025 | BJ15: PGI pu | BK15: =BK6/BK$4 -> #DIV/0! | BL15: =BL6/BL$4 -> 0.34385571 | BM15: =BM6/BM$4 -> 0.49261953 | BN15: =BN6/BN$4 -> 0.13864 | BO15: =BO6/BO$4 -> 0.32369887 | BP15: =BP6/BP$4 -> 0.47572 | BQ15: =BQ6/BQ$4 -> 0.33509908 | BR15: =BR6/BR$4 -> 0.57088531 | ... BT15: =BT6/BT$4 -> 0.3138719 | BV15: PGI pu | BW15: =BW6/BW$4 -> #DIV/0! | BX15: =BX6/BX$4 -> 0.33979938 | BY15: =BY6/BY$4 -> 0.41437 | BZ15: =BZ6/BZ$4 -> 0.13864 | CA15: =CA6/CA$4 -> 0.2842103 | CB15: =CB6/CB$4 -> 0.47572 | CC15: =CC6/CC$4 -> 0.33570505 | CD15: =CD6/CD$4 -> 0.54958266 | ... CF15: =CF6/CF$4 -> 0.30968199 | CH15: PGI pu | CI15: =CI6/CI$4 -> #DIV/0! | CJ15: =CJ6/CJ$4 -> 0.32846508 | CK15: =CK6/CK$4 -> 0.62089231 | CL15: =CL6/CL$4 -> 0.13864 | CM15: =CM6/CM$4 -> 0.30704619 | CN15: =CN6/CN$4 -> 0.47572 | CO15: =CO6/CO$4 -> 0.33475119 | CP15: =CP6/CP$4 -> 0.5610254 | ... CR15: =CR6/CR$4 -> 0.30933381 | CT15: PGI pu | CU15: =CU6/CU$4 -> #DIV/0! | CV15: =CV6/CV$4 -> 0.34059041 | CW15: =CW6/CW$4 -> 0.66540848 | CX15: =CX6/CX$4 -> 0.13864 | CY15: =CY6/CY$4 -> 0.30951332 | CZ15: =CZ6/CZ$4 -> 0.47572 | DA15: =DA6/DA$4 -> 0.33526308 | DB15: =DB6/DB$4 -> 0.57126782 | ... DD15: =DD6/DD$4 -> 0.30935014 | DF15: PGI pu | DG15: =DG6/DG$4 -> #DIV/0! | DH15: =DH6/DH$4 -> 0.32980389 | DI15: =DI6/DI$4 -> 0.51718 | DJ15: =DJ6/DJ$4 -> 0.13864 | DK15: =DK6/DK$4 -> 0.27389215 | DL15: =DL6/DL$4 -> 0.47572 | DM15: =DM6/DM$4 -> 0.33497797 | DN15: =DN6/DN$4 -> 0.56896201 | ... DP15: =DP6/DP$4 -> 0.30726512 | DR15: PGI pu | DS15: =DS6/DS$4 -> #DIV/0! | DT15: =DT6/DT$4 -> 0.33403845 | DU15: =DU6/DU$4 -> 0.29362 | DV15: =DV6/DV$4 -> 0.13864 | DW15: =DW6/DW$4 -> 0.29763257 | DX15: =DX6/DX$4 -> 0.47572 | DY15: =DY6/DY$4 -> 0.33486786 | DZ15: =DZ6/DZ$4 -> 0.5618161 | ... EB15: =EB6/EB$4 -> 0.30625994 | ED15: PGI pu | EE15: =EE6/EE$4 -> #DIV/0! | EF15: =EF6/EF$4 -> 0.34965674 | EG15: =EG6/EG$4 -> 0.28490268 | EH15: =EH6/EH$4 -> 0.13864 | EI15: =EI6/EI$4 -> 0.30837867 | EJ15: =EJ6/EJ$4 -> 0.47572 | EK15: =EK6/EK$4 -> 0.3363789 | EL15: =EL6/EL$4 -> 0.53166192 | ... EN15: =EN6/EN$4 -> 0.30646419 | EP15: PGI pu | EQ15: =EQ6/EQ$4 -> #DIV/0! | ER15: =ER6/ER$4 -> 0.34464075 | ES15: =ES6/ES$4 -> 0.59246667 | ET15: =ET6/ET$4 -> 0.14432372 | EU15: =EU6/EU$4 -> 0.31357377 | EV15: =EV6/EV$4 -> 0.47572 | EW15: =EW6/EW$4 -> 0.33680451 | EX15: =EX6/EX$4 -> 0.53485937 | ... EZ15: =EZ6/EZ$4 -> 0.3068287 | FB15: PGI pu | FC15: =FC6/FC$4 -> #DIV/0! | FD15: =FD6/FD$4 -> 0.34519621 | FE15: =FE6/FE$4 -> 0.29251423 | FF15: =FF6/FF$4 -> 0.13864 | FG15: =FG6/FG$4 -> 0.2872901 | FH15: =FH6/FH$4 -> 0.47572 | FI15: =FI6/FI$4 -> 0.33739477 | FJ15: =FJ6/FJ$4 -> 0.5100719 | ... FL15: =FL6/FL$4 -> 0.30534886 | FN15: PGI pu | FO15: =FO6/FO$4 -> #DIV/0! | FP15: =FP6/FP$4 -> 0.34358097 | FQ15: =FQ6/FQ$4 -> 0.35417273 | FR15: =FR6/FR$4 -> 0.13864 | FS15: =FS6/FS$4 -> 0.31858414 | FT15: =FT6/FT$4 -> 0.47572 | FU15: =FU6/FU$4 -> 0.33770435 | FV15: =FV6/FV$4 -> 0.49765416 | ... FX15: =FX6/FX$4 -> 0.30596227 | FZ15: PGI pu | GA15: =GA6/GA$4 -> #DIV/0! | GB15: =GB6/GB$4 -> 0.3280407 | GC15: =GC6/GC$4 -> 0.43741557 | GD15: =GD6/GD$4 -> 0.13864 | GE15: =GE6/GE$4 -> 0.090725 | GF15: =GF6/GF$4 -> 0.30556776 | GG15: =GG6/GG$4 -> 0.47572 | GH15: =GH6/GH$4 -> 0.33736243 | ... GL15: =GL6/GL$4 -> 0.30594378 | GN15: PGI pu | GO15: =GO6/GO$4 -> 0.47572 | GP15: =GP6/GP$4 -> 0.33951604 | GQ15: =GQ6/GQ$4 -> 0.41109359 | GR15: =GR6/GR$4 -> 0.13864 | GS15: =GS6/GS$4 -> #DIV/0! | GT15: =GT6/GT$4 -> 0.33614563 | GU15: =GU6/GU$4 -> 0.47572 | GV15: =GV6/GV$4 -> 0.33745514 | ... GZ15: =GZ6/GZ$4 -> 0.30810721 | HB15: PGI pu | HC15: =HC6/HC$4 -> #DIV/0! | HD15: =HD6/HD$4 -> 0.34619878 | HE15: =HE6/HE$4 -> 0.517755 | HF15: =HF6/HF$4 -> 0.13864 | HG15: =HG6/HG$4 -> #DIV/0! | HH15: =HH6/HH$4 -> 0.28120284 | HI15: =HI6/HI$4 -> 0.47572 | HJ15: =HJ6/HJ$4 -> 0.33786838 | ... HN15: =HN6/HN$4 -> 0.30680853 | HP15: PGI pu | HQ15: =HQ6/HQ$4 -> #DIV/0! | HR15: =HR6/HR$4 -> 0.34348427 | HS15: =HS6/HS$4 -> 0.32440962 | HT15: =HT6/HT$4 -> 0.13864 | HU15: =HU6/HU$4 -> #DIV/0! | HV15: =HV6/HV$4 -> 0.29801041 | HW15: =HW6/HW$4 -> 0.47572 | HX15: =HX6/HX$4 -> 0.33814351 | ... IB15: =IB6/IB$4 -> 0.30638332 | ID15: PGI pu | IE15: =IE6/IE$4 -> #DIV/0! | IF15: =IF6/IF$4 -> 0.35116225 | IG15: =IG6/IG$4 -> 0.33509125 | IH15: =IH6/IH$4 -> 0.13864 | II15: =II6/II$4 -> #DIV/0! | IJ15: =IJ6/IJ$4 -> 0.29412055 | IK15: =IK6/IK$4 -> 0.47572 | IL15: =IL6/IL$4 -> 0.33887133 | ... IP15: =IP6/IP$4 -> 0.3056276 | IR15: PGI pu | IS15: =IS6/IS$4 -> #DIV/0! | IT15: =IT6/IT$4 -> 0.35019 | IU15: =IU6/IU$4 -> 0.32408895 | IV15: =IV6/IV$4 -> 0.13864 | IW15: =IW6/IW$4 -> #DIV/0! | IX15: =IX6/IX$4 -> 0.27705102 | IY15: =IY6/IY$4 -> 0.47572 | IZ15: =IZ6/IZ$4 -> 0.33926383 | ... JD15: =JD6/JD$4 -> 0.30454806 | JF15: PGI pu | JG15: =JG6/JG$4 -> 0.47572 | JH15: =JH6/JH$4 -> 0.34851753 | JI15: =JI6/JI$4 -> 0.53252488 | JJ15: =JJ6/JJ$4 -> 0.13864 | JK15: =JK6/JK$4 -> #DIV/0! | JL15: =JL6/JL$4 -> 0.33051678 | JM15: =JM6/JM$4 -> 0.47572 | JN15: =JN6/JN$4 -> 0.33954766 | ... JR15: =JR6/JR$4 -> 0.30573151 | JT15: PGI pu | JU15: =JU6/JU$4 -> #DIV/0! | JV15: =JV6/JV$4 -> 0.3511125 | JW15: =JW6/JW$4 -> 0.381782 | JX15: =JX6/JX$4 -> 0.13864 | JY15: =JY6/JY$4 -> #DIV/0! | JZ15: =JZ6/JZ$4 -> 0.25476292 | KA15: =KA6/KA$4 -> 0.47572 | KB15: =KB6/KB$4 -> 0.33971999 | ... KF15: =KF6/KF$4 -> 0.30444079 | KH15: PGI pu | KI15: =KI6/KI$4 -> #DIV/0! | KJ15: =KJ6/KJ$4 -> 0.32804 | KK15: =KK6/KK$4 -> #DIV/0! | KL15: =KL6/KL$4 -> 0.13864 | KM15: =KM6/KM$4 -> #DIV/0! | KN15: =KN6/KN$4 -> 0.2670707 | KO15: =KO6/KO$4 -> 0.47572 | KP15: =KP6/KP$4 -> 0.33929602 | ... KT15: =KT6/KT$4 -> 0.30311011
B16: GM pu | C16: =C14-C15 -> 0.26059 | D16: =D14-D15 -> 0.033894286 | E16: =E14-E15 -> 0.097361111 | F16: =F14-F15 -> 0.01607 | G16: =G14-G15 -> 0.075336832 | H16: =H14-H15 -> 0.26059 | I16: =I14-I15 -> 0.033894286 | J16: =J14-J15 -> 0.097361111 | K16: =K14-K15 -> 0.01607 | L16: =L7/L$4 -> 0.30831224 | N16: GM pu | O16: =O14-O15 -> #DIV/0! | P16: =P14-P15 -> 0.02782 | Q16: =Q14-Q15 -> 0.069886585 | R16: =R14-R15 -> 0.01607 | S16: =S14-S15 -> 0.027641679 | T16: =T14-T15 -> 0.26059 | U16: =U14-U15 -> 0.029844762 | V16: =V14-V15 -> 0.078268644 | W16: =W14-W15 -> 0.01607 | X16: =X7/X$4 -> 0.27174927 | Z16: GM pu | AA16: =AA14-AA15 -> #DIV/0! | AB16: =AB14-AB15 -> 0.027925 | AC16: =AC14-AC15 -> 0.12035 | AD16: =AD14-AD15 -> 0.01607 | AE16: =AE14-AE15 -> 0.029924278 | AF16: =AF14-AF15 -> 0.26059 | AG16: =AG14-AG15 -> 0.029315172 | AH16: =AH14-AH15 -> 0.085866667 | AI16: =AI14-AI15 -> 0.01607 | AJ16: =AJ7/AJ$4 -> 0.27080327 | AL16: GM pu | AM16: =AM14-AM15 -> #DIV/0! | AN16: =AN14-AN15 -> 0.02812 | AO16: =AO14-AO15 -> 0.079708929 | AP16: =AP14-AP15 -> #DIV/0! | AQ16: =AQ14-AQ15 -> 0.032691171 | AR16: =AR14-AR15 -> 0.26059 | AS16: =AS14-AS15 -> 0.028965366 | AT16: =AT14-AT15 -> 0.0841425 | AU16: =AU14-AU15 -> 0.01607 | AV16: =AV7/AV$4 -> 0.27715024 | AX16: GM pu | AY16: =AY14-AY15 -> #DIV/0! | AZ16: =AZ14-AZ15 -> 0.029058613 | BA16: =BA14-BA15 -> #DIV/0! | BB16: =BB14-BB15 -> 0.01607 | BC16: =BC14-BC15 -> 0.026411253 | BD16: =BD14-BD15 -> 0.26059 | BE16: =BE14-BE15 -> 0.028991096 | BF16: =BF14-BF15 -> 0.0841425 | BG16: =BG14-BG15 -> 0.01607 | BH16: =BH7/BH$4 -> 0.2715413 | BJ16: GM pu | BK16: =BK14-BK15 -> #DIV/0! | BL16: =BL14-BL15 -> 0.031002857 | BM16: =BM14-BM15 -> 0.062971533 | BN16: =BN14-BN15 -> 0.01607 | BO16: =BO14-BO15 -> 0.031220896 | BP16: =BP14-BP15 -> 0.26059 | BQ16: =BQ14-BQ15 -> 0.02921243 | BR16: =BR14-BR15 -> 0.080987187 | BS16: =BS14-BS15 -> 0.01607 | BT16: =BT7/BT$4 -> 0.27250033 | BV16: GM pu | BW16: =BW14-BW15 -> #DIV/0! | BX16: =BX14-BX15 -> 0.030260442 | BY16: =BY14-BY15 -> 0.046479645 | BZ16: =BZ14-BZ15 -> 0.01607 | CA16: =CA14-CA15 -> 0.026923089 | CB16: =CB14-CB15 -> 0.26059 | CC16: =CC14-CC15 -> 0.029347541 | CD16: =CD14-CD15 -> 0.076290508 | CE16: =CE14-CE15 -> 0.01607 | CF16: =CF7/CF$4 -> 0.26895556 | CH16: GM pu | CI16: =CI14-CI15 -> #DIV/0! | CJ16: =CJ14-CJ15 -> 0.028026353 | CK16: =CK14-CK15 -> 0.092498077 | CL16: =CL14-CL15 -> 0.01607 | CM16: =CM14-CM15 -> 0.029876351 | CN16: =CN14-CN15 -> 0.26059 | CO16: =CO14-CO15 -> 0.029173477 | CP16: =CP14-CP15 -> 0.078891264 | CQ16: =CQ14-CQ15 -> 0.01607 | CR16: =CR7/CR$4 -> 0.26866514 | CT16: GM pu | CU16: =CU14-CU15 -> #DIV/0! | CV16: =CV14-CV15 -> 0.030412784 | CW16: =CW14-CW15 -> 0.10274506 | CX16: =CX14-CX15 -> 0.01607 | CY16: =CY14-CY15 -> 0.031267543 | CZ16: =CZ14-CZ15 -> 0.26059 | DA16: =DA14-DA15 -> 0.029282119 | DB16: =DB14-DB15 -> 0.08123188 | DC16: =DC14-DC15 -> 0.01607 | DD16: =DD7/DD$4 -> 0.26884831 | DF16: GM pu | DG16: =DG14-DG15 -> #DIV/0! | DH16: =DH14-DH15 -> 0.028379541 | DI16: =DI14-DI15 -> 0.068625 | DJ16: =DJ14-DJ15 -> 0.01607 | DK16: =DK14-DK15 -> 0.02593686 | DL16: =DL14-DL15 -> 0.26059 | DM16: =DM14-DM15 -> 0.029234982 | DN16: =DN14-DN15 -> 0.080694437 | DO16: =DO14-DO15 -> 0.01607 | DP16: =DP7/DP$4 -> 0.26706959 | DR16: GM pu | DS16: =DS14-DS15 -> #DIV/0! | DT16: =DT14-DT15 -> 0.028577742 | DU16: =DU14-DU15 -> 0.02047 | DV16: =DV14-DV15 -> 0.01607 | DW16: =DW14-DW15 -> 0.026175813 | DX16: =DX14-DX15 -> 0.26059 | DY16: =DY14-DY15 -> 0.02915795 | DZ16: =DZ14-DZ15 -> 0.079131441 | EA16: =EA14-EA15 -> 0.01607 | EB16: =EB7/EB$4 -> 0.2659221 | ED16: GM pu | EE16: =EE14-EE15 -> #DIV/0! | EF16: =EF14-EF15 -> 0.031509336 | EG16: =EG14-EG15 -> 0.022775886 | EH16: =EH14-EH15 -> 0.01607 | EI16: =EI14-EI15 -> 0.028250709 | EJ16: =EJ14-EJ15 -> 0.26059 | EK16: =EK14-EK15 -> 0.029398202 | EL16: =EL14-EL15 -> 0.072994666 | EM16: =EM14-EM15 -> 0.01607 | EN16: =EN7/EN$4 -> 0.26599221 | EP16: GM pu | EQ16: =EQ14-EQ15 -> #DIV/0! | ER16: =ER14-ER15 -> 0.03065375 | ES16: =ES14-ES15 -> 0.087056667 | ET16: =ET14-ET15 -> 0.016502442 | EU16: =EU14-EU15 -> 0.030569638 | EV16: =EV14-EV15 -> 0.26059 | EW16: =EW14-EW15 -> 0.02946288 | EX16: =EX14-EX15 -> 0.073734123 | EY16: =EY14-EY15 -> 0.016093049 | EZ16: =EZ7/EZ$4 -> 0.26637629 | FB16: GM pu | FC16: =FC14-FC15 -> #DIV/0! | FD16: =FD14-FD15 -> 0.030551021 | FE16: =FE14-FE15 -> 0.017037308 | FF16: =FF14-FF15 -> 0.01607 | FG16: =FG14-FG15 -> 0.025769026 | FH16: =FH14-FH15 -> 0.26059 | FI16: =FI14-FI15 -> 0.029539419 | FJ16: =FJ14-FJ15 -> 0.067935078 | FK16: =FK14-FK15 -> 0.016090949 | FL16: =FL7/FL$4 -> 0.2650647 | FN16: GM pu | FO16: =FO14-FO15 -> #DIV/0! | FP16: =FP14-FP15 -> 0.030323352 | FQ16: =FQ14-FQ15 -> 0.032305 | FR16: =FR14-FR15 -> 0.01607 | FS16: =FS14-FS15 -> 0.028705626 | FT16: =FT14-FT15 -> 0.26059 | FU16: =FU14-FU15 -> 0.02957865 | FV16: =FV14-FV15 -> 0.065097056 | FW16: =FW14-FW15 -> 0.01609037 | FX16: =FX7/FX$4 -> 0.26550441 | FZ16: GM pu | GA16: =GA14-GA15 -> #DIV/0! | GB16: =GB14-GB15 -> 0.028119302 | GC16: =GC14-GC15 -> 0.064502462 | GD16: =GD14-GD15 -> 0.01607 | GE16: =GE14-GE15 -> 0.056015 | GF16: =GF14-GF15 -> 0.033352764 | GG16: =GG14-GG15 -> 0.26059 | GH16: =GH14-GH15 -> 0.029527016 | ... GJ16: =GJ14-GJ15 -> 0.016089304 | GK16: =GK7/GK$4 -> 0.084125 | GL16: =GL7/GL$4 -> 0.26565748 | GN16: GM pu | GO16: =GO14-GO15 -> 0.26059 | GP16: =GP14-GP15 -> 0.029808598 | GQ16: =GQ14-GQ15 -> 0.053788718 | GR16: =GR14-GR15 -> 0.01607 | GS16: =GS14-GS15 -> #DIV/0! | GT16: =GT14-GT15 -> 0.088959838 | GU16: =GU14-GU15 -> 0.26059 | GV16: =GV14-GV15 -> 0.029539137 | ... GX16: =GX14-GX15 -> 0.016087841 | GY16: =GY7/GY$4 -> 0.084125 | GZ16: =GZ7/GZ$4 -> 0.26785769 | HB16: GM pu | HC16: =HC14-HC15 -> #DIV/0! | HD16: =HD14-HD15 -> 0.030791905 | HE16: =HE14-HE15 -> 0.07041 | HF16: =HF14-HF15 -> 0.01607 | HG16: =HG14-HG15 -> #DIV/0! | HH16: =HH14-HH15 -> 0.026377548 | HI16: =HI14-HI15 -> 0.26059 | HJ16: =HJ14-HJ15 -> 0.029598345 | ... HL16: =HL14-HL15 -> 0.016086595 | HM16: =HM7/HM$4 -> 0.084125 | HN16: =HN7/HN$4 -> 0.2667744 | HP16: GM pu | HQ16: =HQ14-HQ15 -> #DIV/0! | HR16: =HR14-HR15 -> 0.02943301 | HS16: =HS14-HS15 -> 0.039020769 | HT16: =HT14-HT15 -> 0.01607 | HU16: =HU14-HU15 -> #DIV/0! | HV16: =HV14-HV15 -> 0.027420939 | HW16: =HW14-HW15 -> 0.26059 | HX16: =HX14-HX15 -> 0.029590246 | ... HZ16: =HZ14-HZ15 -> 0.016085815 | IA16: =IA7/IA$4 -> 0.084125 | IB16: =IB7/IB$4 -> 0.26638291 | ID16: GM pu | IE16: =IE14-IE15 -> #DIV/0! | IF16: =IF14-IF15 -> 0.031519839 | IG16: =IG14-IG15 -> 0.041319583 | IH16: =IH14-IH15 -> 0.01607 | II16: =II14-II15 -> #DIV/0! | IJ16: =IJ14-IJ15 -> 0.028685935 | IK16: =IK14-IK15 -> 0.26059 | IL16: =IL14-IL15 -> 0.029698121 | ... IN16: =IN14-IN15 -> 0.016084679 | IO16: =IO7/IO$4 -> 0.084125 | IP16: =IP7/IP$4 -> 0.26581153 | IR16: GM pu | IS16: =IS14-IS15 -> #DIV/0! | IT16: =IT14-IT15 -> 0.03137 | IU16: =IU14-IU15 -> 0.024410175 | IV16: =IV14-IV15 -> 0.01607 | IW16: =IW14-IW15 -> #DIV/0! | IX16: =IX14-IX15 -> 0.025918669 | IY16: =IY14-IY15 -> 0.26059 | IZ16: =IZ14-IZ15 -> 0.029756097 | ... JB16: =JB14-JB15 -> 0.016083844 | JC16: =JC7/JC$4 -> 0.084125 | JD16: =JD7/JD$4 -> 0.26492123 | JF16: GM pu | JG16: =JG14-JG15 -> 0.26359 | JH16: =JH14-JH15 -> 0.031128767 | JI16: =JI14-JI15 -> 0.081947674 | JJ16: =JJ14-JJ15 -> 0.01607 | JK16: =JK14-JK15 -> #DIV/0! | JL16: =JL14-JL15 -> 0.089839932 | JM16: =JM14-JM15 -> 0.26163651 | JN16: =JN14-JN15 -> 0.029798201 | ... JP16: =JP14-JP15 -> 0.016083118 | JQ16: =JQ7/JQ$4 -> 0.084125 | JR16: =JR7/JR$4 -> 0.26614452 | JT16: GM pu | JU16: =JU14-JU15 -> #DIV/0! | JV16: =JV14-JV15 -> 0.031505833 | JW16: =JW14-JW15 -> 0.054298 | JX16: =JX14-JX15 -> 0.01607 | JY16: =JY14-JY15 -> #DIV/0! | JZ16: =JZ14-JZ15 -> 0.0272989 | KA16: =KA14-KA15 -> 0.26163651 | KB16: =KB14-KB15 -> 0.029823646 | ... KD16: =KD14-KD15 -> 0.016082449 | KE16: =KE7/KE$4 -> 0.084125 | KF16: =KF7/KF$4 -> 0.26516123 | KH16: GM pu | KI16: =KI14-KI15 -> #DIV/0! | KJ16: =KJ14-KJ15 -> 0.02812 | KK16: =KK14-KK15 -> #DIV/0! | KL16: =KL14-KL15 -> 0.01607 | KM16: =KM14-KM15 -> #DIV/0! | KN16: =KN14-KN15 -> 0.024241013 | KO16: =KO14-KO15 -> 0.26163651 | KP16: =KP14-KP15 -> 0.029761806 | ... KR16: =KR14-KR15 -> 0.016081849 | KS16: =KS7/KS$4 -> 0.084125 | KT16: =KT7/KT$4 -> 0.26395981
B17: BOM pu | C17: =C7/C4 -> 0.42367 | D17: =D7/D4 -> 0.31022286 | E17: =E7/E4 -> 0.58850333 | F17: =F7/F4 -> 0.13204 | G17: =G7/G4 -> 0.30831224 | H17: =H7/H4 -> 0.42367 | I17: =I7/I4 -> 0.31022286 | J17: =J7/J4 -> 0.58850333 | ... L17: =L7/L4 -> 0.30831224 | N17: BOM pu | O17: =O7/O4 -> #DIV/0! | P17: =P7/P4 -> 0.27804286 | Q17: =Q7/Q4 -> 0.47053683 | R17: =R7/R4 -> 0.13204 | S17: =S7/S4 -> 0.25037127 | T17: =T7/T4 -> 0.42367 | U17: =U7/U4 -> 0.28876952 | V17: =V7/V4 -> 0.50652661 | ... X17: =X7/X4 -> 0.27174927 | Z17: BOM pu | AA17: =AA7/AA4 -> #DIV/0! | AB17: =AB7/AB4 -> 0.279755 | AC17: =AC7/AC4 -> 0.68721 | AD17: =AD7/AD4 -> 0.13204 | AE17: =AE7/AE4 -> 0.26776176 | AF17: =AF7/AF4 -> 0.42367 | AG17: =AG7/AG4 -> 0.28628276 | AH17: =AH7/AH4 -> 0.53915 | ... AJ17: =AJ7/AJ4 -> 0.27080327 | AL17: BOM pu | AM17: =AM7/AM4 -> #DIV/0! | AN17: =AN7/AN4 -> 0.2786 | AO17: =AO7/AO4 -> 0.51271071 | AP17: =AP7/AP4 -> #DIV/0! | AQ17: =AQ7/AQ4 -> 0.29934399 | AR17: =AR7/AR4 -> 0.42367 | AS17: =AS7/AS4 -> 0.28403415 | AT17: =AT7/AT4 -> 0.531747 | ... AV17: =AV7/AV4 -> 0.27715024 | AX17: BOM pu | AY17: =AY7/AY4 -> #DIV/0! | AZ17: =AZ7/AZ4 -> 0.28599992 | BA17: =BA7/BA4 -> #DIV/0! | BB17: =BB7/BB4 -> 0.13204 | BC17: =BC7/BC4 -> 0.25461955 | BD17: =BD7/BD4 -> 0.42367 | BE17: =BE7/BE4 -> 0.28457658 | BF17: =BF7/BF4 -> 0.531747 | ... BH17: =BH7/BH4 -> 0.2715413 | BJ17: BOM pu | BK17: =BK7/BK4 -> #DIV/0! | BL17: =BL7/BL4 -> 0.29441571 | BM17: =BM7/BM4 -> 0.44084589 | BN17: =BN7/BN4 -> 0.13204 | BO17: =BO7/BO4 -> 0.28075535 | BP17: =BP7/BP4 -> 0.42367 | BQ17: =BQ7/BQ4 -> 0.28565908 | BR17: =BR7/BR4 -> 0.51819913 | ... BT17: =BT7/BT4 -> 0.27250033 | BV17: BOM pu | BW17: =BW7/BW4 -> #DIV/0! | BX17: =BX7/BX4 -> 0.29035938 | BY17: =BY7/BY4 -> 0.36400235 | BZ17: =BZ7/BZ4 -> 0.13204 | CA17: =CA7/CA4 -> 0.24740584 | CB17: =CB7/CB4 -> 0.42367 | CC17: =CC7/CC4 -> 0.28626505 | CD17: =CD7/CD4 -> 0.49721205 | ... CF17: =CF7/CF4 -> 0.26895556 | CH17: BOM pu | CI17: =CI7/CI4 -> #DIV/0! | CJ17: =CJ7/CJ4 -> 0.27902308 | CK17: =CK7/CK4 -> 0.56762308 | CL17: =CL7/CL4 -> 0.13204 | CM17: =CM7/CM4 -> 0.26675703 | CN17: =CN7/CN4 -> 0.42367 | CO17: =CO7/CO4 -> 0.28531093 | CP17: =CP7/CP4 -> 0.50851059 | ... CR17: =CR7/CR4 -> 0.26866514 | CT17: BOM pu | CU17: =CU7/CU4 -> #DIV/0! | CV17: =CV7/CV4 -> 0.29115041 | CW17: =CW7/CW4 -> 0.61162021 | CX17: =CX7/CX4 -> 0.13204 | CY17: =CY7/CY4 -> 0.27067813 | CZ17: =CZ7/CZ4 -> 0.42367 | DA17: =DA7/DA4 -> 0.28582284 | DB17: =DB7/DB4 -> 0.51862806 | ... DD17: =DD7/DD4 -> 0.26884831 | DF17: BOM pu | DG17: =DG7/DG4 -> #DIV/0! | DH17: =DH7/DH4 -> 0.28036389 | DI17: =DI7/DI4 -> 0.46512 | DJ17: =DJ7/DJ4 -> 0.13204 | DK17: =DK7/DK4 -> 0.23859938 | DL17: =DL7/DL4 -> 0.42367 | DM17: =DM7/DM4 -> 0.28553775 | DN17: =DN7/DN4 -> 0.51634696 | ... DP17: =DP7/DP4 -> 0.26706959 | DR17: BOM pu | DS17: =DS7/DS4 -> #DIV/0! | DT17: =DT7/DT4 -> 0.28459845 | DU17: =DU7/DU4 -> 0.24524 | DV17: =DV7/DV4 -> 0.13204 | DW17: =DW7/DW4 -> 0.25607326 | DX17: =DX7/DX4 -> 0.42367 | DY17: =DY7/DY4 -> 0.28542766 | DZ17: =DZ7/DZ4 -> 0.50931096 | ... EB17: =EB7/EB4 -> 0.2659221 | ED17: BOM pu | EE17: =EE7/EE4 -> #DIV/0! | EF17: =EF7/EF4 -> 0.30021674 | EG17: =EG7/EG4 -> 0.23739208 | EH17: =EH7/EH4 -> 0.13204 | EI17: =EI7/EI4 -> 0.26664941 | EJ17: =EJ7/EJ4 -> 0.42367 | EK17: =EK7/EK4 -> 0.28693872 | EL17: =EL7/EL4 -> 0.47970066 | ... EN17: =EN7/EN4 -> 0.26599221 | EP17: BOM pu | EQ17: =EQ7/EQ4 -> #DIV/0! | ER17: =ER7/ER4 -> 0.29520075 | ES17: =ES7/ES4 -> 0.53988667 | ET17: =ET7/ET4 -> 0.13772372 | EU17: =EU7/EU4 -> 0.27348339 | EV17: =EV7/EV4 -> 0.42367 | EW17: =EW7/EW4 -> 0.28736434 | EX17: =EX7/EX4 -> 0.48286557 | ... EZ17: =EZ7/EZ4 -> 0.26637629 | FB17: BOM pu | FC17: =FC7/FC4 -> #DIV/0! | FD17: =FD7/FD4 -> 0.29575621 | FE17: =FE7/FE4 -> 0.243115 | FF17: =FF7/FF4 -> 0.13204 | FG17: =FG7/FG4 -> 0.24905917 | FH17: =FH7/FH4 -> 0.42367 | FI17: =FI7/FI4 -> 0.28795461 | FJ17: =FJ7/FJ4 -> 0.45834348 | ... FL17: =FL7/FL4 -> 0.2650647 | FN17: BOM pu | FO17: =FO7/FO4 -> #DIV/0! | FP17: =FP7/FP4 -> 0.29414097 | FQ17: =FQ7/FQ4 -> 0.30440364 | FR17: =FR7/FR4 -> 0.13204 | FS17: =FS7/FS4 -> 0.27455221 | FT17: =FT7/FT4 -> 0.42367 | FU17: =FU7/FU4 -> 0.2882642 | FV17: =FV7/FV4 -> 0.4460818 | ... FX17: =FX7/FX4 -> 0.26550441 | FZ17: BOM pu | GA17: =GA7/GA4 -> #DIV/0! | GB17: =GB7/GB4 -> 0.2786007 | GC17: =GC7/GC4 -> 0.39791549 | GD17: =GD7/GD4 -> 0.13204 | GE17: =GE7/GE4 -> 0.084125 | GF17: =GF7/GF4 -> 0.26877154 | GG17: =GG7/GG4 -> 0.42367 | GH17: =GH7/GH4 -> 0.28792229 | ... GL17: =GL7/GL4 -> 0.26565748 | GN17: BOM pu | GO17: =GO7/GO4 -> 0.42367 | GP17: =GP7/GP4 -> 0.29007604 | GQ17: =GQ7/GQ4 -> 0.36755615 | GR17: =GR7/GR4 -> 0.13204 | GS17: =GS7/GS4 -> #DIV/0! | GT17: =GT7/GT4 -> 0.29637281 | GU17: =GU7/GU4 -> 0.42367 | GV17: =GV7/GV4 -> 0.288015 | ... GZ17: =GZ7/GZ4 -> 0.26785769 | HB17: BOM pu | HC17: =HC7/HC4 -> #DIV/0! | HD17: =HD7/HD4 -> 0.29675878 | HE17: =HE7/HE4 -> 0.466225 | HF17: =HF7/HF4 -> 0.13204 | HG17: =HG7/HG4 -> #DIV/0! | HH17: =HH7/HH4 -> 0.24541554 | HI17: =HI7/HI4 -> 0.42367 | HJ17: =HJ7/HJ4 -> 0.28842825 | ... HN17: =HN7/HN4 -> 0.2667744 | HP17: BOM pu | HQ17: =HQ7/HQ4 -> #DIV/0! | HR17: =HR7/HR4 -> 0.29397738 | HS17: =HS7/HS4 -> 0.28622269 | HT17: =HT7/HT4 -> 0.13204 | HU17: =HU7/HU4 -> #DIV/0! | HV17: =HV7/HV4 -> 0.25867388 | HW17: =HW7/HW4 -> 0.42367 | HX17: =HX7/HX4 -> 0.2887001 | ... IB17: =IB7/IB4 -> 0.26638291 | ID17: BOM pu | IE17: =IE7/IE4 -> #DIV/0! | IF17: =IF7/IF4 -> 0.30172225 | IG17: =IG7/IG4 -> 0.29668042 | IH17: =IH7/IH4 -> 0.13204 | II17: =II7/II4 -> #DIV/0! | IJ17: =IJ7/IJ4 -> 0.25711137 | IK17: =IK7/IK4 -> 0.42367 | IL17: =IL7/IL4 -> 0.28942811 | ... IP17: =IP7/IP4 -> 0.26581153 | IR17: BOM pu | IS17: =IS7/IS4 -> #DIV/0! | IT17: =IT7/IT4 -> 0.30075 | IU17: =IU7/IU4 -> 0.27435561 | IV17: =IV7/IV4 -> 0.13204 | IW17: =IW7/IW4 -> #DIV/0! | IX17: =IX7/IX4 -> 0.24224422 | IY17: =IY7/IY4 -> 0.42367 | IZ17: =IZ7/IZ4 -> 0.28982073 | ... JD17: =JD7/JD4 -> 0.26492123 | JF17: BOM pu | JG17: =JG7/JG4 -> 0.42367 | JH17: =JH7/JH4 -> 0.29907753 | JI17: =JI7/JI4 -> 0.48828302 | JJ17: =JJ7/JJ4 -> 0.13204 | JK17: =JK7/JK4 -> #DIV/0! | JL17: =JL7/JL4 -> 0.29176428 | JM17: =JM7/JM4 -> 0.42367 | JN17: =JN7/JN4 -> 0.29010466 | ... JR17: =JR7/JR4 -> 0.26614452 | JT17: BOM pu | JU17: =JU7/JU4 -> #DIV/0! | JV17: =JV7/JV4 -> 0.3016725 | JW17: =JW7/JW4 -> 0.3450556 | JX17: =JX7/JX4 -> 0.13204 | JY17: =JY7/JY4 -> #DIV/0! | JZ17: =JZ7/JZ4 -> 0.22731589 | KA17: =KA7/KA4 -> 0.42367 | KB17: =KB7/KB4 -> 0.29027703 | ... KF17: =KF7/KF4 -> 0.26516123 | KH17: BOM pu | KI17: =KI7/KI4 -> #DIV/0! | KJ17: =KJ7/KJ4 -> 0.2786 | KK17: =KK7/KK4 -> #DIV/0! | KL17: =KL7/KL4 -> 0.13204 | KM17: =KM7/KM4 -> #DIV/0! | KN17: =KN7/KN4 -> 0.23142122 | KO17: =KO7/KO4 -> 0.42367 | KP17: =KP7/KP4 -> 0.28985317 | ... KT17: =KT7/KT4 -> 0.26395981
H19: 738.20732 | I19: 358.72142 | J19: 542.6413 | K19: 154.80128 | L19: 368.37672 | T19: =T5*1000/T$4 -> 736.31 | U19: =U5*1000/U$4 -> 368.05429 | V19: =V5*1000/V$4 -> 637.34373 | W19: =W5*1000/W$4 -> 154.71 | X19: =X5*1000/X$4 -> 355.50433 | AF19: =AF5*1000/AF$4 -> 736.31 | AG19: =AG5*1000/AG$4 -> 365.03793 | AH19: =AH5*1000/AH$4 -> 677.95 | AI19: =AI5*1000/AI$4 -> 154.71 | AJ19: =AJ5*1000/AJ$4 -> 351.36287 | AR19: =AR5*1000/AR$4 -> 736.31 | AS19: =AS5*1000/AS$4 -> 362.43951 | AT19: =AT5*1000/AT$4 -> 668.7355 | AU19: =AU5*1000/AU$4 -> 154.71 | AV19: =AV5*1000/AV$4 -> 358.12202 | BD19: =BD5*1000/BD$4 -> 736.31 | BE19: =BE5*1000/BE$4 -> 363.00767 | BF19: =BF5*1000/BF$4 -> 668.7355 | BG19: =BG5*1000/BG$4 -> 154.71 | BH19: =BH5*1000/BH$4 -> 349.06461 | BP19: =BP5*1000/BP$4 -> 736.31 | BQ19: =BQ5*1000/BQ$4 -> 364.31151 | BR19: =BR5*1000/BR$4 -> 651.87249 | BS19: =BS5*1000/BS$4 -> 154.71 | BT19: =BT5*1000/BT$4 -> 349.67404 | CB19: =CB5*1000/CB$4 -> 736.31 | CC19: =CC5*1000/CC$4 -> 365.05259 | CD19: =CD5*1000/CD$4 -> 625.87317 | CE19: =CE5*1000/CE$4 -> 154.71 | CF19: =CF5*1000/CF$4 -> 344.2299 | CN19: =CN5*1000/CN$4 -> 736.31 | CO19: =CO5*1000/CO$4 -> 363.92467 | CP19: =CP5*1000/CP$4 -> 639.91666 | CQ19: =CQ5*1000/CQ$4 -> 154.71 | CR19: =CR5*1000/CR$4 -> 343.26462 | CZ19: =CZ5*1000/CZ$4 -> 736.31 | DA19: =DA5*1000/DA$4 -> 364.5452 | DB19: =DB5*1000/DB$4 -> 652.4997 | DC19: =DC5*1000/DC$4 -> 154.71 | DD19: =DD5*1000/DD$4 -> 343.03862 | DL19: =DL5*1000/DL$4 -> 736.31 | DM19: =DM5*1000/DM$4 -> 364.21296 | DN19: =DN5*1000/DN$4 -> 649.65644 | DO19: =DO5*1000/DO$4 -> 154.71 | DP19: =DP5*1000/DP$4 -> 340.49777 | DX19: =DX5*1000/DX$4 -> 736.31 | DY19: =DY5*1000/DY$4 -> 364.02581 | DZ19: =DZ5*1000/DZ$4 -> 640.94754 | EA19: =EA5*1000/EA$4 -> 154.71 | EB19: =EB5*1000/EB$4 -> 338.75621 | EJ19: =EJ5*1000/EJ$4 -> 736.31 | EK19: =EK5*1000/EK$4 -> 365.77711 | EL19: =EL5*1000/EL$4 -> 604.65659 | EM19: =EM5*1000/EM$4 -> 154.71 | EN19: =EN5*1000/EN$4 -> 338.55118 | EV19: =EV5*1000/EV$4 -> 736.31 | EW19: =EW5*1000/EW$4 -> 366.26739 | EX19: =EX5*1000/EX$4 -> 608.59349 | EY19: =EY5*1000/EY$4 -> 155.03599 | EZ19: =EZ5*1000/EZ$4 -> 338.83789 | FH19: =FH5*1000/FH$4 -> 736.31 | FI19: =FI5*1000/FI$4 -> 366.93419 | FJ19: =FJ5*1000/FJ$4 -> 578.00698 | FK19: =FK5*1000/FK$4 -> 155.00628 | FL19: =FL5*1000/FL$4 -> 336.88542 | FT19: =FT5*1000/FT$4 -> 736.31 | FU19: =FU5*1000/FU$4 -> 367.283 | FV19: =FV5*1000/FV$4 -> 562.75121 | FW19: =FW5*1000/FW$4 -> 154.9981 | FX19: =FX5*1000/FX$4 -> 337.36763 | GG19: =GG5*1000/GG$4 -> 736.31 | GH19: =GH5*1000/GH$4 -> 366.88945 | GI19: =GI5*1000/GI$4 -> 552.98832 | GJ19: =GJ5*1000/GJ$4 -> 154.98303 | GK19: =GK5*1000/GK$4 -> 146.74 | GL19: =GL5*1000/GL$4 -> 337.44039 | GU19: =GU5*1000/GU$4 -> 736.31 | GV19: =GV5*1000/GV$4 -> 366.99427 | GW19: =GW5*1000/GW$4 -> 543.651 | GX19: =GX5*1000/GX$4 -> 154.96233 | GY19: =GY5*1000/GY$4 -> 146.74 | GZ19: =GZ5*1000/GZ$4 -> 343.72003 | HI19: =HI5*1000/HI$4 -> 736.31 | HJ19: =HJ5*1000/HJ$4 -> 367.46673 | HK19: =HK5*1000/HK$4 -> 543.89161 | HL19: =HL5*1000/HL$4 -> 154.9447 | HM19: =HM5*1000/HM$4 -> 146.74 | HN19: =HN5*1000/HN$4 -> 341.97556 | HW19: =HW5*1000/HW$4 -> 736.31 | HX19: =HX5*1000/HX$4 -> 367.73375 | HY19: =HY5*1000/HY$4 -> 532.04315 | HZ19: =HZ5*1000/HZ$4 -> 154.93368 | IA19: =IA5*1000/IA$4 -> 146.74 | IB19: =IB5*1000/IB$4 -> 341.176 | IK19: =IK5*1000/IK$4 -> 736.31 | IL19: =IL5*1000/IL$4 -> 368.56945 | IM19: =IM5*1000/IM$4 -> 515.21803 | IN19: =IN5*1000/IN$4 -> 154.91761 | IO19: =IO5*1000/IO$4 -> 146.74 | IP19: =IP5*1000/IP$4 -> 340.04392 | IY19: =IY5*1000/IY$4 -> 736.31 | IZ19: =IZ5*1000/IZ$4 -> 369.01993 | JA19: =JA5*1000/JA$4 -> 512.21551 | JB19: =JB5*1000/JB$4 -> 154.9058 | JC19: =JC5*1000/JC$4 -> 146.74 | JD19: =JD5*1000/JD$4 -> 338.64337 | JM19: =JM5*1000/JM$4 -> 737.35651 | JN19: =JN5*1000/JN$4 -> 369.34586 | JO19: =JO5*1000/JO$4 -> 513.58616 | JP19: =JP5*1000/JP$4 -> 154.89553 | JQ19: =JQ5*1000/JQ$4 -> 146.74 | JR19: =JR5*1000/JR$4 -> 342.36723 | KA19: =KA5*1000/KA$4 -> 737.35651 | KB19: =KB5*1000/KB$4 -> 369.54364 | KC19: =KC5*1000/KC$4 -> 509.57683 | KD19: =KD5*1000/KD$4 -> 154.88606 | KE19: =KE5*1000/KE$4 -> 146.74 | KF19: =KF5*1000/KF$4 -> 340.84006 | KO19: =KO5*1000/KO$4 -> 737.35651 | KP19: =KP5*1000/KP$4 -> 369.05783 | KQ19: =KQ5*1000/KQ$4 -> 509.57683 | KR19: =KR5*1000/KR$4 -> 154.87758 | KS19: =KS5*1000/KS$4 -> 146.74 | KT19: =KT5*1000/KT$4 -> 339.07645
H20: 487.35685 | I20: 338.62636 | J20: 547.33123 | K20: 157.86447 | L20: 331.34814 | T20: =T6*1000/T$4 -> 475.72 | U20: =U6*1000/U$4 -> 338.20952 | V20: =V6*1000/V$4 -> 559.07508 | W20: =W6*1000/W$4 -> 138.64 | X20: =X6*1000/X$4 -> 310.26497 | AF20: =AF6*1000/AF$4 -> 475.72 | AG20: =AG6*1000/AG$4 -> 335.72276 | AH20: =AH6*1000/AH$4 -> 592.08333 | AI20: =AI6*1000/AI$4 -> 138.64 | AJ20: =AJ6*1000/AJ$4 -> 309.75685 | AR20: =AR6*1000/AR$4 -> 475.72 | AS20: =AS6*1000/AS$4 -> 333.47415 | AT20: =AT6*1000/AT$4 -> 584.593 | AU20: =AU6*1000/AU$4 -> 138.64 | AV20: =AV6*1000/AV$4 -> 318.49852 | BD20: =BD6*1000/BD$4 -> 475.72 | BE20: =BE6*1000/BE$4 -> 334.01658 | BF20: =BF6*1000/BF$4 -> 584.593 | BG20: =BG6*1000/BG$4 -> 138.64 | BH20: =BH6*1000/BH$4 -> 312.73025 | BP20: =BP6*1000/BP$4 -> 475.72 | BQ20: =BQ6*1000/BQ$4 -> 335.09908 | BR20: =BR6*1000/BR$4 -> 570.88531 | BS20: =BS6*1000/BS$4 -> 138.64 | BT20: =BT6*1000/BT$4 -> 313.8719 | CB20: =CB6*1000/CB$4 -> 475.72 | CC20: =CC6*1000/CC$4 -> 335.70505 | CD20: =CD6*1000/CD$4 -> 549.58266 | CE20: =CE6*1000/CE$4 -> 138.64 | CF20: =CF6*1000/CF$4 -> 309.68199 | CN20: =CN6*1000/CN$4 -> 475.72 | CO20: =CO6*1000/CO$4 -> 334.75119 | CP20: =CP6*1000/CP$4 -> 561.0254 | CQ20: =CQ6*1000/CQ$4 -> 138.64 | CR20: =CR6*1000/CR$4 -> 309.33381 | CZ20: =CZ6*1000/CZ$4 -> 475.72 | DA20: =DA6*1000/DA$4 -> 335.26308 | DB20: =DB6*1000/DB$4 -> 571.26782 | DC20: =DC6*1000/DC$4 -> 138.64 | DD20: =DD6*1000/DD$4 -> 309.35014 | DL20: =DL6*1000/DL$4 -> 475.72 | DM20: =DM6*1000/DM$4 -> 334.97797 | DN20: =DN6*1000/DN$4 -> 568.96201 | DO20: =DO6*1000/DO$4 -> 138.64 | DP20: =DP6*1000/DP$4 -> 307.26512 | DX20: =DX6*1000/DX$4 -> 475.72 | DY20: =DY6*1000/DY$4 -> 334.86786 | DZ20: =DZ6*1000/DZ$4 -> 561.8161 | EA20: =EA6*1000/EA$4 -> 138.64 | EB20: =EB6*1000/EB$4 -> 306.25994 | EJ20: =EJ6*1000/EJ$4 -> 475.72 | EK20: =EK6*1000/EK$4 -> 336.3789 | EL20: =EL6*1000/EL$4 -> 531.66192 | EM20: =EM6*1000/EM$4 -> 138.64 | EN20: =EN6*1000/EN$4 -> 306.46419 | EV20: =EV6*1000/EV$4 -> 475.72 | EW20: =EW6*1000/EW$4 -> 336.80451 | EX20: =EX6*1000/EX$4 -> 534.85937 | EY20: =EY6*1000/EY$4 -> 138.94294 | EZ20: =EZ6*1000/EZ$4 -> 306.8287 | FH20: =FH6*1000/FH$4 -> 475.72 | FI20: =FI6*1000/FI$4 -> 337.39477 | FJ20: =FJ6*1000/FJ$4 -> 510.0719 | FK20: =FK6*1000/FK$4 -> 138.91533 | FL20: =FL6*1000/FL$4 -> 305.34886 | FT20: =FT6*1000/FT$4 -> 475.72 | FU20: =FU6*1000/FU$4 -> 337.70435 | FV20: =FV6*1000/FV$4 -> 497.65416 | FW20: =FW6*1000/FW$4 -> 138.90773 | FX20: =FX6*1000/FX$4 -> 305.96227 | GG20: =GG6*1000/GG$4 -> 475.72 | GH20: =GH6*1000/GH$4 -> 337.36243 | GI20: =GI6*1000/GI$4 -> 487.98669 | GJ20: =GJ6*1000/GJ$4 -> 138.89372 | GK20: =GK6*1000/GK$4 -> 90.725 | GL20: =GL6*1000/GL$4 -> 305.94378 | GU20: =GU6*1000/GU$4 -> 475.72 | GV20: =GV6*1000/GV$4 -> 337.45514 | GW20: =GW6*1000/GW$4 -> 479.83769 | GX20: =GX6*1000/GX$4 -> 138.87449 | GY20: =GY6*1000/GY$4 -> 90.725 | GZ20: =GZ6*1000/GZ$4 -> 308.10721 | HI20: =HI6*1000/HI$4 -> 475.72 | HJ20: =HJ6*1000/HJ$4 -> 337.86838 | HK20: =HK6*1000/HK$4 -> 480.04265 | HL20: =HL6*1000/HL$4 -> 138.85811 | HM20: =HM6*1000/HM$4 -> 90.725 | HN20: =HN6*1000/HN$4 -> 306.80853 | HW20: =HW6*1000/HW$4 -> 475.72 | HX20: =HX6*1000/HX$4 -> 338.14351 | HY20: =HY6*1000/HY$4 -> 469.82432 | HZ20: =HZ6*1000/HZ$4 -> 138.84787 | IA20: =IA6*1000/IA$4 -> 90.725 | IB20: =IB6*1000/IB$4 -> 306.38332 | IK20: =IK6*1000/IK$4 -> 475.72 | IL20: =IL6*1000/IL$4 -> 338.87133 | IM20: =IM6*1000/IM$4 -> 455.25858 | IN20: =IN6*1000/IN$4 -> 138.83293 | IO20: =IO6*1000/IO$4 -> 90.725 | IP20: =IP6*1000/IP$4 -> 305.6276 | IY20: =IY6*1000/IY$4 -> 475.72 | IZ20: =IZ6*1000/IZ$4 -> 339.26383 | JA20: =JA6*1000/JA$4 -> 452.89628 | JB20: =JB6*1000/JB$4 -> 138.82196 | JC20: =JC6*1000/JC$4 -> 90.725 | JD20: =JD6*1000/JD$4 -> 304.54806 | JM20: =JM6*1000/JM$4 -> 475.72 | JN20: =JN6*1000/JN$4 -> 339.54766 | JO20: =JO6*1000/JO$4 -> 453.96362 | JP20: =JP6*1000/JP$4 -> 138.81241 | JQ20: =JQ6*1000/JQ$4 -> 90.725 | JR20: =JR6*1000/JR$4 -> 305.73151 | KA20: =KA6*1000/KA$4 -> 475.72 | KB20: =KB6*1000/KB$4 -> 339.71999 | KC20: =KC6*1000/KC$4 -> 450.22972 | KD20: =KD6*1000/KD$4 -> 138.80362 | KE20: =KE6*1000/KE$4 -> 90.725 | KF20: =KF6*1000/KF$4 -> 304.44079 | KO20: =KO6*1000/KO$4 -> 475.72 | KP20: =KP6*1000/KP$4 -> 339.29602 | KQ20: =KQ6*1000/KQ$4 -> 450.22972 | KR20: =KR6*1000/KR$4 -> 138.79573 | KS20: =KS6*1000/KS$4 -> 90.725 | KT20: =KT6*1000/KT$4 -> 303.11011
H21: 250.85047 | I21: 20.095055 | J21: -4.6899353 | K21: -3.0631833 | L21: 281.24837 | T21: =T7*1000/T$4 -> 423.67 | U21: =U7*1000/U$4 -> 288.76952 | V21: =V7*1000/V$4 -> 506.52661 | W21: =W7*1000/W$4 -> 132.04 | X21: =X7*1000/X$4 -> 271.74927 | AF21: =AF7*1000/AF$4 -> 423.67 | AG21: =AG7*1000/AG$4 -> 286.28276 | AH21: =AH7*1000/AH$4 -> 539.15 | AI21: =AI7*1000/AI$4 -> 132.04 | AJ21: =AJ7*1000/AJ$4 -> 270.80327 | AR21: =AR7*1000/AR$4 -> 423.67 | AS21: =AS7*1000/AS$4 -> 284.03415 | AT21: =AT7*1000/AT$4 -> 531.747 | AU21: =AU7*1000/AU$4 -> 132.04 | AV21: =AV7*1000/AV$4 -> 277.15024 | BD21: =BD7*1000/BD$4 -> 423.67 | BE21: =BE7*1000/BE$4 -> 284.57658 | BF21: =BF7*1000/BF$4 -> 531.747 | BG21: =BG7*1000/BG$4 -> 132.04 | BH21: =BH7*1000/BH$4 -> 271.5413 | BP21: =BP7*1000/BP$4 -> 423.67 | BQ21: =BQ7*1000/BQ$4 -> 285.65908 | BR21: =BR7*1000/BR$4 -> 518.19913 | BS21: =BS7*1000/BS$4 -> 132.04 | BT21: =BT7*1000/BT$4 -> 272.50033 | CB21: =CB7*1000/CB$4 -> 423.67 | CC21: =CC7*1000/CC$4 -> 286.26505 | CD21: =CD7*1000/CD$4 -> 497.21205 | CE21: =CE7*1000/CE$4 -> 132.04 | CF21: =CF7*1000/CF$4 -> 268.95556 | CN21: =CN7*1000/CN$4 -> 423.67 | CO21: =CO7*1000/CO$4 -> 285.31093 | CP21: =CP7*1000/CP$4 -> 508.51059 | CQ21: =CQ7*1000/CQ$4 -> 132.04 | CR21: =CR7*1000/CR$4 -> 268.66514 | CZ21: =CZ7*1000/CZ$4 -> 423.67 | DA21: =DA7*1000/DA$4 -> 285.82284 | DB21: =DB7*1000/DB$4 -> 518.62806 | DC21: =DC7*1000/DC$4 -> 132.04 | DD21: =DD7*1000/DD$4 -> 268.84831 | DL21: =DL7*1000/DL$4 -> 423.67 | DM21: =DM7*1000/DM$4 -> 285.53775 | DN21: =DN7*1000/DN$4 -> 516.34696 | DO21: =DO7*1000/DO$4 -> 132.04 | DP21: =DP7*1000/DP$4 -> 267.06959 | DX21: =DX7*1000/DX$4 -> 423.67 | DY21: =DY7*1000/DY$4 -> 285.42766 | DZ21: =DZ7*1000/DZ$4 -> 509.31096 | EA21: =EA7*1000/EA$4 -> 132.04 | EB21: =EB7*1000/EB$4 -> 265.9221 | EJ21: =EJ7*1000/EJ$4 -> 423.67 | EK21: =EK7*1000/EK$4 -> 286.93872 | EL21: =EL7*1000/EL$4 -> 479.70066 | EM21: =EM7*1000/EM$4 -> 132.04 | EN21: =EN7*1000/EN$4 -> 265.99221 | EV21: =EV7*1000/EV$4 -> 423.67 | EW21: =EW7*1000/EW$4 -> 287.36434 | EX21: =EX7*1000/EX$4 -> 482.86557 | EY21: =EY7*1000/EY$4 -> 132.34294 | EZ21: =EZ7*1000/EZ$4 -> 266.37629 | FH21: =FH7*1000/FH$4 -> 423.67 | FI21: =FI7*1000/FI$4 -> 287.95461 | FJ21: =FJ7*1000/FJ$4 -> 458.34348 | FK21: =FK7*1000/FK$4 -> 132.31533 | FL21: =FL7*1000/FL$4 -> 265.0647 | FT21: =FT7*1000/FT$4 -> 423.67 | FU21: =FU7*1000/FU$4 -> 288.2642 | FV21: =FV7*1000/FV$4 -> 446.0818 | FW21: =FW7*1000/FW$4 -> 132.30773 | FX21: =FX7*1000/FX$4 -> 265.50441 | GG21: =GG7*1000/GG$4 -> 423.67 | GH21: =GH7*1000/GH$4 -> 287.92229 | GI21: =GI7*1000/GI$4 -> 438.35176 | GJ21: =GJ7*1000/GJ$4 -> 132.29372 | GK21: =GK7*1000/GK$4 -> 84.125 | GL21: =GL7*1000/GL$4 -> 265.65748 | GU21: =GU7*1000/GU$4 -> 423.67 | GV21: =GV7*1000/GV$4 -> 288.015 | GW21: =GW7*1000/GW$4 -> 430.84897 | GX21: =GX7*1000/GX$4 -> 132.27449 | GY21: =GY7*1000/GY$4 -> 84.125 | GZ21: =GZ7*1000/GZ$4 -> 267.85769 | HI21: =HI7*1000/HI$4 -> 423.67 | HJ21: =HJ7*1000/HJ$4 -> 288.42825 | HK21: =HK7*1000/HK$4 -> 431.04019 | HL21: =HL7*1000/HL$4 -> 132.25811 | HM21: =HM7*1000/HM$4 -> 84.125 | HN21: =HN7*1000/HN$4 -> 266.7744 | HW21: =HW7*1000/HW$4 -> 423.67 | HX21: =HX7*1000/HX$4 -> 288.7001 | HY21: =HY7*1000/HY$4 -> 421.53197 | HZ21: =HZ7*1000/HZ$4 -> 132.24787 | IA21: =IA7*1000/IA$4 -> 84.125 | IB21: =IB7*1000/IB$4 -> 266.38291 | IK21: =IK7*1000/IK$4 -> 423.67 | IL21: =IL7*1000/IL$4 -> 289.42811 | IM21: =IM7*1000/IM$4 -> 408.03451 | IN21: =IN7*1000/IN$4 -> 132.23293 | IO21: =IO7*1000/IO$4 -> 84.125 | IP21: =IP7*1000/IP$4 -> 265.81153 | IY21: =IY7*1000/IY$4 -> 423.67 | IZ21: =IZ7*1000/IZ$4 -> 289.82073 | JA21: =JA7*1000/JA$4 -> 405.62702 | JB21: =JB7*1000/JB$4 -> 132.22196 | JC21: =JC7*1000/JC$4 -> 84.125 | JD21: =JD7*1000/JD$4 -> 264.92123 | JM21: =JM7*1000/JM$4 -> 423.67 | JN21: =JN7*1000/JN$4 -> 290.10466 | JO21: =JO7*1000/JO$4 -> 406.73494 | JP21: =JP7*1000/JP$4 -> 132.21241 | JQ21: =JQ7*1000/JQ$4 -> 84.125 | JR21: =JR7*1000/JR$4 -> 266.14452 | KA21: =KA7*1000/KA$4 -> 423.67 | KB21: =KB7*1000/KB$4 -> 290.27703 | KC21: =KC7*1000/KC$4 -> 403.54431 | KD21: =KD7*1000/KD$4 -> 132.20362 | KE21: =KE7*1000/KE$4 -> 84.125 | KF21: =KF7*1000/KF$4 -> 265.16123 | KO21: =KO7*1000/KO$4 -> 423.67 | KP21: =KP7*1000/KP$4 -> 289.85317 | KQ21: =KQ7*1000/KQ$4 -> 403.54431 | KR21: =KR7*1000/KR$4 -> 132.19573 | KS21: =KS7*1000/KS$4 -> 84.125 | KT21: =KT7*1000/KT$4 -> 263.95981
H22: 430.83685 | I22: 284.39293 | J22: 491.28794 | K22: 137.36447 | L22: 281.24837 | T22: =T8*1000/T$4 -> 32.57 | U22: =U8*1000/U$4 -> 30.76 | V22: =V8*1000/V$4 -> 32.907458 | W22: =W8*1000/W$4 -> 4.6 | X22: =X8*1000/X$4 -> 24.121248 | AF22: =AF8*1000/AF$4 -> 32.57 | AG22: =AG8*1000/AG$4 -> 30.76 | AH22: =AH8*1000/AH$4 -> 33.173333 | AI22: =AI8*1000/AI$4 -> 4.6 | AJ22: =AJ8*1000/AJ$4 -> 24.385965 | AR22: =AR8*1000/AR$4 -> 32.57 | AS22: =AS8*1000/AS$4 -> 30.76 | AT22: =AT8*1000/AT$4 -> 33.113 | AU22: =AU8*1000/AU$4 -> 4.6 | AV22: =AV8*1000/AV$4 -> 25.846751 | BD22: =BD8*1000/BD$4 -> 32.57 | BE22: =BE8*1000/BE$4 -> 30.76 | BF22: =BF8*1000/BF$4 -> 33.113 | BG22: =BG8*1000/BG$4 -> 4.6 | BH22: =BH8*1000/BH$4 -> 25.74251 | BP22: =BP8*1000/BP$4 -> 32.57 | BQ22: =BQ8*1000/BQ$4 -> 30.76 | BR22: =BR8*1000/BR$4 -> 33.002587 | BS22: =BS8*1000/BS$4 -> 4.6 | BT22: =BT8*1000/BT$4 -> 25.853396 | CB22: =CB8*1000/CB$4 -> 32.57 | CC22: =CC8*1000/CC$4 -> 30.76 | CD22: =CD8*1000/CD$4 -> 32.784726 | CE22: =CE8*1000/CE$4 -> 4.6 | CF22: =CF8*1000/CF$4 -> 25.457143 | CN22: =CN8*1000/CN$4 -> 32.57 | CO22: =CO8*1000/CO$4 -> 30.760178 | CP22: =CP8*1000/CP$4 -> 32.88432 | CQ22: =CQ8*1000/CQ$4 -> 4.6 | CR22: =CR8*1000/CR$4 -> 25.422319 | CZ22: =CZ8*1000/CZ$4 -> 32.57 | DA22: =DA8*1000/DA$4 -> 30.760163 | DB22: =DB8*1000/DB$4 -> 32.970633 | DC22: =DC8*1000/DC$4 -> 4.6 | DD22: =DD8*1000/DD$4 -> 25.320734 | DL22: =DL8*1000/DL$4 -> 32.57 | DM22: =DM8*1000/DM$4 -> 30.760154 | DN22: =DN8*1000/DN$4 -> 32.953554 | DO22: =DO8*1000/DO$4 -> 4.6 | DP22: =DP8*1000/DP$4 -> 25.133093 | DX22: =DX8*1000/DX$4 -> 32.57 | DY22: =DY8*1000/DY$4 -> 30.760136 | DZ22: =DZ8*1000/DZ$4 -> 32.877679 | EA22: =EA8*1000/EA$4 -> 4.6 | EB22: =EB8*1000/EB$4 -> 25.217987 | EJ22: =EJ8*1000/EJ$4 -> 32.57 | EK22: =EK8*1000/EK$4 -> 30.760122 | EL22: =EL8*1000/EL$4 -> 32.502524 | EM22: =EM8*1000/EM$4 -> 4.6 | EN22: =EN8*1000/EN$4 -> 25.297478 | EV22: =EV8*1000/EV$4 -> 32.57 | EW22: =EW8*1000/EW$4 -> 30.760116 | EX22: =EX8*1000/EX$4 -> 32.525003 | EY22: =EY8*1000/EY$4 -> 4.6 | EZ22: =EZ8*1000/EZ$4 -> 25.285529 | FH22: =FH8*1000/FH$4 -> 32.57 | FI22: =FI8*1000/FI$4 -> 30.760108 | FJ22: =FJ8*1000/FJ$4 -> 32.341604 | FK22: =FK8*1000/FK$4 -> 4.6 | FL22: =FL8*1000/FL$4 -> 25.181727 | FT22: =FT8*1000/FT$4 -> 32.57 | FU22: =FU8*1000/FU$4 -> 30.760102 | FV22: =FV8*1000/FV$4 -> 32.233801 | FW22: =FW8*1000/FW$4 -> 4.6 | FX22: =FX8*1000/FX$4 -> 25.287328 | GG22: =GG8*1000/GG$4 -> 32.57 | GH22: =GH8*1000/GH$4 -> 30.760099 | GI22: =GI8*1000/GI$4 -> 30.901185 | GJ22: =GJ8*1000/GJ$4 -> 4.6 | GK22: =GK8*1000/GK$4 -> 4.6 | GL22: =GL8*1000/GL$4 -> 25.174179 | GU22: =GU8*1000/GU$4 -> 32.57 | GV22: =GV8*1000/GV$4 -> 30.760094 | GW22: =GW8*1000/GW$4 -> 30.456494 | GX22: =GX8*1000/GX$4 -> 4.6 | GY22: =GY8*1000/GY$4 -> 4.6 | GZ22: =GZ8*1000/GZ$4 -> 25.152289 | HI22: =HI8*1000/HI$4 -> 32.57 | HJ22: =HJ8*1000/HJ$4 -> 30.76009 | HK22: =HK8*1000/HK$4 -> 30.465945 | HL22: =HL8*1000/HL$4 -> 4.6 | HM22: =HM8*1000/HM$4 -> 4.6 | HN22: =HN8*1000/HN$4 -> 25.020606 | HW22: =HW8*1000/HW$4 -> 32.57 | HX22: =HX8*1000/HX$4 -> 30.762312 | HY22: =HY8*1000/HY$4 -> 29.977247 | HZ22: =HZ8*1000/HZ$4 -> 4.6 | IA22: =IA8*1000/IA$4 -> 4.6 | IB22: =IB8*1000/IB$4 -> 24.996281 | IK22: =IK8*1000/IK$4 -> 32.57 | IL22: =IL8*1000/IL$4 -> 30.762182 | IM22: =IM8*1000/IM$4 -> 29.242094 | IN22: =IN8*1000/IN$4 -> 4.6 | IO22: =IO8*1000/IO$4 -> 4.6 | IP22: =IP8*1000/IP$4 -> 24.877426 | IY22: =IY8*1000/IY$4 -> 32.57 | IZ22: =IZ8*1000/IZ$4 -> 30.762107 | JA22: =JA8*1000/JA$4 -> 29.273083 | JB22: =JB8*1000/JB$4 -> 4.6 | JC22: =JC8*1000/JC$4 -> 4.6 | JD22: =JD8*1000/JD$4 -> 24.762118 | JM22: =JM8*1000/JM$4 -> 32.57 | JN22: =JN8*1000/JN$4 -> 30.762042 | JO22: =JO8*1000/JO$4 -> 29.245221 | JP22: =JP8*1000/JP$4 -> 4.6 | JQ22: =JQ8*1000/JQ$4 -> 4.6 | JR22: =JR8*1000/JR$4 -> 24.740315 | KA22: =KA8*1000/KA$4 -> 32.57 | KB22: =KB8*1000/KB$4 -> 30.762012 | KC22: =KC8*1000/KC$4 -> 28.871507 | KD22: =KD8*1000/KD$4 -> 4.6 | KE22: =KE8*1000/KE$4 -> 4.6 | KF22: =KF8*1000/KF$4 -> 24.549303 | KO22: =KO8*1000/KO$4 -> 32.57 | KP22: =KP8*1000/KP$4 -> 30.761939 | KQ22: =KQ8*1000/KQ$4 -> 28.871507 | KR22: =KR8*1000/KR$4 -> 4.6 | KS22: =KS8*1000/KS$4 -> 4.6 | KT22: =KT8*1000/KT$4 -> 24.470595
T23: =T9*1000/T$4 -> 19.51 | U23: =U9*1000/U$4 -> 18.69 | V23: =V9*1000/V$4 -> 19.662881 | W23: =W9*1000/W$4 -> 2 | X23: =X9*1000/X$4 -> 14.403995 | AF23: =AF9*1000/AF$4 -> 19.51 | AG23: =AG9*1000/AG$4 -> 18.69 | AH23: =AH9*1000/AH$4 -> 19.783333 | AI23: =AI9*1000/AI$4 -> 2 | AJ23: =AJ9*1000/AJ$4 -> 14.576987 | AR23: =AR9*1000/AR$4 -> 19.51 | AS23: =AS9*1000/AS$4 -> 18.69 | AT23: =AT9*1000/AT$4 -> 19.756 | AU23: =AU9*1000/AU$4 -> 2 | AV23: =AV9*1000/AV$4 -> 15.511272 | BD23: =BD9*1000/BD$4 -> 19.51 | BE23: =BE9*1000/BE$4 -> 18.69 | BF23: =BF9*1000/BF$4 -> 19.756 | BG23: =BG9*1000/BG$4 -> 2 | BH23: =BH9*1000/BH$4 -> 15.455743 | BP23: =BP9*1000/BP$4 -> 19.51 | BQ23: =BQ9*1000/BQ$4 -> 18.69 | BR23: =BR9*1000/BR$4 -> 19.705979 | BS23: =BS9*1000/BS$4 -> 2 | BT23: =BT9*1000/BT$4 -> 15.527462 | CB23: =CB9*1000/CB$4 -> 19.51 | CC23: =CC9*1000/CC$4 -> 18.69 | CD23: =CD9*1000/CD$4 -> 19.607324 | CE23: =CE9*1000/CE$4 -> 2 | CF23: =CF9*1000/CF$4 -> 15.278302 | CN23: =CN9*1000/CN$4 -> 19.51 | CO23: =CO9*1000/CO$4 -> 18.690079 | CP23: =CP9*1000/CP$4 -> 19.652437 | CQ23: =CQ9*1000/CQ$4 -> 2 | CR23: =CR9*1000/CR$4 -> 15.255333 | CZ23: =CZ9*1000/CZ$4 -> 19.51 | DA23: =DA9*1000/DA$4 -> 18.690072 | DB23: =DB9*1000/DB$4 -> 19.691536 | DC23: =DC9*1000/DC$4 -> 2 | DD23: =DD9*1000/DD$4 -> 15.190041 | DL23: =DL9*1000/DL$4 -> 19.51 | DM23: =DM9*1000/DM$4 -> 18.690069 | DN23: =DN9*1000/DN$4 -> 19.683797 | DO23: =DO9*1000/DO$4 -> 2 | DP23: =DP9*1000/DP$4 -> 15.071266 | DX23: =DX9*1000/DX$4 -> 19.51 | DY23: =DY9*1000/DY$4 -> 18.69006 | DZ23: =DZ9*1000/DZ$4 -> 19.649441 | EA23: =EA9*1000/EA$4 -> 2 | EB23: =EB9*1000/EB$4 -> 15.128615 | EJ23: =EJ9*1000/EJ$4 -> 19.51 | EK23: =EK9*1000/EK$4 -> 18.690054 | EL23: =EL9*1000/EL$4 -> 19.479496 | EM23: =EM9*1000/EM$4 -> 2 | EN23: =EN9*1000/EN$4 -> 15.183212 | EV23: =EV9*1000/EV$4 -> 19.51 | EW23: =EW9*1000/EW$4 -> 18.690052 | EX23: =EX9*1000/EX$4 -> 19.489689 | EY23: =EY9*1000/EY$4 -> 2 | EZ23: =EZ9*1000/EZ$4 -> 15.175586 | FH23: =FH9*1000/FH$4 -> 19.51 | FI23: =FI9*1000/FI$4 -> 18.690048 | FJ23: =FJ9*1000/FJ$4 -> 19.406598 | FK23: =FK9*1000/FK$4 -> 2 | FL23: =FL9*1000/FL$4 -> 15.111034 | FT23: =FT9*1000/FT$4 -> 19.51 | FU23: =FU9*1000/FU$4 -> 18.690045 | FV23: =FV9*1000/FV$4 -> 19.357774 | FW23: =FW9*1000/FW$4 -> 2 | FX23: =FX9*1000/FX$4 -> 15.179148 | GG23: =GG9*1000/GG$4 -> 19.51 | GH23: =GH9*1000/GH$4 -> 18.690044 | GI23: =GI9*1000/GI$4 -> 18.753924 | GJ23: =GJ9*1000/GJ$4 -> 2 | GK23: =GK9*1000/GK$4 -> 2 | GL23: =GL9*1000/GL$4 -> 15.120848 | GU23: =GU9*1000/GU$4 -> 19.51 | GV23: =GV9*1000/GV$4 -> 18.690042 | GW23: =GW9*1000/GW$4 -> 18.552449 | GX23: =GX9*1000/GX$4 -> 2 | GY23: =GY9*1000/GY$4 -> 2 | GZ23: =GZ9*1000/GZ$4 -> 15.106331 | HI23: =HI9*1000/HI$4 -> 19.51 | HJ23: =HJ9*1000/HJ$4 -> 18.69004 | HK23: =HK9*1000/HK$4 -> 18.556733 | HL23: =HL9*1000/HL$4 -> 2 | HM23: =HM9*1000/HM$4 -> 2 | HN23: =HN9*1000/HN$4 -> 15.022514 | HW23: =HW9*1000/HW$4 -> 19.51 | HX23: =HX9*1000/HX$4 -> 18.691027 | HY23: =HY9*1000/HY$4 -> 18.335306 | HZ23: =HZ9*1000/HZ$4 -> 2 | IA23: =IA9*1000/IA$4 -> 2 | IB23: =IB9*1000/IB$4 -> 15.013069 | IK23: =IK9*1000/IK$4 -> 19.51 | IL23: =IL9*1000/IL$4 -> 18.69097 | IM23: =IM9*1000/IM$4 -> 18.00221 | IN23: =IN9*1000/IN$4 -> 2 | IO23: =IO9*1000/IO$4 -> 2 | IP23: =IP9*1000/IP$4 -> 14.947564 | IY23: =IY9*1000/IY$4 -> 19.51 | IZ23: =IZ9*1000/IZ$4 -> 18.690936 | JA23: =JA9*1000/JA$4 -> 18.016252 | JB23: =JB9*1000/JB$4 -> 2 | JC23: =JC9*1000/JC$4 -> 2 | JD23: =JD9*1000/JD$4 -> 14.873551 | JM23: =JM9*1000/JM$4 -> 19.51 | JN23: =JN9*1000/JN$4 -> 18.690908 | JO23: =JO9*1000/JO$4 -> 18.003625 | JP23: =JP9*1000/JP$4 -> 2 | JQ23: =JQ9*1000/JQ$4 -> 2 | JR23: =JR9*1000/JR$4 -> 14.855698 | KA23: =KA9*1000/KA$4 -> 19.51 | KB23: =KB9*1000/KB$4 -> 18.690894 | KC23: =KC9*1000/KC$4 -> 17.834283 | KD23: =KD9*1000/KD$4 -> 2 | KE23: =KE9*1000/KE$4 -> 2 | KF23: =KF9*1000/KF$4 -> 14.739232 | KO23: =KO9*1000/KO$4 -> 19.51 | KP23: =KP9*1000/KP$4 -> 18.690862 | KQ23: =KQ9*1000/KQ$4 -> 17.834283 | KR23: =KR9*1000/KR$4 -> 2 | KS23: =KS9*1000/KS$4 -> 2 | KT23: =KT9*1000/KT$4 -> 14.688602

Sheet Shared DB - June 25
B2: AIPL SALES DB | C2: 45811 | I2: MTD - June-25 | P2: AIPL SALES DB | Q2: 45811 | W2: MTD - June-25 | AD2: AIPL SALES DB | AE2: 45812 | AK2: YTM - June-25 | AR2: AIPL SALES DB | AS2: 45813 | AY2: MTD - June-25 | BF2: AIPL SALES DB | BG2: 45817 | BM2: MTD - June-25 | BT2: AIPL SALES DB | BU2: 45818 | CA2: MTD - June-25 | CH2: AIPL SALES DB | CI2: 45819 | CO2: MTD - June-25 | CV2: AIPL SALES DB | CW2: 45820 | DC2: MTD - June-25 | DJ2: AIPL SALES DB | DK2: 45821 | DQ2: MTD - June-25 | DX2: AIPL SALES DB | DY2: 45823 | EE2: MTD - June-25 | EL2: AIPL SALES DB | EM2: 45824 | ES2: MTD - June-25 | EZ2: AIPL SALES DB | FA2: 45825 | FG2: MTD - June-25 | FN2: AIPL SALES DB | FO2: 45826 | FU2: MTD - June-25 | GB2: AIPL SALES DB | GC2: 45827 | GI2: MTD - June-25 | GP2: AIPL SALES DB | GQ2: 45828 | GW2: MTD - June-25 | HD2: AIPL SALES DB | HE2: 45830 | HK2: MTD - June-25 | HR2: AIPL SALES DB | HS2: 45831 | HY2: MTD - June-25 | IF2: AIPL SALES DB | IG2: 45832 | IM2: MTD - June-25 | IT2: AIPL SALES DB | IU2: 45833 | JA2: MTD - June-25 | JH2: AIPL SALES DB | JI2: 45834 | JO2: MTD - June-25 | JV2: AIPL SALES DB | JW2: 45835 | KC2: MTD - June-25 | KJ2: AIPL SALES DB | KK2: 45837 | KQ2: MTD - June-25 | KX2: AIPL SALES DB | KY2: 45838 | LE2: MTD - June-25
B3: Product (INR in '000) | C3: PCB Ref | D3: PCB CF | E3: PCB MG | F3: Stator CF | G3: Rotor Ref | H3: Total | I3: PCB Ref | J3: PCB CF | K3: PCB MG | L3: Stator CF | M3: Rotor Ref | N3: Total | P3: Product (INR in '000) | Q3: PCB Ref | R3: PCB CF | S3: PCB MG | T3: Stator CF | U3: Rotor Ref | V3: Total | W3: PCB Ref | X3: PCB CF | Y3: PCB MG | Z3: Stator CF | AA3: Rotor Ref | AB3: Total | AD3: Product (INR in '000) | AE3: PCB Ref | AF3: PCB CF | AG3: PCB MG | AH3: Stator CF | AI3: Rotor Ref | AJ3: Total | AK3: PCB Ref | AL3: PCB CF | AM3: PCB MG | AN3: Stator CF | AO3: Rotor Ref | AP3: Total | AR3: Product (INR in '000) | AS3: PCB Ref | AT3: PCB CF | AU3: PCB MG | AV3: Stator CF | AW3: Rotor Ref | AX3: Total | AY3: PCB Ref | AZ3: PCB CF | BA3: PCB MG | BB3: Stator CF | BC3: Rotor Ref | BD3: Total | BF3: Product (INR in '000) | BG3: PCB Ref | BH3: PCB CF | BI3: PCB MG | BJ3: Stator CF | BK3: Rotor Ref | BL3: Total | BM3: PCB Ref | BN3: PCB CF | BO3: PCB MG | BP3: Stator CF | BQ3: Rotor Ref | BR3: Total | BT3: Product (INR in '000) | BU3: PCB Ref | BV3: PCB CF | BW3: PCB MG | BX3: Stator CF | BY3: Rotor Ref | BZ3: Total | CA3: PCB Ref | CB3: PCB CF | CC3: PCB MG | CD3: Stator CF | CE3: Rotor Ref | CF3: Total | CH3: Product (INR in '000) | CI3: PCB Ref | CJ3: PCB CF | CK3: PCB MG | CL3: Stator CF | CM3: ODU AC | CN3: Total | CO3: PCB Ref | CP3: PCB CF | CQ3: PCB MG | CR3: Stator CF | CS3: ODU AC | CT3: Total | CV3: Product (INR in '000) | CW3: PCB Ref | CX3: PCB CF | CY3: PCB MG | CZ3: Stator CF | DA3: ODU AC | DB3: Total | DC3: PCB Ref | DD3: PCB CF | DE3: PCB MG | DF3: Stator CF | DG3: ODU AC | DH3: Total | DJ3: Product (INR in '000) | DK3: PCB Ref | DL3: PCB CF | DM3: PCB MG | DN3: Stator CF | DO3: ODU AC | DP3: Total | DQ3: PCB Ref | DR3: PCB CF | DS3: PCB MG | DT3: Stator CF | DU3: ODU AC | DV3: Total | DX3: Product (INR in '000) | DY3: PCB Ref | DZ3: PCB CF | EA3: PCB MG | EB3: Stator CF | EC3: ODU AC | ED3: Total | EE3: PCB Ref | EF3: PCB CF | EG3: PCB MG | EH3: Stator CF | EI3: ODU AC | EJ3: Total | EL3: Product (INR in '000) | EM3: PCB Ref | EN3: PCB CF | EO3: PCB MG | EP3: Stator CF | EQ3: ODU AC | ER3: Total | ES3: PCB Ref | ET3: PCB CF | EU3: PCB MG | EV3: Stator CF | EW3: ODU AC | EX3: Total | EZ3: Product (INR in '000) | FA3: PCB Ref | FB3: PCB CF | FC3: PCB MG | FD3: Stator CF | FE3: ODU AC | FF3: Total | FG3: PCB Ref | FH3: PCB CF | FI3: PCB MG | FJ3: Stator CF | FK3: ODU AC | FL3: Total | FN3: Product (INR in '000) | FO3: PCB Ref | FP3: PCB CF | FQ3: PCB MG | FR3: Stator CF | FS3: ODU AC | FT3: Total | FU3: PCB Ref | FV3: PCB CF | FW3: PCB MG | FX3: Stator CF | FY3: ODU AC | FZ3: Total | GB3: Product (INR in '000) | GC3: PCB Ref | GD3: PCB CF | GE3: PCB MG | GF3: Stator CF | GG3: ODU AC | GH3: Total | GI3: PCB Ref | GJ3: PCB CF | GK3: PCB MG | GL3: Stator CF | GM3: ODU AC | GN3: Total | GP3: Product (INR in '000) | GQ3: PCB Ref | GR3: PCB CF | GS3: PCB MG | GT3: Stator CF | GU3: ODU AC | GV3: Total | GW3: PCB Ref | GX3: PCB CF | GY3: PCB MG | GZ3: Stator CF | HA3: ODU AC | HB3: Total | HD3: Product (INR in '000) | HE3: PCB Ref | HF3: PCB CF | HG3: PCB MG | HH3: Stator CF | HI3: ODU AC | HJ3: Total | HK3: PCB Ref | HL3: PCB CF | HM3: PCB MG | HN3: Stator CF | HO3: ODU AC | HP3: Total | HR3: Product (INR in '000) | HS3: PCB Ref | HT3: PCB CF | HU3: PCB MG | HV3: Stator CF | HW3: ODU AC | HX3: Total | HY3: PCB Ref | HZ3: PCB CF | IA3: PCB MG | IB3: Stator CF | IC3: ODU AC | ID3: Total | IF3: Product (INR in '000) | IG3: PCB Ref | IH3: PCB CF | II3: PCB MG | IJ3: Stator CF | IK3: ODU AC | IL3: Total | IM3: PCB Ref | IN3: PCB CF | IO3: PCB MG | IP3: Stator CF | IQ3: ODU AC | IR3: Total | IT3: Product (INR in '000) | IU3: PCB Ref | IV3: PCB CF | IW3: PCB MG | IX3: Stator CF | IY3: ODU AC | IZ3: Total | JA3: PCB Ref | JB3: PCB CF | JC3: PCB MG | JD3: Stator CF | JE3: ODU AC | JF3: Total | JH3: Product (INR in '000) | JI3: PCB Ref | JJ3: PCB CF | JK3: PCB MG | JL3: Stator CF | JM3: ODU AC | JN3: Total | JO3: PCB Ref | JP3: PCB CF | JQ3: PCB MG | JR3: Stator CF | JS3: ODU AC | JT3: Total | JV3: Product (INR in '000) | JW3: PCB Ref | JX3: PCB CF | JY3: PCB MG | JZ3: Stator CF | KA3: ODU AC | KB3: Total | KC3: PCB Ref | KD3: PCB CF | KE3: PCB MG | KF3: Stator CF | KG3: ODU AC | KH3: Total | KJ3: Product (INR in '000) | KK3: PCB Ref | KL3: PCB CF | KM3: PCB MG | KN3: Stator CF | KO3: ODU AC | KP3: Total | KQ3: PCB Ref | KR3: PCB CF | KS3: PCB MG | KT3: Stator CF | KU3: ODU AC | KV3: Total | KX3: Product (INR in '000) | KY3: PCB Ref | KZ3: PCB CF | LA3: PCB MG | LB3: Stator CF | LC3: ODU AC | LD3: Total | LE3: PCB Ref | LF3: PCB CF | LG3: PCB MG | LH3: Stator CF | LI3: ODU AC | LJ3: Total
B4: Qty (In Units) | C4: 0 | D4: 7560 | E4: 670 | F4: 2674 | G4: 0 | H4: 10904 | I4: 0 | J4: 17045 | K4: 2209 | L4: 4522 | M4: 0 | N4: 23776 | P4: Qty (In Units) | Q4: 0 | R4: 7560 | S4: 455 | T4: 2674 | U4: 0 | V4: 10689 | W4: 0 | X4: 17045 | Y4: 1504 | Z4: 4522 | AA4: 0 | AB4: 23071 | AD4: Qty (In Units) | AE4: 0 | AF4: 6427 | AG4: 315 | AH4: 3322 | AI4: 0 | AJ4: 10064 | AK4: 0 | AL4: 23472 | AM4: 1819 | AN4: 7844 | AO4: 0 | AP4: 33135 | AR4: Qty (In Units) | AS4: 0 | AT4: 6720 | AU4: 525 | AV4: 2016 | AW4: 0 | AX4: 9261 | AY4: 0 | AZ4: 30192 | BA4: 2344 | BB4: 9860 | BC4: 0 | BD4: 42396 | BF4: Qty (In Units) | BG4: 3000 | BH4: 9065 | BI4: 1050 | BJ4: 1904 | BK4: 0 | BL4: 15019 | BM4: 3000 | BN4: 54825 | BO4: 4549 | BP4: 19082 | BQ4: 0 | BR4: 81456 | BT4: Qty (In Units) | BU4: 0 | BV4: 5250 | BW4: 242 | BX4: 1876 | BY4: 0 | BZ4: 7368 | CA4: 3000 | CB4: 60075 | CC4: 4721 | CD4: 20958 | CE4: 0 | CF4: 88754 | CH4: Qty (In Units) | CI4: 0 | CJ4: 7355 | CK4: 735 | CL4: 3026 | CM4: 200 | CN4: =SUM(CI4:CM4) -> 11316 | CO4: 3000 | CP4: 67430 | CQ4: 5456 | CR4: 23984 | CS4: 200 | CT4: 100070 | CV4: Qty (In Units) | CW4: 0 | CX4: 8400 | CY4: 700 | CZ4: 4032 | DA4: 0 | DB4: 13132 | DC4: 3000 | DD4: 75830 | DE4: 6156 | DF4: 28016 | DG4: 200 | DH4: 113202 | DJ4: Qty (In Units) | DK4: 0 | DL4: 6265 | DM4: 140 | DN4: 2240 | DO4: 0 | DP4: 8645 | DQ4: 3000 | DR4: 82095 | DS4: 6296 | DT4: 30256 | DU4: 200 | DV4: 121847 | DX4: Qty (In Units) | DY4: 0 | DZ4: 6755 | EA4: 245 | EB4: 2520 | EC4: 0 | ED4: 9520 | EE4: 3000 | EF4: 88850 | EG4: 6541 | EH4: 32776 | EI4: 200 | EJ4: 131367 | EL4: Qty (In Units) | EM4: 0 | EN4: 11830 | EO4: 385 | EP4: 1008 | EQ4: 0 | ER4: 13223 | ES4: 3000 | ET4: 100680 | EU4: 6926 | EV4: 33784 | EW4: 200 | EX4: 144590 | EZ4: Qty (In Units) | FA4: 0 | FB4: 9940 | FC4: 770 | FD4: 2016 | FE4: 0 | FF4: 12726 | FG4: 3000 | FH4: 110620 | FI4: 7696 | FJ4: 35800 | FK4: 200 | FL4: 157316 | FN4: Qty (In Units) | FO4: 0 | FP4: 7560 | FQ4: 280 | FR4: 1008 | FS4: 0 | FT4: 8848 | FU4: 3000 | FV4: 118180 | FW4: 7976 | FX4: 36808 | FY4: 200 | FZ4: 166164 | GB4: Qty (In Units) | GC4: 0 | GD4: 7625 | GE4: 245 | GF4: 2016 | GG4: 0 | GH4: 9886 | GI4: 3000 | GJ4: 125805 | GK4: 8221 | GL4: 38824 | GM4: 200 | GN4: 176050 | GP4: Qty (In Units) | GQ4: 0 | GR4: 5460 | GS4: 1190 | GT4: 5531 | GU4: 0 | GV4: 12181 | GW4: 3000 | GX4: 131265 | GY4: 9411 | GZ4: 44355 | HA4: 200 | HB4: 188231 | HD4: Qty (In Units) | HE4: 0 | HF4: 8365 | HG4: 1254 | HH4: 2560 | HI4: 0 | HJ4: 12179 | HK4: 3000 | HL4: 139630 | HM4: 10665 | HN4: 46915 | HO4: 200 | HP4: 200410 | HR4: Qty (In Units) | HS4: 0 | HT4: 5880 | HU4: 1085 | HV4: 2424 | HW4: 0 | HX4: 9389 | HY4: 3000 | HZ4: 145510 | IA4: 11750 | IB4: 49339 | IC4: 200 | ID4: 209799 | IF4: Qty (In Units) | IG4: 0 | IH4: 5005 | II4: 875 | IJ4: 2588 | IK4: 0 | IL4: 8468 | IM4: 3000 | IN4: 150515 | IO4: 12625 | IP4: 51927 | IQ4: 200 | IR4: 218267 | IT4: Qty (In Units) | IU4: 0 | IV4: 6195 | IW4: 239 | IX4: 3024 | IY4: 0 | IZ4: 9458 | JA4: 3000 | JB4: 156710 | JC4: 12864 | JD4: 54951 | JE4: 200 | JF4: 227725 | JH4: Qty (In Units) | JI4: 2807 | JJ4: 5880 | JK4: 175 | JL4: 2457 | JM4: 0 | JN4: 11319 | JO4: 5807 | JP4: 162590 | JQ4: 13039 | JR4: 57408 | JS4: 200 | JT4: 239044 | JV4: Qty (In Units) | JW4: 50 | JX4: 6615 | JY4: 595 | JZ4: 3192 | KA4: 0 | KB4: 10452 | KC4: 5857 | KD4: 169205 | KE4: 13634 | KF4: 60600 | KG4: 200 | KH4: 249496 | KJ4: Qty (In Units) | KK4: 2200 | KL4: 10850 | KM4: 245 | KN4: 1817 | KO4: 0 | KP4: 15112 | KQ4: 8057 | KR4: 180055 | KS4: 13879 | KT4: 62417 | KU4: 200 | KV4: 264608 | KX4: Qty (In Units) | KY4: 0 | KZ4: 7766 | LA4: 595 | LB4: 0 | LC4: 0 | LD4: 8361 | LE4: 8057 | LF4: 187821 | LG4: 14474 | LH4: 62417 | LI4: 200 | LJ4: 272969 | LK4: =LE4-KY4-KQ4 -> 0 | LL4: =LF4-KZ4-KR4 -> 0 | LM4: =LG4-LA4-KS4 -> 0 | LN4: =LH4-LB4-KT4 -> 0 | LO4: =LI4-LC4-KU4 -> 0 | LP4: =LJ4-LD4-KV4 -> 0
B5: Sales | C5: 0 | D5: 2679.1296 | E5: 412.616 | F5: 413.69454 | G5: 0 | H5: 3505.4401 | I5: 0 | J5: 6348.3672 | K5: 1343.564 | L5: 699.59862 | M5: 0 | N5: 8391.5298 | P5: Sales | Q5: 0 | R5: 2679.1296 | S5: 412.616 | T5: 413.69454 | U5: 0 | V5: 3505.4401 | W5: 0 | X5: 6348.3672 | Y5: 1343.564 | Z5: 699.59862 | AA5: 0 | AB5: 8391.5298 | AD5: Sales | AE5: 0 | AF5: 2293.6611 | AG5: 320.69065 | AH5: 580.25912 | AI5: 0 | AJ5: 3194.6109 | AK5: 0 | AL5: 8642.0284 | AM5: 1664.2547 | AN5: 1279.8577 | AO5: 0 | AP5: 11586.141 | AR5: Sales | AS5: 0 | AT5: 2616.432 | AU5: 488.4075 | AV5: 311.89536 | AW5: 0 | AX5: 3416.7349 | AY5: 0 | AZ5: 11258.46 | BA5: 2152.6622 | BB5: 1591.7531 | BC5: 0 | BD5: 15002.876 | BF5: Sales | BG5: 2217.93 | BH5: 3335.2592 | BI5: 761.99585 | BJ5: 315.36344 | BK5: 0 | BL5: 6630.5485 | BM5: 2217.93 | BN5: 20256.261 | BO5: 4076.6889 | BP5: 3129.9998 | BQ5: 0 | BR5: 29680.879 | BT5: Sales | BU5: 0 | BV5: 2082.36 | BW5: 265.4349 | BX5: 321.42936 | BY5: 0 | BZ5: 2669.2243 | CA5: 2217.93 | CB5: 22338.621 | CC5: 4342.1238 | CD5: 3451.4292 | CE5: 0 | CF5: 32350.104 | CH5: Sales | CI5: 0 | CJ5: 2634.36 | CK5: 671.17645 | CL5: 521.73296 | CM5: 143.6 | CN5: =SUM(CI5:CM5) -> 3970.8694 | CO5: 2217.93 | CP5: 24972.981 | CQ5: 5013.3003 | CR5: 3973.1621 | CS5: 143.6 | CT5: 36320.973 | CV5: Sales | CW5: 0 | CX5: 3011.0976 | CY5: 797.77625 | CZ5: 677.26512 | DA5: 0 | DB5: 4486.139 | DC5: 2217.93 | DD5: 27984.078 | DE5: 5811.0765 | DF5: 4650.4273 | DG5: 143.6 | DH5: 40807.112 | DJ5: Sales | DK5: 0 | DL5: 2236.0464 | DM5: 265.81205 | DN5: 411.908 | DO5: 0 | DP5: 2913.7664 | DQ5: 2217.93 | DR5: 30220.125 | DS5: 6076.8886 | DT5: 5062.3353 | DU5: 143.6 | DV5: 43720.878 | DX5: Sales | DY5: 0 | DZ5: 2589.181 | EA5: 269.93925 | EB5: 470.0808 | EC5: 0 | ED5: 3329.2011 | EE5: 2217.93 | EF5: 32809.306 | EG5: 6346.8278 | EH5: 5532.4161 | EI5: 143.6 | EJ5: 47050.08 | EL5: Sales | EM5: 0 | EN5: 4254.9514 | EO5: 256.06805 | EP5: 209.42208 | EQ5: 0 | ER5: 4720.4415 | ES5: 2217.93 | ET5: 37064.257 | EU5: 6602.8959 | EV5: 5741.8381 | EW5: 143.6 | EX5: 51770.521 | EZ5: Sales | FA5: 0 | FB5: 3542.5152 | FC5: 548.13115 | FD5: 365.36976 | FE5: 0 | FF5: 4456.0161 | FG5: 2217.93 | FH5: 40606.772 | FI5: 7151.027 | FJ5: 6107.2079 | FK5: 143.6 | FL5: 56226.537 | FN5: Sales | FO5: 0 | FP5: 2702.2464 | FQ5: 299.0974 | FR5: 209.42208 | FS5: 0 | FT5: 3210.7659 | FU5: 2217.93 | FV5: 43309.019 | FW5: 7450.1244 | FX5: 6316.63 | FY5: 143.6 | FZ5: 59437.303 | GB5: Sales | GC5: 0 | GD5: 2719.2144 | GE5: 229.866 | GF5: 418.84416 | GG5: 0 | GH5: 3367.9246 | GI5: 2217.93 | GJ5: 46028.233 | GK5: 7679.9904 | GL5: 6735.4741 | GM5: 143.6 | GN5: 62805.228 | GP5: Sales | GQ5: 0 | GR5: 1980.1936 | GS5: 704.24165 | GT5: 951.69069 | GU5: 0 | GV5: 3636.1259 | GW5: 2217.93 | GX5: 48008.427 | GY5: 8384.2321 | GZ5: 7687.1648 | HA5: 143.6 | HB5: 66441.354 | HD5: Sales | HE5: 0 | HF5: 2988.9608 | HG5: 739.92306 | HH5: 482.9535 | HI5: 0 | HJ5: 4211.8374 | HK5: 2217.93 | HL5: 50997.387 | HM5: 9124.1551 | HN5: 8170.1183 | HO5: 143.6 | HP5: 70653.191 | HR5: Sales | HS5: 0 | HT5: 2100.672 | HU5: 676.33125 | HV5: 396.88632 | HW5: 0 | HX5: 3173.8896 | HY5: 2217.93 | HZ5: 53098.059 | IA5: 9800.4864 | IB5: 8567.0047 | IC5: 143.6 | ID5: 73827.08 | IF5: Sales | IG5: 0 | IH5: 1782.5808 | II5: 652.0129 | IJ5: 400.50948 | IK5: 0 | IL5: 2835.1032 | IM5: 2217.93 | IN5: 54880.64 | IO5: 10452.499 | IP5: 8967.5141 | IQ5: 143.6 | IR5: 76662.184 | IT5: Sales | IU5: 0 | IV5: 2238.313 | IW5: 206.89008 | IX5: 552.29328 | IY5: 0 | IZ5: 2997.4964 | JA5: 2217.93 | JB5: 57118.953 | JC5: 10659.389 | JD5: 9519.8074 | JE5: 143.6 | JF5: 79659.68 | JH5: Sales | JI5: 1850.6832 | JJ5: 2100.672 | JK5: 181.12675 | JL5: 427.84532 | JM5: 0 | JN5: 4560.3272 | JO5: 4068.6132 | JP5: 59219.625 | JQ5: 10840.516 | JR5: 9947.6527 | JS5: 143.6 | JT5: 84220.007 | JV5: Sales | JW5: 32.965 | JX5: 2383.4748 | JY5: 618.13535 | JZ5: 473.23752 | KA5: 0 | KB5: 3507.8127 | KC5: 4101.5782 | KD5: 61603.1 | KE5: 11458.651 | KF5: 10420.89 | KG5: 143.6 | KH5: 87727.82 | KJ5: Sales | KK5: 1450.482 | KL5: 3917.676 | KM5: 237.9951 | KN5: 313.96301 | KO5: 0 | KP5: 5920.1161 | KQ5: 5552.0602 | KR5: 65520.776 | KS5: 11696.647 | KT5: 10734.853 | KU5: 143.6 | KV5: 93647.936 | KX5: Sales | KY5: 0 | KZ5: 2621.1744 | LA5: 544.9234 | LB5: 0 | LC5: 0 | LD5: 3166.0978 | LE5: 5552.0602 | LF5: 68141.95 | LG5: 12241.57 | LH5: 10734.853 | LI5: 143.6 | LJ5: 96814.034 | LK5: =LE5-KY5-KQ5 -> 0 | LL5: =LF5-KZ5-KR5 -> 0 | LM5: =LG5-LA5-KS5 -> 0 | LN5: =LH5-LB5-KT5 -> 0 | LO5: =LI5-LC5-KU5 -> 0 | LP5: =LJ5-LD5-KV5 -> 0
B6: COGS | C6: 0 | D6: 2633.5344 | E6: 383.00635 | F6: 395.11024 | G6: 0 | H6: 3411.651 | I6: 0 | J6: 6192.3183 | K6: 1234.2015 | L6: 668.17072 | M6: 0 | N6: 8094.6905 | P6: COGS | Q6: 0 | R6: 2633.5344 | S6: 383.00635 | T6: 395.11024 | U6: 0 | V6: 3411.651 | W6: 0 | X6: 6192.3183 | Y6: 1234.2015 | Z6: 668.17072 | AA6: 0 | AB6: 8094.6905 | AD6: COGS | AE6: 0 | AF6: 2239.4424 | AG6: 309.6457 | AH6: 545.93372 | AI6: 0 | AJ6: 3095.0218 | AK6: 0 | AL6: 8431.7607 | AM6: 1534.3855 | AN6: 1214.1044 | AO6: 0 | AP6: 11180.251 | AR6: COGS | AS6: 0 | AT6: 2529.3072 | AU6: 500.20425 | AV6: 297.88416 | AW6: 0 | AX6: 3327.3956 | AY6: 0 | AZ6: 10961.068 | BA6: 2034.5897 | BB6: 1511.9886 | BC6: 0 | BD6: 14507.646 | BF6: COGS | BG6: 1487.49 | BH6: 3239.7901 | BI6: 715.97925 | BJ6: 298.60656 | BK6: 0 | BL6: 5741.8659 | BM6: 1487.49 | BN6: 19718.45 | BO6: 3913.8738 | BP6: 2967.2454 | BQ6: 0 | BR6: 28087.059 | BT6: COGS | BU6: 0 | BV6: 2007.2808 | BW6: 208.21742 | BX6: 303.10504 | BY6: 0 | BZ6: 2518.6033 | CA6: 1487.49 | CB6: 21725.73 | CC6: 4122.0912 | CD6: 3270.3505 | CE6: 0 | CF6: 30605.662 | CH6: COGS | CI6: 0 | CJ6: 2573.4695 | CK6: 618.3037 | CL6: 491.62236 | CM6: 168.73472 | CN6: =SUM(CI6:CM6) -> 3852.1303 | CO6: 1487.49 | CP6: 24299.2 | CQ6: 4740.3949 | CR6: 3761.9728 | CS6: 168.73472 | CT6: 34457.792 | CV6: COGS | CW6: 0 | CX6: 2942.1168 | CY6: 693.36825 | CZ6: 640.1808 | DA6: 0 | DB6: 4275.6658 | DC6: 1487.49 | DD6: 27241.317 | DE6: 5433.7631 | DF6: 4402.1536 | DG6: 168.73472 | DH6: 38733.458 | DJ6: COGS | DK6: 0 | DL6: 2182.6217 | DM6: 319.71415 | DN6: 385.26432 | DO6: 0 | DP6: 2887.6002 | DQ6: 1487.49 | DR6: 29423.938 | DS6: 5753.4773 | DT6: 4787.418 | DU6: 168.73472 | DV6: 41621.058 | DX6: COGS | DY6: 0 | DZ6: 2504.4912 | EA6: 273.805 | EB6: 438.97392 | EC6: 0 | ED6: 3217.2701 | EE6: 1487.49 | EF6: 31928.429 | EG6: 6027.2823 | EH6: 5226.3919 | EI6: 168.73472 | EJ6: 44838.328 | EL6: COGS | EM6: 0 | EN6: 4152.9435 | EO6: 278.6644 | EP6: 193.35456 | EQ6: 0 | ER6: 4624.9625 | ES6: 1487.49 | ET6: 36081.373 | EU6: 6305.9467 | EV6: 5419.7464 | EW6: 168.73472 | EX6: 49463.291 | EZ6: COGS | FA6: 0 | FB6: 3475.5812 | FC6: 520.29565 | FD6: 342.29664 | FE6: 0 | FF6: 4338.1735 | FG6: 1487.49 | FH6: 39556.954 | FI6: 6826.2423 | FJ6: 5762.0431 | FK6: 168.73472 | FL6: 53801.464 | FN6: COGS | FO6: 0 | FP6: 2638.5912 | FQ6: 326.9966 | FR6: 193.35456 | FS6: 0 | FT6: 3158.9424 | FU6: 1487.49 | FV6: 42195.545 | FW6: 7153.2389 | FX6: 5955.3976 | FY6: 168.73472 | FZ6: 56960.407 | GB6: COGS | GC6: 0 | GD6: 2653.38 | GE6: 252.22855 | GF6: 386.70912 | GG6: 0 | GH6: 3292.3177 | GI6: 1487.49 | GJ6: 44848.925 | GK6: 7405.4675 | GL6: 6342.1068 | GM6: 168.73472 | GN6: 60252.724 | GP6: COGS | GQ6: 0 | GR6: 1926.946 | GS6: 814.69955 | GT6: 898.58795 | GU6: 0 | GV6: 3640.2335 | GW6: 1487.49 | GX6: 46775.871 | GY6: 8220.167 | GZ6: 7240.6947 | HA6: 168.73472 | HB6: 63892.958 | HD6: COGS | HE6: 0 | HF6: 2926.575 | HG6: 731.87554 | HH6: 450.43588 | HI6: 0 | HJ6: 4108.8865 | HK6: 1487.49 | HL6: 49702.446 | HM6: 8952.0426 | HN6: 7691.1306 | HO6: 168.73472 | HP6: 68001.844 | HR6: COGS | HS6: 0 | HT6: 2050.944 | HU6: 657.4708 | HV6: 380.9604 | HW6: 0 | HX6: 3089.3752 | HY6: 1487.49 | HZ6: 51753.39 | IA6: 9609.5134 | IB6: 8072.091 | IC6: 168.73472 | ID6: 71091.22 | IF6: COGS | IG6: 0 | IH6: 1738.7773 | II6: 632.63095 | IJ6: 388.44956 | IK6: 0 | IL6: 2759.8578 | IM6: 1487.49 | IN6: 53492.168 | IO6: 10242.144 | IP6: 8460.5406 | IQ6: 168.73472 | IR6: 73851.077 | IT6: COGS | IU6: 0 | IV6: 2183.2458 | IW6: 208.15851 | IX6: 520.25904 | IY6: 0 | IZ6: 2911.6633 | JA6: 1487.49 | JB6: 55675.413 | JC6: 10450.303 | JD6: 8980.7996 | JE6: 168.73472 | JF6: 76762.741 | JH6: COGS | JI6: 1391.7948 | JJ6: 2050.608 | JK6: 244.8677 | JL6: 405.4267 | JM6: 0 | JN6: 4092.6972 | JO6: 2879.2848 | JP6: 57726.021 | JQ6: 10695.171 | JR6: 9386.2263 | JS6: 168.73472 | JT6: 80855.438 | JV6: COGS | JW6: 24.689 | JX6: 2321.9263 | JY6: 610.1837 | JZ6: 462.77784 | KA6: 0 | KB6: 3419.5768 | KC6: 2903.9738 | KD6: 60047.948 | KE6: 11305.354 | KF6: 9849.0041 | KG6: 168.73472 | KH6: 84275.015 | KJ6: COGS | KK6: 1090.826 | KL6: 3814.3777 | KM6: 228.42645 | KN6: 298.52175 | KO6: 0 | KP6: 5432.1519 | KQ6: 3994.7998 | KR6: 63862.325 | KS6: 11533.781 | KT6: 10147.526 | KU6: 168.73472 | KV6: 89707.167 | KX6: COGS | KY6: 0 | KZ6: 2577.5123 | LA6: 505.92885 | LB6: 0 | LC6: 0 | LD6: 3083.4411 | LE6: 3994.7998 | LF6: 66439.838 | LG6: 12039.71 | LH6: 10147.526 | LI6: 168.73472 | LJ6: 92790.608 | LK6: =LE6-KY6-KQ6 -> 0 | LL6: =LF6-KZ6-KR6 -> 0 | LM6: =LG6-LA6-KS6 -> 0 | LN6: =LH6-LB6-KT6 -> 0 | LO6: =LI6-LC6-KU6 -> 0 | LP6: =LJ6-LD6-KV6 -> 0
B7: BOM cost | C7: 0 | D7: 2134.2888 | E7: 323.52845 | F7: 377.9699 | G7: 0 | H7: 2835.7871 | I7: 0 | J7: 5058.8654 | K7: 1053.4713 | L7: 639.1847 | M7: 0 | N7: 6751.5213 | P7: BOM cost | Q7: 0 | R7: 2134.2888 | S7: 323.52845 | T7: 377.9699 | U7: 0 | V7: 2835.7871 | W7: 0 | X7: 5058.8654 | Y7: 1053.4713 | Z7: 639.1847 | AA7: 0 | AB7: 6751.5213 | AD7: BOM cost | AE7: 0 | AF7: 1830.1745 | AG7: 248.2277 | AH7: 524.6397 | AI7: 0 | AJ7: 2603.0419 | AK7: 0 | AL7: 6889.0399 | AM7: 1301.699 | AN7: 1163.8244 | AO7: 0 | AP7: 9354.5632 | AR7: BOM cost | AS7: 0 | AT7: 2085.1992 | AU7: 380.50635 | AV7: 284.9616 | AW7: 0 | AX7: 2750.6671 | AY7: 0 | AZ7: 8974.2391 | BA7: 1682.2053 | BB7: 1448.786 | BC7: 0 | BD7: 12105.23 | BF7: BOM cost | BG7: 1264.83 | BH7: 2653.2937 | BI7: 598.74325 | BJ7: 286.40192 | BK7: 0 | BL7: 4803.2688 | BM7: 1264.83 | BN7: 16140.766 | BO7: 3185.5589 | BP7: 2844.9298 | BQ7: 0 | BR7: 23436.085 | BT7: BOM cost | BU7: 0 | BV7: 1655.9403 | BW7: 174.45828 | BX7: 291.07988 | BY7: 0 | BZ7: 2121.4785 | CA7: 1264.83 | CB7: 17796.707 | CC7: 3360.0172 | CD7: 3136.0097 | CE7: 0 | CF7: 25557.564 | CH7: BOM cost | CI7: 0 | CJ7: 2104.0734 | CK7: 525.0833 | CL7: 472.2257 | CM7: 162.32472 | CN7: =SUM(CI7:CM7) -> 3263.7071 | CO7: 1264.83 | CP7: 19900.78 | CQ7: 3885.1005 | CR7: 3608.2354 | CS7: 162.32472 | CT7: 28821.271 | CV7: BOM cost | CW7: 0 | CX7: 2406.0288 | CY7: 549.23955 | CZ7: 614.33568 | DA7: 0 | DB7: 3569.604 | DC7: 1264.83 | DD7: 22306.809 | DE7: 4434.3401 | DF7: 4222.5711 | DG7: 162.32472 | DH7: 32390.875 | DJ7: BOM cost | DK7: 0 | DL7: 1782.7894 | DM7: 201.51355 | DN7: 370.90592 | DO7: 0 | DP7: 2355.2089 | DQ7: 1264.83 | DR7: 24089.598 | DS7: 4635.8536 | DT7: 4593.477 | DU7: 162.32472 | DV7: 34746.084 | DX7: BOM cost | DY7: 0 | DZ7: 2060.3716 | EA7: 209.0438 | EB7: 422.82072 | EC7: 0 | ED7: 2692.2361 | EE7: 1264.83 | EF7: 26149.97 | EG7: 4844.8974 | EH7: 5016.2977 | EI7: 162.32472 | EJ7: 37438.32 | EL7: BOM cost | EM7: 0 | EN7: 3396.3657 | EO7: 198.7811 | EP7: 186.89328 | EQ7: 0 | ER7: 3782.0401 | ES7: 1264.83 | ET7: 29546.336 | EU7: 5043.6785 | EV7: 5203.191 | EW7: 162.32472 | EX7: 41220.36 | EZ7: BOM cost | FA7: 0 | FB7: 2828.6356 | FC7: 431.36975 | FD7: 329.37408 | FE7: 0 | FF7: 3589.3794 | FG7: 1264.83 | FH7: 32374.971 | FI7: 5475.0483 | FJ7: 5532.5651 | FK7: 162.32472 | FL7: 44809.739 | FN7: BOM cost | FO7: 0 | FP7: 2156.112 | FQ7: 232.1627 | FR7: 186.89328 | FS7: 0 | FT7: 2575.168 | FU7: 1264.83 | FV7: 34531.083 | FW7: 5707.211 | FX7: 5719.4584 | FY7: 162.32472 | FZ7: 47384.907 | GB7: BOM cost | GC7: 0 | GD7: 2166.7525 | GE7: 175.94885 | GF7: 373.78656 | GG7: 0 | GH7: 2716.4879 | GI7: 1264.83 | GJ7: 36697.836 | GK7: 5883.1598 | GL7: 6093.2449 | GM7: 162.32472 | GN7: 50101.395 | GP7: BOM cost | GQ7: 0 | GR7: 1575.9492 | GS7: 547.87845 | GT7: 863.13424 | GU7: 0 | GV7: 2986.9619 | GW7: 1264.83 | GX7: 38273.785 | GY7: 6431.0383 | GZ7: 6956.3792 | HA7: 162.32472 | HB7: 53088.357 | HD7: BOM cost | HE7: 0 | HF7: 2388.7038 | HG7: 582.54214 | HH7: 434.02628 | HI7: 0 | HJ7: 3405.2722 | HK7: 1264.83 | HL7: 40662.489 | HM7: 7013.5804 | HN7: 7390.4054 | HO7: 162.32472 | HP7: 56493.629 | HR7: BOM cost | HS7: 0 | HT7: 1675.6824 | HU7: 531.4029 | HV7: 365.42256 | HW7: 0 | HX7: 2572.5079 | HY7: 1264.83 | HZ7: 42338.171 | IA7: 7544.9833 | IB7: 7755.828 | IC7: 162.32472 | ID7: 59066.137 | IF7: BOM cost | IG7: 0 | IH7: 1419.3582 | II7: 512.51585 | IJ7: 371.86048 | IK7: 0 | IL7: 2303.7345 | IM7: 1264.83 | IN7: 43757.529 | IO7: 8057.4992 | IP7: 8127.6885 | IQ7: 162.32472 | IR7: 61369.872 | IT7: BOM cost | IU7: 0 | IV7: 1786.2936 | IW7: 162.36503 | IX7: 500.8752 | IY7: 0 | IZ7: 2449.5338 | JA7: 1264.83 | JB7: 45543.823 | JC7: 8219.8642 | JD7: 8628.5637 | JE7: 162.32472 | JF7: 63819.405 | JH7: BOM cost | JI7: 1183.4593 | JJ7: 1675.3464 | JK7: 137.9196 | JL7: 389.67733 | JM7: 0 | JN7: 3386.4026 | JO7: 2448.2893 | JP7: 47219.169 | JQ7: 8357.7838 | JR7: 9018.241 | JS7: 162.32472 | JT7: 67205.808 | JV7: BOM cost | JW7: 21.2565 | JX7: 1897.8523 | JY7: 482.8061 | JZ7: 442.31712 | KA7: 0 | KB7: 2844.232 | KC7: 2469.5458 | KD7: 49117.021 | KE7: 8840.5899 | KF7: 9460.5581 | KG7: 162.32472 | KH7: 70050.04 | KJ7: BOM cost | KK7: 927.542 | KL7: 3118.1213 | KM7: 185.95885 | KN7: 286.87478 | KO7: 0 | KP7: 4518.4969 | KQ7: 3397.0878 | KR7: 52235.143 | KS7: 9026.5487 | KT7: 9747.4329 | KU7: 162.32472 | KV7: 74568.537 | KX7: BOM cost | KY7: 0 | KZ7: 2093.2347 | LA7: 427.16205 | LB7: 0 | LC7: 0 | LD7: 2520.3967 | LE7: 3397.0878 | LF7: 54328.377 | LG7: 9453.7108 | LH7: 9747.4329 | LI7: 162.32472 | LJ7: 77088.934 | LK7: =LE7-KY7-KQ7 -> 0 | LL7: =LF7-KZ7-KR7 -> 0 | LM7: =LG7-LA7-KS7 -> 0 | LN7: =LH7-LB7-KT7 -> 0 | LO7: =LI7-LC7-KU7 -> 0 | LP7: =LJ7-LD7-KV7 -> 0
B8: Labour Cost | C8: 0 | D8: 255.738 | E8: 32.94395 | F8: 12.3004 | G8: 0 | H8: 300.98235 | I8: 0 | J8: 581.8764 | K8: 98.24051 | L8: 20.8012 | M8: 0 | N8: 700.91811 | P8: Labour Cost | Q8: 0 | R8: 255.738 | S8: 32.94395 | T8: 12.3004 | U8: 0 | V8: 300.98235 | W8: 0 | X8: 581.8764 | Y8: 98.24051 | Z8: 20.8012 | AA8: 0 | AB8: 700.91811 | AD8: Labour Cost | AE8: 0 | AF8: 207.25576 | AG8: 37.2785 | AH8: 15.2812 | AI8: 0 | AJ8: 259.81546 | AK8: 0 | AL8: 789.13216 | AM8: 135.51901 | AN8: 36.0824 | AO8: 0 | AP8: 960.73357 | AR8: Labour Cost | AS8: 0 | AT8: 227.5392 | AU8: 72.43635 | AV8: 9.2736 | AW8: 0 | AX8: 309.24915 | AY8: 0 | AZ8: 1016.6714 | BA8: 207.95536 | BB8: 45.356 | BC8: 0 | BD8: 1269.9827 | BF8: Labour Cost | BG8: 118.05 | BH8: 298.44815 | BI8: 67.69385 | BJ8: 8.7584 | BK8: 0 | BL8: 492.9504 | BM8: 118.05 | BN8: 1826.4127 | BO8: 432.06689 | BP8: 87.7772 | BQ8: 0 | BR8: 2464.3068 | BT8: Labour Cost | BU8: 0 | BV8: 180.7218 | BW8: 20.18847 | BX8: 8.6296 | BY8: 0 | BZ8: 209.53987 | CA8: 118.05 | CB8: 2007.1345 | CC8: 452.25536 | CD8: 96.4068 | CE8: 0 | CF8: 2673.8467 | CH8: Labour Cost | CI8: 0 | CJ8: 237.78715 | CK8: 54.2297 | CL8: 13.9196 | CM8: 4.6 | CN8: =SUM(CI8:CM8) -> 310.53645 | CO8: 118.05 | CP8: 2244.9217 | CQ8: 506.48506 | CR8: 110.3264 | CS8: 4.6 | CT8: 2984.3832 | CV8: Labour Cost | CW8: 0 | CX8: 271.572 | CY8: 87.3898 | CZ8: 18.5472 | DA8: 0 | DB8: 377.509 | DC8: 118.05 | DD8: 2516.4937 | DE8: 593.87486 | DF8: 128.8736 | DG8: 4.6 | DH8: 3361.8921 | DJ8: Labour Cost | DK8: 0 | DL8: 202.54745 | DM8: 74.54615 | DN8: 10.304 | DO8: 0 | DP8: 287.3976 | DQ8: 118.05 | DR8: 2719.0411 | DS8: 668.42101 | DT8: 139.1776 | DU8: 4.6 | DV8: 3649.2897 | DX8: Labour Cost | DY8: 0 | DZ8: 227.17135 | EA8: 39.6088 | EB8: 11.592 | EC8: 0 | ED8: 278.37215 | EE8: 118.05 | EF8: 2946.2125 | EG8: 708.02981 | EH8: 150.7696 | EI8: 4.6 | EJ8: 3927.6619 | EL8: Labour Cost | EM8: 0 | EN8: 383.5349 | EO8: 48.538 | EP8: 4.6368 | EQ8: 0 | ER8: 436.7097 | ES8: 118.05 | ET8: 3329.7474 | EU8: 756.56781 | EV8: 155.4064 | EW8: 4.6 | EX8: 4364.3716 | EZ8: Labour Cost | FA8: 0 | FB8: 329.8526 | FC8: 51.18155 | FD8: 9.2736 | FE8: 0 | FF8: 390.30775 | FG8: 118.05 | FH8: 3659.6 | FI8: 807.74936 | FJ8: 164.68 | FK8: 4.6 | FL8: 4754.6794 | FN8: Labour Cost | FO8: 0 | FP8: 244.4148 | FQ8: 58.74225 | FR8: 4.6368 | FS8: 0 | FT8: 307.79385 | FU8: 118.05 | FV8: 3904.0148 | FW8: 866.49161 | FX8: 169.3168 | FY8: 4.6 | FZ8: 5062.4732 | GB8: Labour Cost | GC8: 0 | GD8: 246.51625 | GE8: 47.38405 | GF8: 9.2736 | GG8: 0 | GH8: 303.1739 | GI8: 118.05 | GJ8: 4150.531 | GK8: 913.87566 | GL8: 178.5904 | GM8: 4.6 | GN8: 5365.6471 | GP8: Labour Cost | GQ8: 0 | GR8: 178.2354 | GS8: 162.44725 | GT8: 25.4426 | GU8: 0 | GV8: 366.12525 | GW8: 118.05 | GX8: 4328.7664 | GY8: 1076.3229 | GZ8: 204.033 | HA8: 4.6 | HB8: 5731.7724 | HD8: Labour Cost | HE8: 0 | HF8: 273.1533 | HG8: 86.74776 | HH8: 11.776 | HI8: 0 | HJ8: 371.67706 | HK8: 118.05 | HL8: 4601.9197 | HM8: 1163.0707 | HN8: 215.809 | HO8: 4.6 | HP8: 6103.4494 | HR8: Labour Cost | HS8: 0 | HT8: 190.1004 | HU8: 73.206 | HV8: 11.1504 | HW8: 0 | HX8: 274.4568 | HY8: 118.05 | HZ8: 4792.0201 | IA8: 1236.2767 | IB8: 226.9594 | IC8: 4.6 | ID8: 6377.9062 | IF8: Labour Cost | IG8: 0 | IH8: 161.81165 | II8: 70.5418 | IJ8: 11.9048 | IK8: 0 | IL8: 244.25825 | IM8: 118.05 | IN8: 4953.8318 | IO8: 1306.8185 | IP8: 238.8642 | IQ8: 4.6 | IR8: 6622.1645 | IT8: Labour Cost | IU8: 0 | IV8: 201.35535 | IW8: 27.89159 | IX8: 13.9104 | IY8: 0 | IZ8: 243.15734 | JA8: 118.05 | JB8: 5155.1871 | JC8: 1334.7101 | JD8: 252.7746 | JE8: 4.6 | JF8: 6865.3218 | JH8: Labour Cost | JI8: 110.45545 | JJ8: 190.1004 | JK8: 67.5962 | JL8: 11.3022 | JM8: 0 | JN8: 379.45425 | JO8: 228.50545 | JP8: 5345.2875 | JQ8: 1402.3063 | JR8: 264.0768 | JS8: 4.6 | JT8: 7244.776 | JV8: Labour Cost | JW8: 1.9675 | JX8: 215.14815 | JY8: 77.3241 | JZ8: 14.6832 | KA8: 0 | KB8: 309.12295 | KC8: 230.47295 | KD8: 5560.4357 | KE8: 1479.6304 | KF8: 278.76 | KG8: 4.6 | KH8: 7553.899 | KJ8: Labour Cost | KK8: 86.57 | KL8: 353.3509 | KM8: 25.23955 | KN8: 8.3582 | KO8: 0 | KP8: 473.51865 | KQ8: 317.04295 | KR8: 5913.7866 | KS8: 1504.8699 | KT8: 287.1182 | KU8: 4.6 | KV8: 8027.4176 | KX8: Labour Cost | KY8: 0 | KZ8: 243.41718 | LA8: 45.75235 | LB8: 0 | LC8: 0 | LD8: 289.16953 | LE8: 317.04295 | LF8: 6157.2038 | LG8: 1550.6223 | LH8: 287.1182 | LI8: 4.6 | LJ8: 8316.5872 | LK8: =LE8-KY8-KQ8 -> 0 | LL8: =LF8-KZ8-KR8 -> 0 | LM8: =LG8-LA8-KS8 -> 0 | LN8: =LH8-LB8-KT8 -> 0 | LO8: =LI8-LC8-KU8 -> 0 | LP8: =LJ8-LD8-KV8 -> 0
B9: Other Conv Cost | C9: 0 | D9: 243.5076 | E9: 26.53395 | F9: 4.83994 | G9: 0 | H9: 274.88149 | I9: 0 | J9: 551.57655 | K9: 82.48967 | L9: 8.18482 | M9: 0 | N9: 642.25104 | P9: Other Conv Cost | Q9: 0 | R9: 243.5076 | S9: 26.53395 | T9: 4.83994 | U9: 0 | V9: 274.88149 | W9: 0 | X9: 551.57655 | Y9: 82.48967 | Z9: 8.18482 | AA9: 0 | AB9: 642.25104 | AD9: Other Conv Cost | AE9: 0 | AF9: 202.01213 | AG9: 24.1395 | AH9: 6.01282 | AI9: 0 | AJ9: 232.16445 | AK9: 0 | AL9: 753.58868 | AM9: 97.16747 | AN9: 14.19764 | AO9: 0 | AP9: 864.95379 | AR9: Other Conv Cost | AS9: 0 | AT9: 216.5688 | AU9: 47.26155 | AV9: 3.64896 | AW9: 0 | AX9: 267.47931 | AY9: 0 | AZ9: 970.15748 | BA9: 144.42902 | BB9: 17.8466 | BC9: 0 | BD9: 1132.4331 | BF9: Other Conv Cost | BG9: 104.61 | BH9: 288.04825 | BI9: 49.54215 | BJ9: 3.44624 | BK9: 0 | BL9: 445.64664 | BM9: 104.61 | BN9: 1751.2704 | BO9: 296.24793 | BP9: 34.53842 | BQ9: 0 | BR9: 2186.6667 | BT9: Other Conv Cost | BU9: 0 | BV9: 170.6187 | BW9: 13.57067 | BX9: 3.39556 | BY9: 0 | BZ9: 187.58493 | CA9: 104.61 | CB9: 1921.8891 | CC9: 309.8186 | CD9: 37.93398 | CE9: 0 | CF9: 2374.2517 | CH9: Other Conv Cost | CI9: 0 | CJ9: 231.60895 | CK9: 38.9907 | CL9: 5.47706 | CM9: 1.81 | CN9: =SUM(CI9:CM9) -> 277.88671 | CO9: 104.61 | CP9: 2153.498 | CQ9: 348.8093 | CR9: 43.41104 | CS9: 1.81 | CT9: 2652.1384 | CV9: Other Conv Cost | CW9: 0 | CX9: 264.516 | CY9: 56.7389 | CZ9: 7.29792 | DA9: 0 | DB9: 328.55282 | DC9: 104.61 | DD9: 2418.0141 | DE9: 405.5482 | DF9: 50.70896 | DG9: 1.81 | DH9: 2980.6912 | DJ9: Other Conv Cost | DK9: 0 | DL9: 197.28485 | DM9: 43.65445 | DN9: 4.0544 | DO9: 0 | DP9: 244.9937 | DQ9: 104.61 | DR9: 2615.2989 | DS9: 449.20265 | DT9: 54.76336 | DU9: 1.81 | DV9: 3225.6849 | DX9: Other Conv Cost | DY9: 0 | DZ9: 216.9482 | EA9: 25.1524 | EB9: 4.5612 | EC9: 0 | ED9: 246.6618 | EE9: 104.61 | EF9: 2832.2471 | EG9: 474.35505 | EH9: 59.32456 | EI9: 1.81 | EJ9: 3472.3467 | EL9: Other Conv Cost | EM9: 0 | EN9: 373.04295 | EO9: 31.3453 | EP9: 1.82448 | EQ9: 0 | ER9: 406.21273 | ES9: 104.61 | ET9: 3205.2901 | EU9: 505.70035 | EV9: 61.14904 | EW9: 1.81 | EX9: 3878.5594 | EZ9: Other Conv Cost | FA9: 0 | FB9: 317.093 | FC9: 37.74435 | FD9: 3.64896 | FE9: 0 | FF9: 358.48631 | FG9: 104.61 | FH9: 3522.383 | FI9: 543.4447 | FJ9: 64.798 | FK9: 1.81 | FL9: 4237.0458 | FN9: Other Conv Cost | FO9: 0 | FP9: 238.0644 | FQ9: 36.09165 | FR9: 1.82448 | FS9: 0 | FT9: 275.98053 | FU9: 104.61 | FV9: 3760.4474 | FW9: 579.53635 | FX9: 66.62248 | FY9: 1.81 | FZ9: 4513.0263 | GB9: Other Conv Cost | GC9: 0 | GD9: 240.11125 | GE9: 28.89565 | GF9: 3.64896 | GG9: 0 | GH9: 272.65586 | GI9: 104.61 | GJ9: 4000.5587 | GK9: 608.432 | GL9: 70.27144 | GM9: 1.81 | GN9: 4785.6821 | GP9: Other Conv Cost | GQ9: 0 | GR9: 172.7614 | GS9: 104.37385 | GT9: 10.01111 | GU9: 0 | GV9: 287.14636 | GW9: 104.61 | GX9: 4173.3201 | GY9: 712.80585 | GZ9: 80.28255 | HA9: 1.81 | HB9: 5072.8285 | HD9: Other Conv Cost | HE9: 0 | HF9: 264.71795 | HG9: 62.58564 | HH9: 4.6336 | HI9: 0 | HJ9: 331.93719 | HK9: 104.61 | HL9: 4438.0381 | HM9: 775.39149 | HN9: 84.91615 | HO9: 1.81 | HP9: 5404.7657 | HR9: Other Conv Cost | HS9: 0 | HT9: 185.1612 | HU9: 52.8619 | HV9: 4.38744 | HW9: 0 | HX9: 242.41054 | HY9: 104.61 | HZ9: 4623.1993 | IA9: 828.25339 | IB9: 89.30359 | IC9: 1.81 | ID9: 5647.1762 | IF9: Other Conv Cost | IG9: 0 | IH9: 157.60745 | II9: 49.5733 | IJ9: 4.68428 | IK9: 0 | IL9: 211.86503 | IM9: 104.61 | IN9: 4780.8067 | IO9: 877.82669 | IP9: 93.98787 | IQ9: 1.81 | IR9: 5859.0413 | IT9: Other Conv Cost | IU9: 0 | IV9: 195.5968 | IW9: 17.90189 | IX9: 5.47344 | IY9: 0 | IZ9: 218.97213 | JA9: 104.61 | JB9: 4976.4035 | JC9: 895.72858 | JD9: 99.46131 | JE9: 1.81 | JF9: 6078.0134 | JH9: Other Conv Cost | JI9: 97.88009 | JJ9: 185.1612 | JK9: 39.3519 | JL9: 4.44717 | JM9: 0 | JN9: 326.84036 | JO9: 202.49009 | JP9: 5161.5647 | JQ9: 935.08048 | JR9: 103.90848 | JS9: 1.81 | JT9: 6404.8538 | JV9: Other Conv Cost | JW9: 1.465 | JX9: 208.92585 | JY9: 50.0535 | JZ9: 5.77752 | KA9: 0 | KB9: 266.22187 | KC9: 203.95509 | KD9: 5370.4906 | KE9: 985.13398 | KF9: 109.686 | KG9: 1.81 | KH9: 6671.0756 | KJ9: Other Conv Cost | KK9: 76.714 | KL9: 342.9055 | KM9: 17.22805 | KN9: 3.28877 | KO9: 0 | KP9: 440.13632 | KQ9: 280.66909 | KR9: 5713.3961 | KS9: 1002.362 | KT9: 112.97477 | KU9: 1.81 | KV9: 7111.2119 | KX9: Other Conv Cost | KY9: 0 | KZ9: 240.86046 | LA9: 33.01445 | LB9: 0 | LC9: 0 | LD9: 273.87491 | LE9: 280.66909 | LF9: 5954.2565 | LG9: 1035.3765 | LH9: 112.97477 | LI9: 1.81 | LJ9: 7385.0869 | LK9: =LE9-KY9-KQ9 -> 0 | LL9: =LF9-KZ9-KR9 -> 0 | LM9: =LG9-LA9-KS9 -> 0 | LN9: =LH9-LB9-KT9 -> 0 | LO9: =LI9-LC9-KU9 -> 0 | LP9: =LJ9-LD9-KV9 -> 0
B10: Margin | C10: 0 | D10: 45.5952 | E10: 29.60965 | F10: 18.5843 | G10: 0 | H10: 93.78915 | I10: 0 | J10: 156.0489 | K10: 109.36254 | L10: 31.4279 | M10: 0 | N10: 296.83934 | P10: Margin | Q10: 0 | R10: 45.5952 | S10: 29.60965 | T10: 18.5843 | U10: 0 | V10: 93.78915 | W10: 0 | X10: 156.0489 | Y10: 109.36254 | Z10: 31.4279 | AA10: 0 | AB10: 296.83934 | AD10: Margin | AE10: 0 | AF10: 54.21875 | AG10: 11.04495 | AH10: 34.3254 | AI10: 0 | AJ10: 99.5891 | AK10: 0 | AL10: 210.26765 | AM10: 129.86919 | AN10: 65.7533 | AO10: 0 | AP10: 405.89014 | AR10: Margin | AS10: 0 | AT10: 87.1248 | AU10: -11.79675 | AV10: 14.0112 | AW10: 0 | AX10: 89.33925 | AY10: 0 | AZ10: 297.39245 | BA10: 118.07244 | BB10: 79.7645 | BC10: 0 | BD10: 495.22939 | BF10: Margin | BG10: 730.44 | BH10: 95.46915 | BI10: 46.0166 | BJ10: 16.75688 | BK10: 0 | BL10: 888.68263 | BM10: 730.44 | BN10: 537.8111 | BO10: 162.81515 | BP10: 162.75438 | BQ10: 0 | BR10: 1593.8206 | BT10: Margin | BU10: 0 | BV10: 75.0792 | BW10: 57.21748 | BX10: 18.32432 | BY10: 0 | BZ10: 150.621 | CA10: 730.44 | CB10: 612.8903 | CC10: 220.03263 | CD10: 181.0787 | CE10: 0 | CF10: 1744.4416 | CH10: Margin | CI10: 0 | CJ10: 60.8905 | CK10: 52.87275 | CL10: 30.1106 | CM10: -25.13472 | CN10: =SUM(CI10:CM10) -> 118.73913 | CO10: 730.44 | CP10: 673.7808 | CQ10: 272.90538 | CR10: 211.1893 | CS10: -25.13472 | CT10: 1863.1808 | CV10: Margin | CW10: 0 | CX10: 68.9808 | CY10: 104.408 | CZ10: 37.08432 | DA10: 0 | DB10: 210.47312 | DC10: 730.44 | DD10: 742.7616 | DE10: 377.31338 | DF10: 248.27362 | DG10: -25.13472 | DH10: 2073.6539 | DJ10: Margin | DK10: 0 | DL10: 53.4247 | DM10: -53.9021 | DN10: 26.64368 | DO10: 0 | DP10: 26.16628 | DQ10: 730.44 | DR10: 796.1863 | DS10: 323.41128 | DT10: 274.9173 | DU10: -25.13472 | DV10: 2099.8202 | DX10: Margin | DY10: 0 | DZ10: 84.68985 | EA10: -3.86575 | EB10: 31.10688 | EC10: 0 | ED10: 111.93098 | EE10: 730.44 | EF10: 880.87615 | EG10: 319.54553 | EH10: 306.02418 | EI10: -25.13472 | EJ10: 2211.7511 | EL10: Margin | EM10: 0 | EN10: 102.00785 | EO10: -22.59635 | EP10: 16.06752 | EQ10: 0 | ER10: 95.47902 | ES10: 730.44 | ET10: 982.884 | EU10: 296.94918 | EV10: 322.0917 | EW10: -25.13472 | EX10: 2307.2302 | EZ10: Margin | FA10: 0 | FB10: 66.934 | FC10: 27.8355 | FD10: 23.07312 | FE10: 0 | FF10: 117.84262 | FG10: 730.44 | FH10: 1049.818 | FI10: 324.78468 | FJ10: 345.16482 | FK10: -25.13472 | FL10: 2425.0728 | FN10: Margin | FO10: 0 | FP10: 63.6552 | FQ10: -27.8992 | FR10: 16.06752 | FS10: 0 | FT10: 51.82352 | FU10: 730.44 | FV10: 1113.4732 | FW10: 296.88548 | FX10: 361.23234 | FY10: -25.13472 | FZ10: 2476.8963 | GB10: Margin | GC10: 0 | GD10: 65.8344 | GE10: -22.36255 | GF10: 32.13504 | GG10: 0 | GH10: 75.60689 | GI10: 730.44 | GJ10: 1179.3076 | GK10: 274.52293 | GL10: 393.36738 | GM10: -25.13472 | GN10: 2552.5032 | GP10: Margin | GQ10: 0 | GR10: 53.2476 | GS10: -110.4579 | GT10: 53.10274 | GU10: 0 | GV10: -4.10756 | GW10: 730.44 | GX10: 1232.5552 | GY10: 164.06503 | GZ10: 446.47012 | HA10: -25.13472 | HB10: 2548.3956 | HD10: Margin | HE10: 0 | HF10: 62.38575 | HG10: 8.04752 | HH10: 32.51762 | HI10: 0 | HJ10: 102.95089 | HK10: 730.44 | HL10: 1294.9409 | HM10: 172.11255 | HN10: 478.98774 | HO10: -25.13472 | HP10: 2651.3465 | HR10: Margin | HS10: 0 | HT10: 49.728 | HU10: 18.86045 | HV10: 15.92592 | HW10: 0 | HX10: 84.51437 | HY10: 730.44 | HZ10: 1344.6689 | IA10: 190.973 | IB10: 494.91366 | IC10: -25.13472 | ID10: 2735.8609 | IF10: Margin | IG10: 0 | IH10: 43.80355 | II10: 19.38195 | IJ10: 12.05992 | IK10: 0 | IL10: 75.24542 | IM10: 730.44 | IN10: 1388.4725 | IO10: 210.35495 | IP10: 506.97358 | IQ10: -25.13472 | IR10: 2811.1063 | IT10: Margin | IU10: 0 | IV10: 55.06725 | IW10: -1.26843 | IX10: 32.03424 | IY10: 0 | IZ10: 85.83306 | JA10: 730.44 | JB10: 1443.5397 | JC10: 209.08652 | JD10: 539.00782 | JE10: -25.13472 | JF10: 2896.9394 | JH10: Margin | JI10: 458.88836 | JJ10: 50.064 | JK10: -63.74095 | JL10: 22.41862 | JM10: 0 | JN10: 467.63003 | JO10: 1189.3284 | JP10: 1493.6037 | JQ10: 145.34557 | JR10: 561.42644 | JS10: -25.13472 | JT10: 3364.5694 | JV10: Margin | JW10: 8.276 | JX10: 61.54855 | JY10: 7.95165 | JZ10: 10.45968 | KA10: 0 | KB10: 88.23588 | KC10: 1197.6044 | KD10: 1555.1523 | KE10: 153.29722 | KF10: 571.88612 | KG10: -25.13472 | KH10: 3452.8053 | KJ10: Margin | KK10: 359.656 | KL10: 103.2983 | KM10: 9.56865 | KN10: 15.44126 | KO10: 0 | KP10: 487.96421 | KQ10: 1557.2604 | KR10: 1658.4506 | KS10: 162.86587 | KT10: 587.32738 | KU10: -25.13472 | KV10: 3940.7695 | KX10: Margin | KY10: 0 | KZ10: 43.66211 | LA10: 38.99455 | LB10: 0 | LC10: 0 | LD10: 82.65666 | LE10: 1557.2604 | LF10: 1702.1127 | LG10: 201.86042 | LH10: 587.32738 | LI10: -25.13472 | LJ10: 4023.4261 | LK10: =LE10-KY10-KQ10 -> 0 | LL10: =LF10-KZ10-KR10 -> 5.0022209e-12 | LM10: =LG10-LA10-KS10 -> -4.5474735e-12 | LN10: =LH10-LB10-KT10 -> 0 | LO10: =LI10-LC10-KU10 -> 0 | LP10: =LJ10-LD10-KV10 -> 0
B11: Margin % | D11: 0.017018662 | E11: 0.07176079 | F11: 0.044922759 | H11: 0.026755314 | J11: 0.024580951 | K11: 0.081397343 | L11: 0.044922759 | N11: 0.035373686 | P11: Margin % | R11: 0.017018662 | S11: 0.07176079 | T11: 0.044922759 | V11: 0.026755314 | X11: 0.024580951 | Y11: 0.081397343 | Z11: 0.044922759 | AB11: 0.035373686 | AD11: Margin % | AF11: 0.023638518 | AG11: 0.034441135 | AH11: 0.059155296 | AJ11: 0.031174094 | AL11: 0.024330822 | AM11: 0.078034446 | AN11: 0.051375476 | AP11: 0.035032385 | AR11: Margin % | AT11: 0.033299088 | AU11: -0.024153499 | AV11: 0.044922759 | AX11: 0.026147551 | AZ11: 0.02641502 | BA11: 0.054849499 | BB11: 0.050111101 | BD11: 0.033008965 | BF11: Margin % | BG11: 0.32933411 | BH11: 0.028624207 | BI11: 0.060389568 | BJ11: 0.053135138 | BL11: 0.13402852 | BM11: 0.32933411 | BN11: 0.026550364 | BO11: 0.039938085 | BP11: 0.051998207 | BR11: 0.053698565 | BT11: Margin % | BV11: 0.036054861 | BW11: 0.21556125 | BX11: 0.057008856 | BZ11: 0.056428754 | CA11: 0.32933411 | CB11: 0.027436354 | CC11: 0.050673965 | CD11: 0.052464846 | CF11: 0.053923834 | CH11: Margin % | CJ11: 0.023113963 | CK11: 0.078776229 | CL11: 0.057712666 | CM11: -0.17503287 | CN11: 0.037591775 | CO11: 0.32933411 | CP11: 0.026980392 | CQ11: 0.054436273 | CR11: 0.05315396 | CS11: -0.17503287 | CT11: 0.052196036 | CV11: Margin % | CX11: 0.022908856 | CY11: 0.13087379 | CZ11: 0.054755987 | DB11: 0.046916317 | DC11: 0.32933411 | DD11: 0.026542293 | DE11: 0.064930031 | DF11: 0.053387271 | DG11: -0.17503287 | DH11: 0.050815992 | DJ11: Margin % | DL11: 0.023892483 | DM11: -0.20278276 | DN11: 0.06468357 | DP11: 0.0089802256 | DQ11: 0.32933411 | DR11: 0.026346228 | DS11: 0.05321988 | DT11: 0.054306419 | DU11: -0.17503287 | DV11: 0.048027858 | DX11: Margin % | DZ11: 0.032709127 | EA11: -0.014320815 | EB11: 0.066173475 | ED11: 0.033620973 | EE11: 0.32933411 | EF11: 0.026848363 | EG11: 0.050347282 | EH11: 0.055314744 | EI11: -0.17503287 | EJ11: 0.047008446 | EL11: Margin % | EN11: 0.023973917 | EO11: -0.088243535 | EP11: 0.076723142 | ER11: 0.020226714 | ES11: 0.32933411 | ET11: 0.026518379 | EU11: 0.044972567 | EV11: 0.056095573 | EW11: -0.17503287 | EX11: 0.044566485 | EZ11: Margin % | FB11: 0.018894485 | FC11: 0.050782555 | FD11: 0.063150054 | FF11: 0.026445735 | FG11: 0.32933411 | FH11: 0.025853274 | FI11: 0.045417907 | FJ11: 0.056517614 | FK11: -0.17503287 | FL11: 0.043130395 | FN11: Margin % | FP11: 0.023556401 | FQ11: -0.093277976 | FR11: 0.076723142 | FT11: 0.016140548 | FU11: 0.32933411 | FV11: 0.025709961 | FW11: 0.039849734 | FX11: 0.05718751 | FY11: -0.17503287 | FZ11: 0.041672421 | GB11: Margin % | GD11: 0.024210816 | GE11: -0.097285157 | GF11: 0.076723142 | GH11: 0.022449104 | GI11: 0.32933411 | GJ11: 0.025621396 | GK11: 0.035745218 | GL11: 0.058402329 | GM11: -0.17503287 | GN11: 0.040641572 | GP11: Margin % | GR11: 0.026890098 | GS11: -0.15684659 | GT11: 0.055798318 | GV11: -0.0011296528 | GW11: 0.32933411 | GX11: 0.025673726 | GY11: 0.019568283 | GZ11: 0.058079946 | HA11: -0.17503287 | HB11: 0.038355565 | HD11: Margin % | HF11: 0.020872054 | HG11: 0.010876158 | HH11: 0.067330747 | HJ11: 0.024443225 | HK11: 0.32933411 | HL11: 0.0253923 | HM11: 0.018863396 | HN11: 0.058626781 | HO11: -0.17503287 | HP11: 0.037526211 | HR11: Margin % | HT11: 0.023672425 | HU11: 0.027886409 | HV11: 0.040127158 | HX11: 0.026628012 | HY11: 0.32933411 | HZ11: 0.025324258 | IA11: 0.019486074 | IB11: 0.057769743 | IC11: -0.17503287 | ID11: 0.037057688 | IF11: Margin % | IH11: 0.024573108 | II11: 0.029726329 | IJ11: 0.030111447 | IL11: 0.026540628 | IM11: 0.32933411 | IN11: 0.02529986 | IO11: 0.020124847 | IP11: 0.056534461 | IQ11: -0.17503287 | IR11: 0.036668748 | IT11: Margin % | IV11: 0.024602122 | IW11: -0.0061309368 | IX11: 0.058002227 | IZ11: 0.028634917 | JA11: 0.32933411 | JB11: 0.025272518 | JC11: 0.019615244 | JD11: 0.056619614 | JE11: -0.17503287 | JF11: 0.036366445 | JH11: Margin % | JI11: 0.2479562 | JJ11: 0.023832374 | JK11: -0.35191351 | JL11: 0.05239889 | JN11: 0.10254309 | JO11: 0.29231788 | JP11: 0.025221432 | JQ11: 0.013407625 | JR11: 0.056438082 | JS11: -0.17503287 | JT11: 0.039949764 | JV11: Margin % | JW11: 0.25105415 | JX11: 0.025823034 | JY11: 0.01286393 | JZ11: 0.02210239 | KB11: 0.025154103 | KC11: 0.29198623 | KD11: 0.025244708 | KE11: 0.013378295 | KF11: 0.054878816 | KG11: -0.17503287 | KH11: 0.039358157 | KJ11: Margin % | KK11: 0.2479562 | KL11: 0.026367239 | KM11: 0.04020524 | KN11: 0.049181781 | KP11: 0.08242477 | KQ11: 0.28048334 | KR11: 0.025311828 | KS11: 0.013924151 | KT11: 0.054712195 | KU11: -0.17503287 | KV11: 0.042080687 | KX11: Margin % | KZ11: 0.016657461 | LA11: 0.071559691 | LD11: 0.026106793 | LE11: 0.28048334 | LF11: 0.024978926 | LG11: 0.016489749 | LH11: 0.054712195 | LI11: -0.17503287 | LJ11: 0.041558295
B12: Rent & White Collar employees Salary doesn't form part of Other Conversion Cost | P12: Rent & White Collar employees Salary doesn't form part of Other Conversion Cost | AD12: Rent & White Collar employees Salary doesn't form part of Other Conversion Cost | AR12: Rent & White Collar employees Salary doesn't form part of Other Conversion Cost | BF12: Rent & White Collar employees Salary doesn't form part of Other Conversion Cost | BT12: Rent & White Collar employees Salary doesn't form part of Other Conversion Cost | CH12: Rent & White Collar employees Salary doesn't form part of Other Conversion Cost | CV12: Rent & White Collar employees Salary doesn't form part of Other Conversion Cost | DJ12: Rent & White Collar employees Salary doesn't form part of Other Conversion Cost | DX12: Rent & White Collar employees Salary doesn't form part of Other Conversion Cost | EL12: Rent & White Collar employees Salary doesn't form part of Other Conversion Cost | EZ12: Rent & White Collar employees Salary doesn't form part of Other Conversion Cost | FN12: Rent & White Collar employees Salary doesn't form part of Other Conversion Cost | GB12: Rent & White Collar employees Salary doesn't form part of Other Conversion Cost | GP12: Rent & White Collar employees Salary doesn't form part of Other Conversion Cost | HD12: Rent & White Collar employees Salary doesn't form part of Other Conversion Cost | HR12: Rent & White Collar employees Salary doesn't form part of Other Conversion Cost | IF12: Rent & White Collar employees Salary doesn't form part of Other Conversion Cost | IT12: Rent & White Collar employees Salary doesn't form part of Other Conversion Cost | JH12: Rent & White Collar employees Salary doesn't form part of Other Conversion Cost | JV12: Rent & White Collar employees Salary doesn't form part of Other Conversion Cost | KJ12: Rent & White Collar employees Salary doesn't form part of Other Conversion Cost | KX12: Rent & White Collar employees Salary doesn't form part of Other Conversion Cost
BF14: Qty (In Units) | BG14: =BG5*1000/BG$4 -> 739.31 | BH14: =BH5*1000/BH$4 -> 367.9271 | BI14: =BI5*1000/BI$4 -> 725.71033 | BJ14: =BJ5*1000/BJ$4 -> 165.63206 | BK14: =BK5*1000/BK$4 -> #DIV/0! | BM14: =BM5*1000/BM$4 -> 739.31 | BN14: =BN5*1000/BN$4 -> 369.47124 | BO14: =BO5*1000/BO$4 -> 896.17255 | BP14: =BP5*1000/BP$4 -> 164.02892 | BQ14: =BQ5*1000/BQ$4 -> #DIV/0! | BT14: Qty (In Units) | BU14: =BU5*1000/BU$4 -> #DIV/0! | BV14: =BV5*1000/BV$4 -> 396.64 | BW14: =BW5*1000/BW$4 -> 1096.8384 | BX14: =BX5*1000/BX$4 -> 171.33761 | BY14: =BY5*1000/BY$4 -> #DIV/0! | CA14: =CA5*1000/CA$4 -> 739.31 | CB14: =CB5*1000/CB$4 -> 371.84554 | CC14: =CC5*1000/CC$4 -> 919.74663 | CD14: =CD5*1000/CD$4 -> 164.68314 | CE14: =CE5*1000/CE$4 -> #DIV/0! | CH14: Qty (In Units) | CI14: =CI4 -> 0 | CJ14: =CJ4 -> 7355 | CK14: =CK4 -> 735 | CL14: =CL4 -> 3026 | CM14: =CM4 -> 200 | CO14: =CO4 -> 3000 | CP14: =CP4 -> 67430 | CQ14: =CQ4 -> 5456 | CR14: =CR4 -> 23984 | CS14: =CS4 -> 200 | CV14: Qty (In Units) | CW14: =CW4 -> 0 | CX14: =CX4 -> 8400 | CY14: =CY4 -> 700 | CZ14: =CZ4 -> 4032 | DA14: =DA4 -> 0 | DC14: =DC4 -> 3000 | DD14: =DD4 -> 75830 | DE14: =DE4 -> 6156 | DF14: =DF4 -> 28016 | DG14: =DG4 -> 200 | DJ14: Qty (In Units) | DK14: =DK4 -> 0 | DL14: =DL4 -> 6265 | DM14: =DM4 -> 140 | DN14: =DN4 -> 2240 | DO14: =DO4 -> 0 | DQ14: =DQ4 -> 3000 | DR14: =DR4 -> 82095 | DS14: =DS4 -> 6296 | DT14: =DT4 -> 30256 | DU14: =DU4 -> 200 | DX14: Qty (In Units) | DY14: =DY4 -> 0 | DZ14: =DZ4 -> 6755 | EA14: =EA4 -> 245 | EB14: =EB4 -> 2520 | EC14: =EC4 -> 0 | EE14: =EE4 -> 3000 | EF14: =EF4 -> 88850 | EG14: =EG4 -> 6541 | EH14: =EH4 -> 32776 | EI14: =EI4 -> 200 | EL14: Qty (In Units) | EM14: =EM4 -> 0 | EN14: =EN4 -> 11830 | EO14: =EO4 -> 385 | EP14: =EP4 -> 1008 | EQ14: =EQ4 -> 0 | ES14: =ES4 -> 3000 | ET14: =ET4 -> 100680 | EU14: =EU4 -> 6926 | EV14: =EV4 -> 33784 | EW14: =EW4 -> 200 | EZ14: Qty (In Units) | FA14: =FA4 -> 0 | FB14: =FB4 -> 9940 | FC14: =FC4 -> 770 | FD14: =FD4 -> 2016 | FE14: =FE4 -> 0 | FG14: =FG4 -> 3000 | FH14: =FH4 -> 110620 | FI14: =FI4 -> 7696 | FJ14: =FJ4 -> 35800 | FK14: =FK4 -> 200 | FN14: Qty (In Units) | FO14: =FO4 -> 0 | FP14: =FP4 -> 7560 | FQ14: =FQ4 -> 280 | FR14: =FR4 -> 1008 | FS14: =FS4 -> 0 | FU14: =FU4 -> 3000 | FV14: =FV4 -> 118180 | FW14: =FW4 -> 7976 | FX14: =FX4 -> 36808 | FY14: =FY4 -> 200 | GB14: Qty (In Units) | GC14: =GC4 -> 0 | GD14: =GD4 -> 7625 | GE14: =GE4 -> 245 | GF14: =GF4 -> 2016 | GG14: =GG4 -> 0 | GI14: =GI4 -> 3000 | GJ14: =GJ4 -> 125805 | GK14: =GK4 -> 8221 | GL14: =GL4 -> 38824 | GM14: =GM4 -> 200 | GP14: Qty (In Units) | GQ14: =GQ4 -> 0 | GR14: =GR4 -> 5460 | GS14: =GS4 -> 1190 | GT14: =GT4 -> 5531 | GU14: =GU4 -> 0 | GW14: =GW4 -> 3000 | GX14: =GX4 -> 131265 | GY14: =GY4 -> 9411 | GZ14: =GZ4 -> 44355 | HA14: =HA4 -> 200 | HD14: Qty (In Units) | HE14: =HE4 -> 0 | HF14: =HF4 -> 8365 | HG14: =HG4 -> 1254 | HH14: =HH4 -> 2560 | HI14: =HI4 -> 0 | HK14: =HK4 -> 3000 | HL14: =HL4 -> 139630 | HM14: =HM4 -> 10665 | HN14: =HN4 -> 46915 | HO14: =HO4 -> 200 | HR14: Qty (In Units) | HS14: =HS4 -> 0 | HT14: =HT4 -> 5880 | HU14: =HU4 -> 1085 | HV14: =HV4 -> 2424 | HW14: =HW4 -> 0 | HY14: =HY4 -> 3000 | HZ14: =HZ4 -> 145510 | IA14: =IA4 -> 11750 | IB14: =IB4 -> 49339 | IC14: =IC4 -> 200 | IF14: Qty (In Units) | IG14: =IG4 -> 0 | IH14: =IH4 -> 5005 | II14: =II4 -> 875 | IJ14: =IJ4 -> 2588 | IK14: =IK4 -> 0 | IM14: =IM4 -> 3000 | IN14: =IN4 -> 150515 | IO14: =IO4 -> 12625 | IP14: =IP4 -> 51927 | IQ14: =IQ4 -> 200 | IT14: Qty (In Units) | IU14: =IU4 -> 0 | IV14: =IV4 -> 6195 | IW14: =IW4 -> 239 | IX14: =IX4 -> 3024 | IY14: =IY4 -> 0 | JA14: =JA4 -> 3000 | JB14: =JB4 -> 156710 | JC14: =JC4 -> 12864 | JD14: =JD4 -> 54951 | JE14: =JE4 -> 200 | JH14: Qty (In Units) | JI14: =JI4 -> 2807 | JJ14: =JJ4 -> 5880 | JK14: =JK4 -> 175 | JL14: =JL4 -> 2457 | JM14: =JM4 -> 0 | JO14: =JO4 -> 5807 | JP14: =JP4 -> 162590 | JQ14: =JQ4 -> 13039 | JR14: =JR4 -> 57408 | JS14: =JS4 -> 200 | JV14: Qty (In Units) | JW14: =JW4 -> 50 | JX14: =JX4 -> 6615 | JY14: =JY4 -> 595 | JZ14: =JZ4 -> 3192 | KA14: =KA4 -> 0 | KC14: =KC4 -> 5857 | KD14: =KD4 -> 169205 | KE14: =KE4 -> 13634 | KF14: =KF4 -> 60600 | KG14: =KG4 -> 200 | KJ14: Qty (In Units) | KK14: =KK4 -> 2200 | KL14: =KL4 -> 10850 | KM14: =KM4 -> 245 | KN14: =KN4 -> 1817 | KO14: =KO4 -> 0 | KQ14: =KQ4 -> 8057 | KR14: =KR4 -> 180055 | KS14: =KS4 -> 13879 | KT14: =KT4 -> 62417 | KU14: =KU4 -> 200 | KX14: Qty (In Units) | KY14: =KY4 -> 0 | KZ14: =KZ4 -> 7766 | LA14: =LA4 -> 595 | LB14: =LB4 -> 0 | LC14: =LC4 -> 0 | LE14: =LE4 -> 8057 | LF14: =LF4 -> 187821 | LG14: =LG4 -> 14474 | LH14: =LH4 -> 62417 | LI14: =LI4 -> 200
BF15: Sales | BG15: =BG6*1000/BG$4 -> 495.83 | BH15: =BH6*1000/BH$4 -> 357.39548 | BI15: =BI6*1000/BI$4 -> 681.885 | BJ15: =BJ6*1000/BJ$4 -> 156.83118 | BK15: =BK6*1000/BK$4 -> #DIV/0! | BM15: =BM6*1000/BM$4 -> 495.83 | BN15: =BN6*1000/BN$4 -> 359.66164 | BO15: =BO6*1000/BO$4 -> 860.38113 | BP15: =BP6*1000/BP$4 -> 155.49971 | BQ15: =BQ6*1000/BQ$4 -> #DIV/0! | BT15: Sales | BU15: =BU6*1000/BU$4 -> #DIV/0! | BV15: =BV6*1000/BV$4 -> 382.3392 | BW15: =BW6*1000/BW$4 -> 860.40256 | BX15: =BX6*1000/BX$4 -> 161.56985 | BY15: =BY6*1000/BY$4 -> #DIV/0! | CA15: =CA6*1000/CA$4 -> 495.83 | CB15: =CB6*1000/CB$4 -> 361.64345 | CC15: =CC6*1000/CC$4 -> 873.13942 | CD15: =CD6*1000/CD$4 -> 156.04306 | CE15: =CE6*1000/CE$4 -> #DIV/0! | CH15: Sales | CI15: =CI5*1000/CI$4 -> #DIV/0! | CJ15: =CJ5*1000/CJ$4 -> 358.17267 | CK15: =CK5*1000/CK$4 -> 913.16524 | CL15: =CL5*1000/CL$4 -> 172.41671 | CM15: =CM5*1000/CM$4 -> 718 | CO15: =CO5*1000/CO$4 -> 739.31 | CP15: =CP5*1000/CP$4 -> 370.35415 | CQ15: =CQ5*1000/CQ$4 -> 918.86002 | CR15: =CR5*1000/CR$4 -> 165.65886 | CS15: =CS5*1000/CS$4 -> 718 | CV15: Sales | CW15: =CW5*1000/CW$4 -> #DIV/0! | CX15: =CX5*1000/CX$4 -> 358.464 | CY15: =CY5*1000/CY$4 -> 1139.6804 | CZ15: =CZ5*1000/CZ$4 -> 167.9725 | DA15: =DA5*1000/DA$4 -> #DIV/0! | DC15: =DC5*1000/DC$4 -> 739.31 | DD15: =DD5*1000/DD$4 -> 369.03703 | DE15: =DE5*1000/DE$4 -> 943.96955 | DF15: =DF5*1000/DF$4 -> 165.99184 | DG15: =DG5*1000/DG$4 -> 718 | DJ15: Sales | DK15: =DK5*1000/DK$4 -> #DIV/0! | DL15: =DL5*1000/DL$4 -> 356.91084 | DM15: =DM5*1000/DM$4 -> 1898.6575 | DN15: =DN5*1000/DN$4 -> 183.8875 | DO15: =DO5*1000/DO$4 -> #DIV/0! | DQ15: =DQ5*1000/DQ$4 -> 739.31 | DR15: =DR5*1000/DR$4 -> 368.11163 | DS15: =DS5*1000/DS$4 -> 965.19831 | DT15: =DT5*1000/DT$4 -> 167.31674 | DU15: =DU5*1000/DU$4 -> 718 | DX15: Sales | DY15: =DY5*1000/DY$4 -> #DIV/0! | DZ15: =DZ5*1000/DZ$4 -> 383.29845 | EA15: =EA5*1000/EA$4 -> 1101.7929 | EB15: =EB5*1000/EB$4 -> 186.54 | EC15: =EC5*1000/EC$4 -> #DIV/0! | EE15: =EE5*1000/EE$4 -> 739.31 | EF15: =EF5*1000/EF$4 -> 369.26624 | EG15: =EG5*1000/EG$4 -> 970.3146 | EH15: =EH5*1000/EH$4 -> 168.79473 | EI15: =EI5*1000/EI$4 -> 718 | EL15: Sales | EM15: =EM5*1000/EM$4 -> #DIV/0! | EN15: =EN5*1000/EN$4 -> 359.67467 | EO15: =EO5*1000/EO$4 -> 665.11182 | EP15: =EP5*1000/EP$4 -> 207.76 | EQ15: =EQ5*1000/EQ$4 -> #DIV/0! | ES15: =ES5*1000/ES$4 -> 739.31 | ET15: =ET5*1000/ET$4 -> 368.13922 | EU15: =EU5*1000/EU$4 -> 953.3491 | EV15: =EV5*1000/EV$4 -> 169.95732 | EW15: =EW5*1000/EW$4 -> 718 | EZ15: Sales | FA15: =FA5*1000/FA$4 -> #DIV/0! | FB15: =FB5*1000/FB$4 -> 356.38986 | FC15: =FC5*1000/FC$4 -> 711.85864 | FD15: =FD5*1000/FD$4 -> 181.235 | FE15: =FE5*1000/FE$4 -> #DIV/0! | FG15: =FG5*1000/FG$4 -> 739.31 | FH15: =FH5*1000/FH$4 -> 367.08346 | FI15: =FI5*1000/FI$4 -> 929.1875 | FJ15: =FJ5*1000/FJ$4 -> 170.5924 | FK15: =FK5*1000/FK$4 -> 718 | FN15: Sales | FO15: =FO5*1000/FO$4 -> #DIV/0! | FP15: =FP5*1000/FP$4 -> 357.44 | FQ15: =FQ5*1000/FQ$4 -> 1068.205 | FR15: =FR5*1000/FR$4 -> 207.76 | FS15: =FS5*1000/FS$4 -> #DIV/0! | FU15: =FU5*1000/FU$4 -> 739.31 | FV15: =FV5*1000/FV$4 -> 366.46656 | FW15: =FW5*1000/FW$4 -> 934.06776 | FX15: =FX5*1000/FX$4 -> 171.61025 | FY15: =FY5*1000/FY$4 -> 718 | GB15: Sales | GC15: =GC5*1000/GC$4 -> #DIV/0! | GD15: =GD5*1000/GD$4 -> 356.61828 | GE15: =GE5*1000/GE$4 -> 938.22857 | GF15: =GF5*1000/GF$4 -> 207.76 | GG15: =GG5*1000/GG$4 -> #DIV/0! | GI15: =GI5*1000/GI$4 -> 739.31 | GJ15: =GJ5*1000/GJ$4 -> 365.86966 | GK15: =GK5*1000/GK$4 -> 934.19176 | GL15: =GL5*1000/GL$4 -> 173.48738 | GM15: =GM5*1000/GM$4 -> 718 | GP15: Sales | GQ15: =GQ5*1000/GQ$4 -> #DIV/0! | GR15: =GR5*1000/GR$4 -> 362.67282 | GS15: =GS5*1000/GS$4 -> 591.79971 | GT15: =GT5*1000/GT$4 -> 172.06485 | GU15: =GU5*1000/GU$4 -> #DIV/0! | GW15: =GW5*1000/GW$4 -> 739.31 | GX15: =GX5*1000/GX$4 -> 365.73669 | GY15: =GY5*1000/GY$4 -> 890.89704 | GZ15: =GZ5*1000/GZ$4 -> 173.31 | HA15: =HA5*1000/HA$4 -> 718 | HD15: Sales | HE15: =HE5*1000/HE$4 -> #DIV/0! | HF15: =HF5*1000/HF$4 -> 357.31749 | HG15: =HG5*1000/HG$4 -> 590.05029 | HH15: =HH5*1000/HH$4 -> 188.65371 | HI15: =HI5*1000/HI$4 -> #DIV/0! | HK15: =HK5*1000/HK$4 -> 739.31 | HL15: =HL5*1000/HL$4 -> 365.23231 | HM15: =HM5*1000/HM$4 -> 855.52322 | HN15: =HN5*1000/HN$4 -> 174.14725 | HO15: =HO5*1000/HO$4 -> 718 | HR15: Sales | HS15: =HS5*1000/HS$4 -> #DIV/0! | HT15: =HT5*1000/HT$4 -> 357.25714 | HU15: =HU5*1000/HU$4 -> 623.34677 | HV15: =HV5*1000/HV$4 -> 163.73198 | HW15: =HW5*1000/HW$4 -> #DIV/0! | HY15: =HY5*1000/HY$4 -> 739.31 | HZ15: =HZ5*1000/HZ$4 -> 364.91004 | IA15: =IA5*1000/IA$4 -> 834.08395 | IB15: =IB5*1000/IB$4 -> 173.63556 | IC15: =IC5*1000/IC$4 -> 718 | IF15: Sales | IG15: =IG5*1000/IG$4 -> #DIV/0! | IH15: =IH5*1000/IH$4 -> 356.16 | II15: =II5*1000/II$4 -> 745.1576 | IJ15: =IJ5*1000/IJ$4 -> 154.75637 | IK15: =IK5*1000/IK$4 -> #DIV/0! | IM15: =IM5*1000/IM$4 -> 739.31 | IN15: =IN5*1000/IN$4 -> 364.61908 | IO15: =IO5*1000/IO$4 -> 827.92074 | IP15: =IP5*1000/IP$4 -> 172.69463 | IQ15: =IQ5*1000/IQ$4 -> 718 | IT15: Sales | IU15: =IU5*1000/IU$4 -> #DIV/0! | IV15: =IV5*1000/IV$4 -> 361.3096 | IW15: =IW5*1000/IW$4 -> 865.64887 | IX15: =IX5*1000/IX$4 -> 182.63667 | IY15: =IY5*1000/IY$4 -> #DIV/0! | JA15: =JA5*1000/JA$4 -> 739.31 | JB15: =JB5*1000/JB$4 -> 364.48825 | JC15: =JC5*1000/JC$4 -> 828.62169 | JD15: =JD5*1000/JD$4 -> 173.24175 | JE15: =JE5*1000/JE$4 -> 718 | JH15: Sales | JI15: =JI5*1000/JI$4 -> 659.31 | JJ15: =JJ5*1000/JJ$4 -> 357.25714 | JK15: =JK5*1000/JK$4 -> 1035.01 | JL15: =JL5*1000/JL$4 -> 174.13322 | JM15: =JM5*1000/JM$4 -> #DIV/0! | JO15: =JO5*1000/JO$4 -> 700.63943 | JP15: =JP5*1000/JP$4 -> 364.22674 | JQ15: =JQ5*1000/JQ$4 -> 831.39168 | JR15: =JR5*1000/JR$4 -> 173.2799 | JS15: =JS5*1000/JS$4 -> 718 | JV15: Sales | JW15: =JW5*1000/JW$4 -> 659.3 | JX15: =JX5*1000/JX$4 -> 360.31365 | JY15: =JY5*1000/JY$4 -> 1038.8829 | JZ15: =JZ5*1000/JZ$4 -> 148.25737 | KA15: =KA5*1000/KA$4 -> #DIV/0! | KC15: =KC5*1000/KC$4 -> 700.28652 | KD15: =KD5*1000/KD$4 -> 364.07376 | KE15: =KE5*1000/KE$4 -> 840.44678 | KF15: =KF5*1000/KF$4 -> 171.96189 | KG15: =KG5*1000/KG$4 -> 718 | KJ15: Sales | KK15: =KK5*1000/KK$4 -> 659.31 | KL15: =KL5*1000/KL$4 -> 361.07613 | KM15: =KM5*1000/KM$4 -> 971.40857 | KN15: =KN5*1000/KN$4 -> 172.79197 | KO15: =KO5*1000/KO$4 -> #DIV/0! | KQ15: =KQ5*1000/KQ$4 -> 689.0977 | KR15: =KR5*1000/KR$4 -> 363.89312 | KS15: =KS5*1000/KS$4 -> 842.7586 | KT15: =KT5*1000/KT$4 -> 171.98605 | KU15: =KU5*1000/KU$4 -> 718 | KX15: Sales | KY15: =KY5*1000/KY$4 -> #DIV/0! | KZ15: =KZ5*1000/KZ$4 -> 337.51924 | LA15: =LA5*1000/LA$4 -> 915.83765 | LB15: =LB5*1000/LB$4 -> #DIV/0! | LC15: =LC5*1000/LC$4 -> #DIV/0! | LE15: =LE5*1000/LE$4 -> 689.0977 | LF15: =LF5*1000/LF$4 -> 362.80262 | LG15: =LG5*1000/LG$4 -> 845.76274 | LH15: =LH5*1000/LH$4 -> 171.98605 | LI15: =LI5*1000/LI$4 -> 718
BF16: COGS | BG16: =BG7*1000/BG$4 -> 421.61 | BH16: =BH7*1000/BH$4 -> 292.69649 | BI16: =BI7*1000/BI$4 -> 570.23167 | BJ16: =BJ7*1000/BJ$4 -> 150.42118 | BK16: =BK7*1000/BK$4 -> #DIV/0! | BM16: =BM7*1000/BM$4 -> 421.61 | BN16: =BN7*1000/BN$4 -> 294.40522 | BO16: =BO7*1000/BO$4 -> 700.27675 | BP16: =BP7*1000/BP$4 -> 149.08971 | BQ16: =BQ7*1000/BQ$4 -> #DIV/0! | BT16: COGS | BU16: =BU7*1000/BU$4 -> #DIV/0! | BV16: =BV7*1000/BV$4 -> 315.4172 | BW16: =BW7*1000/BW$4 -> 720.90198 | BX16: =BX7*1000/BX$4 -> 155.15985 | BY16: =BY7*1000/BY$4 -> #DIV/0! | CA16: =CA7*1000/CA$4 -> 421.61 | CB16: =CB7*1000/CB$4 -> 296.24148 | CC16: =CC7*1000/CC$4 -> 711.71727 | CD16: =CD7*1000/CD$4 -> 149.63306 | CE16: =CE7*1000/CE$4 -> #DIV/0! | CH16: COGS | CI16: =CI6*1000/CI$4 -> #DIV/0! | CJ16: =CJ6*1000/CJ$4 -> 349.89388 | CK16: =CK6*1000/CK$4 -> 841.22952 | CL16: =CL6*1000/CL$4 -> 162.46608 | CM16: =CM6*1000/CM$4 -> 843.6736 | CO16: =CO6*1000/CO$4 -> 495.83 | CP16: =CP6*1000/CP$4 -> 360.36185 | CQ16: =CQ6*1000/CQ$4 -> 868.84071 | CR16: =CR6*1000/CR$4 -> 156.85344 | CS16: =CS6*1000/CS$4 -> 843.6736 | CV16: COGS | CW16: =CW6*1000/CW$4 -> #DIV/0! | CX16: =CX6*1000/CX$4 -> 350.252 | CY16: =CY6*1000/CY$4 -> 990.52607 | CZ16: =CZ6*1000/CZ$4 -> 158.775 | DA16: =DA6*1000/DA$4 -> #DIV/0! | DC16: =DC6*1000/DC$4 -> 495.83 | DD16: =DD6*1000/DD$4 -> 359.24194 | DE16: =DE6*1000/DE$4 -> 882.67757 | DF16: =DF6*1000/DF$4 -> 157.12998 | DG16: =DG6*1000/DG$4 -> 843.6736 | DJ16: COGS | DK16: =DK6*1000/DK$4 -> #DIV/0! | DL16: =DL6*1000/DL$4 -> 348.38335 | DM16: =DM6*1000/DM$4 -> 2283.6725 | DN16: =DN6*1000/DN$4 -> 171.993 | DO16: =DO6*1000/DO$4 -> #DIV/0! | DQ16: =DQ6*1000/DQ$4 -> 495.83 | DR16: =DR6*1000/DR$4 -> 358.41328 | DS16: =DS6*1000/DS$4 -> 913.83057 | DT16: =DT6*1000/DT$4 -> 158.23037 | DU16: =DU6*1000/DU$4 -> 843.6736 | DX16: COGS | DY16: =DY6*1000/DY$4 -> #DIV/0! | DZ16: =DZ6*1000/DZ$4 -> 370.76109 | EA16: =EA6*1000/EA$4 -> 1117.5714 | EB16: =EB6*1000/EB$4 -> 174.196 | EC16: =EC6*1000/EC$4 -> #DIV/0! | EE16: =EE6*1000/EE$4 -> 495.83 | EF16: =EF6*1000/EF$4 -> 359.35205 | EG16: =EG6*1000/EG$4 -> 921.4619 | EH16: =EH6*1000/EH$4 -> 159.45789 | EI16: =EI6*1000/EI$4 -> 843.6736 | EL16: COGS | EM16: =EM6*1000/EM$4 -> #DIV/0! | EN16: =EN6*1000/EN$4 -> 351.05186 | EO16: =EO6*1000/EO$4 -> 723.80364 | EP16: =EP6*1000/EP$4 -> 191.82 | EQ16: =EQ6*1000/EQ$4 -> #DIV/0! | ES16: =ES6*1000/ES$4 -> 495.83 | ET16: =ET6*1000/ET$4 -> 358.37677 | EU16: =EU6*1000/EU$4 -> 910.47454 | EV16: =EV6*1000/EV$4 -> 160.42347 | EW16: =EW6*1000/EW$4 -> 843.6736 | EZ16: COGS | FA16: =FA6*1000/FA$4 -> #DIV/0! | FB16: =FB6*1000/FB$4 -> 349.65606 | FC16: =FC6*1000/FC$4 -> 675.70864 | FD16: =FD6*1000/FD$4 -> 169.79 | FE16: =FE6*1000/FE$4 -> #DIV/0! | FG16: =FG6*1000/FG$4 -> 495.83 | FH16: =FH6*1000/FH$4 -> 357.59315 | FI16: =FI6*1000/FI$4 -> 886.98575 | FJ16: =FJ6*1000/FJ$4 -> 160.95092 | FK16: =FK6*1000/FK$4 -> 843.6736 | FN16: COGS | FO16: =FO6*1000/FO$4 -> #DIV/0! | FP16: =FP6*1000/FP$4 -> 349.02 | FQ16: =FQ6*1000/FQ$4 -> 1167.845 | FR16: =FR6*1000/FR$4 -> 191.82 | FS16: =FS6*1000/FS$4 -> #DIV/0! | FU16: =FU6*1000/FU$4 -> 495.83 | FV16: =FV6*1000/FV$4 -> 357.04472 | FW16: =FW6*1000/FW$4 -> 896.8454 | FX16: =FX6*1000/FX$4 -> 161.79628 | FY16: =FY6*1000/FY$4 -> 843.6736 | GB16: COGS | GC16: =GC6*1000/GC$4 -> #DIV/0! | GD16: =GD6*1000/GD$4 -> 347.98426 | GE16: =GE6*1000/GE$4 -> 1029.5043 | GF16: =GF6*1000/GF$4 -> 191.82 | GG16: =GG6*1000/GG$4 -> #DIV/0! | GI16: =GI6*1000/GI$4 -> 495.83 | GJ16: =GJ6*1000/GJ$4 -> 356.49557 | GK16: =GK6*1000/GK$4 -> 900.79887 | GL16: =GL6*1000/GL$4 -> 163.35532 | GM16: =GM6*1000/GM$4 -> 843.6736 | GP16: COGS | GQ16: =GQ6*1000/GQ$4 -> #DIV/0! | GR16: =GR6*1000/GR$4 -> 352.92051 | GS16: =GS6*1000/GS$4 -> 684.62147 | GT16: =GT6*1000/GT$4 -> 162.46392 | GU16: =GU6*1000/GU$4 -> #DIV/0! | GW16: =GW6*1000/GW$4 -> 495.83 | GX16: =GX6*1000/GX$4 -> 356.34687 | GY16: =GY6*1000/GY$4 -> 873.46372 | GZ16: =GZ6*1000/GZ$4 -> 163.24416 | HA16: =HA6*1000/HA$4 -> 843.6736 | HD16: COGS | HE16: =HE6*1000/HE$4 -> #DIV/0! | HF16: =HF6*1000/HF$4 -> 349.85954 | HG16: =HG6*1000/HG$4 -> 583.63281 | HH16: =HH6*1000/HH$4 -> 175.95152 | HI16: =HI6*1000/HI$4 -> #DIV/0! | HK16: =HK6*1000/HK$4 -> 495.83 | HL16: =HL6*1000/HL$4 -> 355.95822 | HM16: =HM6*1000/HM$4 -> 839.38515 | HN16: =HN6*1000/HN$4 -> 163.93756 | HO16: =HO6*1000/HO$4 -> 843.6736 | HR16: COGS | HS16: =HS6*1000/HS$4 -> #DIV/0! | HT16: =HT6*1000/HT$4 -> 348.8 | HU16: =HU6*1000/HU$4 -> 605.96387 | HV16: =HV6*1000/HV$4 -> 157.16188 | HW16: =HW6*1000/HW$4 -> #DIV/0! | HY16: =HY6*1000/HY$4 -> 495.83 | HZ16: =HZ6*1000/HZ$4 -> 355.66896 | IA16: =IA6*1000/IA$4 -> 817.83093 | IB16: =IB6*1000/IB$4 -> 163.60467 | IC16: =IC6*1000/IC$4 -> 843.6736 | IF16: COGS | IG16: =IG6*1000/IG$4 -> #DIV/0! | IH16: =IH6*1000/IH$4 -> 347.40804 | II16: =II6*1000/II$4 -> 723.0068 | IJ16: =IJ6*1000/IJ$4 -> 150.09643 | IK16: =IK6*1000/IK$4 -> #DIV/0! | IM16: =IM6*1000/IM$4 -> 495.83 | IN16: =IN6*1000/IN$4 -> 355.39426 | IO16: =IO6*1000/IO$4 -> 811.25896 | IP16: =IP6*1000/IP$4 -> 162.93143 | IQ16: =IQ6*1000/IQ$4 -> 843.6736 | IT16: COGS | IU16: =IU6*1000/IU$4 -> #DIV/0! | IV16: =IV6*1000/IV$4 -> 352.42062 | IW16: =IW6*1000/IW$4 -> 870.95611 | IX16: =IX6*1000/IX$4 -> 172.04333 | IY16: =IY6*1000/IY$4 -> #DIV/0! | JA16: =JA6*1000/JA$4 -> 495.83 | JB16: =JB6*1000/JB$4 -> 355.27671 | JC16: =JC6*1000/JC$4 -> 812.36807 | JD16: =JD6*1000/JD$4 -> 163.43287 | JE16: =JE6*1000/JE$4 -> 843.6736 | JH16: COGS | JI16: =JI6*1000/JI$4 -> 495.83 | JJ16: =JJ6*1000/JJ$4 -> 348.74286 | JK16: =JK6*1000/JK$4 -> 1399.244 | JL16: =JL6*1000/JL$4 -> 165.00883 | JM16: =JM6*1000/JM$4 -> #DIV/0! | JO16: =JO6*1000/JO$4 -> 495.83 | JP16: =JP6*1000/JP$4 -> 355.04042 | JQ16: =JQ6*1000/JQ$4 -> 820.24469 | JR16: =JR6*1000/JR$4 -> 163.50032 | JS16: =JS6*1000/JS$4 -> 843.6736 | JV16: COGS | JW16: =JW6*1000/JW$4 -> 493.78 | JX16: =JX6*1000/JX$4 -> 351.00926 | JY16: =JY6*1000/JY$4 -> 1025.5188 | JZ16: =JZ6*1000/JZ$4 -> 144.98053 | KA16: =KA6*1000/KA$4 -> #DIV/0! | KC16: =KC6*1000/KC$4 -> 495.8125 | KD16: =KD6*1000/KD$4 -> 354.88282 | KE16: =KE6*1000/KE$4 -> 829.20304 | KF16: =KF6*1000/KF$4 -> 162.52482 | KG16: =KG6*1000/KG$4 -> 843.6736 | KJ16: COGS | KK16: =KK6*1000/KK$4 -> 495.83 | KL16: =KL6*1000/KL$4 -> 351.55555 | KM16: =KM6*1000/KM$4 -> 932.35286 | KN16: =KN6*1000/KN$4 -> 164.29375 | KO16: =KO6*1000/KO$4 -> #DIV/0! | KQ16: =KQ6*1000/KQ$4 -> 495.81728 | KR16: =KR6*1000/KR$4 -> 354.68232 | KS16: =KS6*1000/KS$4 -> 831.0239 | KT16: =KT6*1000/KT$4 -> 162.57632 | KU16: =KU6*1000/KU$4 -> 843.6736 | KX16: COGS | KY16: =KY6*1000/KY$4 -> #DIV/0! | KZ16: =KZ6*1000/KZ$4 -> 331.89702 | LA16: =LA6*1000/LA$4 -> 850.30059 | LB16: =LB6*1000/LB$4 -> #DIV/0! | LC16: =LC6*1000/LC$4 -> #DIV/0! | LE16: =LE6*1000/LE$4 -> 495.81728 | LF16: =LF6*1000/LF$4 -> 353.7402 | LG16: =LG6*1000/LG$4 -> 831.81633 | LH16: =LH6*1000/LH$4 -> 162.57632 | LI16: =LI6*1000/LI$4 -> 843.6736
BF17: BOM cost | BG17: =BG8*1000/BG$4 -> 39.35 | BH17: =BH8*1000/BH$4 -> 32.923127 | BI17: =BI8*1000/BI$4 -> 64.470333 | BJ17: =BJ8*1000/BJ$4 -> 4.6 | BK17: =BK8*1000/BK$4 -> #DIV/0! | BM17: =BM8*1000/BM$4 -> 39.35 | BN17: =BN8*1000/BN$4 -> 33.313502 | BO17: =BO8*1000/BO$4 -> 94.980631 | BP17: =BP8*1000/BP$4 -> 4.6 | BQ17: =BQ8*1000/BQ$4 -> #DIV/0! | BT17: BOM cost | BU17: =BU8*1000/BU$4 -> #DIV/0! | BV17: =BV8*1000/BV$4 -> 34.4232 | BW17: =BW8*1000/BW$4 -> 83.42343 | BX17: =BX8*1000/BX$4 -> 4.6 | BY17: =BY8*1000/BY$4 -> #DIV/0! | CA17: =CA8*1000/CA$4 -> 39.35 | CB17: =CB8*1000/CB$4 -> 33.410479 | CC17: =CC8*1000/CC$4 -> 95.796518 | CD17: =CD8*1000/CD$4 -> 4.6 | CE17: =CE8*1000/CE$4 -> #DIV/0! | CH17: BOM cost | CI17: =CI7*1000/CI$4 -> #DIV/0! | CJ17: =CJ7*1000/CJ$4 -> 286.07388 | CK17: =CK7*1000/CK$4 -> 714.39905 | CL17: =CL7*1000/CL$4 -> 156.05608 | CM17: =CM7*1000/CM$4 -> 811.6236 | CO17: =CO7*1000/CO$4 -> 421.61 | CP17: =CP7*1000/CP$4 -> 295.13243 | CQ17: =CQ7*1000/CQ$4 -> 712.07854 | CR17: =CR7*1000/CR$4 -> 150.44344 | CS17: =CS7*1000/CS$4 -> 811.6236 | CV17: BOM cost | CW17: =CW7*1000/CW$4 -> #DIV/0! | CX17: =CX7*1000/CX$4 -> 286.432 | CY17: =CY7*1000/CY$4 -> 784.62793 | CZ17: =CZ7*1000/CZ$4 -> 152.365 | DA17: =DA7*1000/DA$4 -> #DIV/0! | DC17: =DC7*1000/DC$4 -> 421.61 | DD17: =DD7*1000/DD$4 -> 294.16865 | DE17: =DE7*1000/DE$4 -> 720.32815 | DF17: =DF7*1000/DF$4 -> 150.71998 | DG17: =DG7*1000/DG$4 -> 811.6236 | DJ17: BOM cost | DK17: =DK7*1000/DK$4 -> #DIV/0! | DL17: =DL7*1000/DL$4 -> 284.56335 | DM17: =DM7*1000/DM$4 -> 1439.3825 | DN17: =DN7*1000/DN$4 -> 165.583 | DO17: =DO7*1000/DO$4 -> #DIV/0! | DQ17: =DQ7*1000/DQ$4 -> 421.61 | DR17: =DR7*1000/DR$4 -> 293.43563 | DS17: =DS7*1000/DS$4 -> 736.31729 | DT17: =DT7*1000/DT$4 -> 151.82037 | DU17: =DU7*1000/DU$4 -> 811.6236 | DX17: BOM cost | DY17: =DY7*1000/DY$4 -> #DIV/0! | DZ17: =DZ7*1000/DZ$4 -> 305.0143 | EA17: =EA7*1000/EA$4 -> 853.24 | EB17: =EB7*1000/EB$4 -> 167.786 | EC17: =EC7*1000/EC$4 -> #DIV/0! | EE17: =EE7*1000/EE$4 -> 421.61 | EF17: =EF7*1000/EF$4 -> 294.31592 | EG17: =EG7*1000/EG$4 -> 740.69675 | EH17: =EH7*1000/EH$4 -> 153.04789 | EI17: =EI7*1000/EI$4 -> 811.6236 | EL17: BOM cost | EM17: =EM7*1000/EM$4 -> #DIV/0! | EN17: =EN7*1000/EN$4 -> 287.09769 | EO17: =EO7*1000/EO$4 -> 516.31455 | EP17: =EP7*1000/EP$4 -> 185.41 | EQ17: =EQ7*1000/EQ$4 -> #DIV/0! | ES17: =ES7*1000/ES$4 -> 421.61 | ET17: =ET7*1000/ET$4 -> 293.46778 | EU17: =EU7*1000/EU$4 -> 728.22387 | EV17: =EV7*1000/EV$4 -> 154.01347 | EW17: =EW7*1000/EW$4 -> 811.6236 | EZ17: BOM cost | FA17: =FA7*1000/FA$4 -> #DIV/0! | FB17: =FB7*1000/FB$4 -> 284.57099 | FC17: =FC7*1000/FC$4 -> 560.22045 | FD17: =FD7*1000/FD$4 -> 163.38 | FE17: =FE7*1000/FE$4 -> #DIV/0! | FG17: =FG7*1000/FG$4 -> 421.61 | FH17: =FH7*1000/FH$4 -> 292.66833 | FI17: =FI7*1000/FI$4 -> 711.4148 | FJ17: =FJ7*1000/FJ$4 -> 154.54092 | FK17: =FK7*1000/FK$4 -> 811.6236 | FN17: BOM cost | FO17: =FO7*1000/FO$4 -> #DIV/0! | FP17: =FP7*1000/FP$4 -> 285.2 | FQ17: =FQ7*1000/FQ$4 -> 829.1525 | FR17: =FR7*1000/FR$4 -> 185.41 | FS17: =FS7*1000/FS$4 -> #DIV/0! | FU17: =FU7*1000/FU$4 -> 421.61 | FV17: =FV7*1000/FV$4 -> 292.19058 | FW17: =FW7*1000/FW$4 -> 715.54802 | FX17: =FX7*1000/FX$4 -> 155.38628 | FY17: =FY7*1000/FY$4 -> 811.6236 | GB17: BOM cost | GC17: =GC7*1000/GC$4 -> #DIV/0! | GD17: =GD7*1000/GD$4 -> 284.16426 | GE17: =GE7*1000/GE$4 -> 718.15857 | GF17: =GF7*1000/GF$4 -> 185.41 | GG17: =GG7*1000/GG$4 -> #DIV/0! | GI17: =GI7*1000/GI$4 -> 421.61 | GJ17: =GJ7*1000/GJ$4 -> 291.70411 | GK17: =GK7*1000/GK$4 -> 715.62582 | GL17: =GL7*1000/GL$4 -> 156.94532 | GM17: =GM7*1000/GM$4 -> 811.6236 | GP17: BOM cost | GQ17: =GQ7*1000/GQ$4 -> #DIV/0! | GR17: =GR7*1000/GR$4 -> 288.63538 | GS17: =GS7*1000/GS$4 -> 460.40206 | GT17: =GT7*1000/GT$4 -> 156.05392 | GU17: =GU7*1000/GU$4 -> #DIV/0! | GW17: =GW7*1000/GW$4 -> 421.61 | GX17: =GX7*1000/GX$4 -> 291.57647 | GY17: =GY7*1000/GY$4 -> 683.35334 | GZ17: =GZ7*1000/GZ$4 -> 156.83416 | HA17: =HA7*1000/HA$4 -> 811.6236 | HD17: BOM cost | HE17: =HE7*1000/HE$4 -> #DIV/0! | HF17: =HF7*1000/HF$4 -> 285.55933 | HG17: =HG7*1000/HG$4 -> 464.54716 | HH17: =HH7*1000/HH$4 -> 169.54152 | HI17: =HI7*1000/HI$4 -> #DIV/0! | HK17: =HK7*1000/HK$4 -> 421.61 | HL17: =HL7*1000/HL$4 -> 291.21599 | HM17: =HM7*1000/HM$4 -> 657.62592 | HN17: =HN7*1000/HN$4 -> 157.52756 | HO17: =HO7*1000/HO$4 -> 811.6236 | HR17: BOM cost | HS17: =HS7*1000/HS$4 -> #DIV/0! | HT17: =HT7*1000/HT$4 -> 284.98 | HU17: =HU7*1000/HU$4 -> 489.77226 | HV17: =HV7*1000/HV$4 -> 150.75188 | HW17: =HW7*1000/HW$4 -> #DIV/0! | HY17: =HY7*1000/HY$4 -> 421.61 | HZ17: =HZ7*1000/HZ$4 -> 290.964 | IA17: =IA7*1000/IA$4 -> 642.12624 | IB17: =IB7*1000/IB$4 -> 157.19467 | IC17: =IC7*1000/IC$4 -> 811.6236 | IF17: BOM cost | IG17: =IG7*1000/IG$4 -> #DIV/0! | IH17: =IH7*1000/IH$4 -> 283.58804 | II17: =II7*1000/II$4 -> 585.7324 | IJ17: =IJ7*1000/IJ$4 -> 143.68643 | IK17: =IK7*1000/IK$4 -> #DIV/0! | IM17: =IM7*1000/IM$4 -> 421.61 | IN17: =IN7*1000/IN$4 -> 290.71873 | IO17: =IO7*1000/IO$4 -> 638.21776 | IP17: =IP7*1000/IP$4 -> 156.52143 | IQ17: =IQ7*1000/IQ$4 -> 811.6236 | IT17: BOM cost | IU17: =IU7*1000/IU$4 -> #DIV/0! | IV17: =IV7*1000/IV$4 -> 288.34441 | IW17: =IW7*1000/IW$4 -> 679.35159 | IX17: =IX7*1000/IX$4 -> 165.63333 | IY17: =IY7*1000/IY$4 -> #DIV/0! | JA17: =JA7*1000/JA$4 -> 421.61 | JB17: =JB7*1000/JB$4 -> 290.62487 | JC17: =JC7*1000/JC$4 -> 638.98198 | JD17: =JD7*1000/JD$4 -> 157.02287 | JE17: =JE7*1000/JE$4 -> 811.6236 | JH17: BOM cost | JI17: =JI7*1000/JI$4 -> 421.61 | JJ17: =JJ7*1000/JJ$4 -> 284.92286 | JK17: =JK7*1000/JK$4 -> 788.112 | JL17: =JL7*1000/JL$4 -> 158.59883 | JM17: =JM7*1000/JM$4 -> #DIV/0! | JO17: =JO7*1000/JO$4 -> 421.61 | JP17: =JP7*1000/JP$4 -> 290.41866 | JQ17: =JQ7*1000/JQ$4 -> 640.9835 | JR17: =JR7*1000/JR$4 -> 157.09032 | JS17: =JS7*1000/JS$4 -> 811.6236 | JV17: BOM cost | JW17: =JW7*1000/JW$4 -> 425.13 | JX17: =JX7*1000/JX$4 -> 286.90132 | JY17: =JY7*1000/JY$4 -> 811.43882 | JZ17: =JZ7*1000/JZ$4 -> 138.57053 | KA17: =KA7*1000/KA$4 -> #DIV/0! | KC17: =KC7*1000/KC$4 -> 421.64005 | KD17: =KD7*1000/KD$4 -> 290.28115 | KE17: =KE7*1000/KE$4 -> 648.42232 | KF17: =KF7*1000/KF$4 -> 156.11482 | KG17: =KG7*1000/KG$4 -> 811.6236 | KJ17: BOM cost | KK17: =KK7*1000/KK$4 -> 421.61 | KL17: =KL7*1000/KL$4 -> 287.38445 | KM17: =KM7*1000/KM$4 -> 759.01571 | KN17: =KN7*1000/KN$4 -> 157.88375 | KO17: =KO7*1000/KO$4 -> #DIV/0! | KQ17: =KQ7*1000/KQ$4 -> 421.63184 | KR17: =KR7*1000/KR$4 -> 290.10659 | KS17: =KS7*1000/KS$4 -> 650.37458 | KT17: =KT7*1000/KT$4 -> 156.16632 | KU17: =KU7*1000/KU$4 -> 811.6236 | KX17: BOM cost | KY17: =KY7*1000/KY$4 -> #DIV/0! | KZ17: =KZ7*1000/KZ$4 -> 269.53833 | LA17: =LA7*1000/LA$4 -> 717.91941 | LB17: =LB7*1000/LB$4 -> #DIV/0! | LC17: =LC7*1000/LC$4 -> #DIV/0! | LE17: =LE7*1000/LE$4 -> 421.63184 | LF17: =LF7*1000/LF$4 -> 289.25614 | LG17: =LG7*1000/LG$4 -> 653.15122 | LH17: =LH7*1000/LH$4 -> 156.16632 | LI17: =LI7*1000/LI$4 -> 811.6236
